Workbook

Sheet Invullen groen
A1: Invullen groen — Begrotingswijziging
A2: =A4 | L2: =IFERROR('Invullen groen'!L4,"")
A4: Begrotingswijziging 2026 | G4: Nummer wijziging:
A5: Omschrijving wijziging:
A6: Programma / afdeling: | G6: Corsanummer wijziging: | Q6: Controle budgettair neutrale categorieen
G7: Corsanummer raadsvoorstel:
Q8: Nummer wijziging:
A11: A. Mutaties in de inkomsten en uitgaven (raming van baten en lasten) | H11: -/- = baten
A13: Programma | B13: Nr.hoofd- taakveld | C13: Nr. taakveld | D13: Omschrijving taakveld | E13: Nr grootboek | F13: Econ. categorie | G13: Omschrijving grootboek | H13: Bgr.jaar | I13: MJR | J13: MJR | K13: MJR | L13: Bgr w | M13: Omschr. kostencat. | N13: Nr verbijz- | O13: Omschrijving | Q13: Lasten | R13: Baten
F14: nr | H14: 2026 | I14: 2027 | J14: 2028 | K14: 2029 | N14: ondering | O14: verbijzondering | Q14: 47100 / 47200 | R14: 87100 / 87201
Q15: 47201 / 47500 | R15: 87201 / 87500
A16: A. Uitgaven en inkomsten | Q16: → alleen directe lasten en baten; reserves/voorzieningen in sectie B
A17: =IFERROR(VLOOKUP(E17,Tabellen!A:F,4),0) | C17: =IFERROR(VLOOKUP(E17,Tabellen!A:F,5),0) | D17: =IFERROR(VLOOKUP(E17,Tabellen!A:F,6),0) | G17: =IFERROR(VLOOKUP(E17,Tabellen!A:F,2),0) | L17: =IF(E17>0,$H$4,0) | M17: =IFERROR(VLOOKUP(F17,Tabellen!H:I,2),0) | P17: =IF(E17>0,COUNTIF($E$17:E17,">0"),0) | Q17: =IF(OR(F17=47201,F17=47100,F17=47200,F17=47500),H17,0) | R17: =IF(OR(F17=87201,F17=87100,F17=87200,F17=87500),H17,0)
A18: =IFERROR(VLOOKUP(E18,Tabellen!A:F,4),0) | C18: =IFERROR(VLOOKUP(E18,Tabellen!A:F,5),0) | D18: =IFERROR(VLOOKUP(E18,Tabellen!A:F,6),0) | G18: =IFERROR(VLOOKUP(E18,Tabellen!A:F,2),0) | L18: =IF(E18>0,$H$4,0) | M18: =IFERROR(VLOOKUP(F18,Tabellen!H:I,2),0) | P18: =IF(E18>0,COUNTIF($E$17:E18,">0"),0) | Q18: =IF(OR(F18=47201,F18=47100,F18=47200,F18=47500),H18,0) | R18: =IF(OR(F18=87201,F18=87100,F18=87200,F18=87500),H18,0)
A19: =IFERROR(VLOOKUP(E19,Tabellen!A:F,4),0) | C19: =IFERROR(VLOOKUP(E19,Tabellen!A:F,5),0) | D19: =IFERROR(VLOOKUP(E19,Tabellen!A:F,6),0) | F19: =IFERROR(VLOOKUP(E19,Tabellen!A:H,8),0) | G19: =IFERROR(VLOOKUP(E19,Tabellen!A:F,2),0) | L19: =IF(E19>0,$H$4,0) | M19: =IFERROR(VLOOKUP(F19,Tabellen!H:I,2),0) | P19: =IF(E19>0,COUNTIF($E$17:E19,">0"),0) | Q19: =IF(OR(F19=47201,F19=47100,F19=47200,F19=47500),H19,0) | R19: =IF(OR(F19=87201,F19=87100,F19=87200,F19=87500),H19,0)
A20: =IFERROR(VLOOKUP(E20,Tabellen!A:F,4),0) | C20: =IFERROR(VLOOKUP(E20,Tabellen!A:F,5),0) | D20: =IFERROR(VLOOKUP(E20,Tabellen!A:F,6),0) | F20: =IFERROR(VLOOKUP(E20,Tabellen!A:H,8),0) | G20: =IFERROR(VLOOKUP(E20,Tabellen!A:F,2),0) | L20: =IF(E20>0,$H$4,0) | M20: =IFERROR(VLOOKUP(F20,Tabellen!H:I,2),0) | P20: =IF(E20>0,COUNTIF($E$17:E20,">0"),0) | Q20: =IF(OR(F20=47201,F20=47100,F20=47200,F20=47500),H20,0) | R20: =IF(OR(F20=87201,F20=87100,F20=87200,F20=87500),H20,0)
A21: =IFERROR(VLOOKUP(E21,Tabellen!A:F,4),0) | C21: =IFERROR(VLOOKUP(E21,Tabellen!A:F,5),0) | D21: =IFERROR(VLOOKUP(E21,Tabellen!A:F,6),0) | F21: =IFERROR(VLOOKUP(E21,Tabellen!A:H,8),0) | G21: =IFERROR(VLOOKUP(E21,Tabellen!A:F,2),0) | L21: =IF(E21>0,$H$4,0) | M21: =IFERROR(VLOOKUP(F21,Tabellen!H:I,2),0) | P21: =IF(E21>0,COUNTIF($E$17:E21,">0"),0) | Q21: =IF(OR(F21=47201,F21=47100,F21=47200,F21=47500),H21,0) | R21: =IF(OR(F21=87201,F21=87100,F21=87200,F21=87500),H21,0)
A22: =IFERROR(VLOOKUP(E22,Tabellen!A:F,4),0) | C22: =IFERROR(VLOOKUP(E22,Tabellen!A:F,5),0) | D22: =IFERROR(VLOOKUP(E22,Tabellen!A:F,6),0) | F22: =IFERROR(VLOOKUP(E22,Tabellen!A:H,8),0) | G22: =IFERROR(VLOOKUP(E22,Tabellen!A:F,2),0) | L22: =IF(E22>0,$H$4,0) | M22: =IFERROR(VLOOKUP(F22,Tabellen!H:I,2),0) | P22: =IF(E22>0,COUNTIF($E$17:E22,">0"),0) | Q22: =IF(OR(F22=47201,F22=47100,F22=47200,F22=47500),H22,0) | R22: =IF(OR(F22=87201,F22=87100,F22=87200,F22=87500),H22,0)
A23: =IFERROR(VLOOKUP(E23,Tabellen!A:F,4),0) | C23: =IFERROR(VLOOKUP(E23,Tabellen!A:F,5),0) | D23: =IFERROR(VLOOKUP(E23,Tabellen!A:F,6),0) | F23: =IFERROR(VLOOKUP(E23,Tabellen!A:H,8),0) | G23: =IFERROR(VLOOKUP(E23,Tabellen!A:F,2),0) | L23: =IF(E23>0,$H$4,0) | M23: =IFERROR(VLOOKUP(F23,Tabellen!H:I,2),0) | P23: =IF(E23>0,COUNTIF($E$17:E23,">0"),0) | Q23: =IF(OR(F23=47201,F23=47100,F23=47200,F23=47500),H23,0) | R23: =IF(OR(F23=87201,F23=87100,F23=87200,F23=87500),H23,0)
A24: =IFERROR(VLOOKUP(E24,Tabellen!A:F,4),0) | C24: =IFERROR(VLOOKUP(E24,Tabellen!A:F,5),0) | D24: =IFERROR(VLOOKUP(E24,Tabellen!A:F,6),0) | F24: =IFERROR(VLOOKUP(E24,Tabellen!A:H,8),0) | G24: =IFERROR(VLOOKUP(E24,Tabellen!A:F,2),0) | L24: =IF(E24>0,$H$4,0) | M24: =IFERROR(VLOOKUP(F24,Tabellen!H:I,2),0) | P24: =IF(E24>0,COUNTIF($E$17:E24,">0"),0) | Q24: =IF(OR(F24=47201,F24=47100,F24=47200,F24=47500),H24,0) | R24: =IF(OR(F24=87201,F24=87100,F24=87200,F24=87500),H24,0)
A25: =IFERROR(VLOOKUP(E25,Tabellen!A:F,4),0) | C25: =IFERROR(VLOOKUP(E25,Tabellen!A:F,5),0) | D25: =IFERROR(VLOOKUP(E25,Tabellen!A:F,6),0) | F25: =IFERROR(VLOOKUP(E25,Tabellen!A:H,8),0) | G25: =IFERROR(VLOOKUP(E25,Tabellen!A:F,2),0) | L25: =IF(E25>0,$H$4,0) | M25: =IFERROR(VLOOKUP(F25,Tabellen!H:I,2),0) | P25: =IF(E25>0,COUNTIF($E$17:E25,">0"),0) | Q25: =IF(OR(F25=47201,F25=47100,F25=47200,F25=47500),H25,0) | R25: =IF(OR(F25=87201,F25=87100,F25=87200,F25=87500),H25,0)
A26: =IFERROR(VLOOKUP(E26,Tabellen!A:F,4),0) | C26: =IFERROR(VLOOKUP(E26,Tabellen!A:F,5),0) | D26: =IFERROR(VLOOKUP(E26,Tabellen!A:F,6),0) | F26: =IFERROR(VLOOKUP(E26,Tabellen!A:H,8),0) | G26: =IFERROR(VLOOKUP(E26,Tabellen!A:F,2),0) | L26: =IF(E26>0,$H$4,0) | M26: =IFERROR(VLOOKUP(F26,Tabellen!H:I,2),0) | P26: =IF(E26>0,COUNTIF($E$17:E26,">0"),0) | Q26: =IF(OR(F26=47201,F26=47100,F26=47200,F26=47500),H26,0) | R26: =IF(OR(F26=87201,F26=87100,F26=87200,F26=87500),H26,0)
A27: =IFERROR(VLOOKUP(E27,Tabellen!A:F,4),0) | C27: =IFERROR(VLOOKUP(E27,Tabellen!A:F,5),0) | D27: =IFERROR(VLOOKUP(E27,Tabellen!A:F,6),0) | F27: =IFERROR(VLOOKUP(E27,Tabellen!A:H,8),0) | G27: =IFERROR(VLOOKUP(E27,Tabellen!A:F,2),0) | L27: =IF(E27>0,$H$4,0) | M27: =IFERROR(VLOOKUP(F27,Tabellen!H:I,2),0) | P27: =IF(E27>0,COUNTIF($E$17:E27,">0"),0) | Q27: =IF(OR(F27=47201,F27=47100,F27=47200,F27=47500),H27,0) | R27: =IF(OR(F27=87201,F27=87100,F27=87200,F27=87500),H27,0)
A28: =IFERROR(VLOOKUP(E28,Tabellen!A:F,4),0) | C28: =IFERROR(VLOOKUP(E28,Tabellen!A:F,5),0) | D28: =IFERROR(VLOOKUP(E28,Tabellen!A:F,6),0) | F28: =IFERROR(VLOOKUP(E28,Tabellen!A:H,8),0) | G28: =IFERROR(VLOOKUP(E28,Tabellen!A:F,2),0) | L28: =IF(E28>0,$H$4,0) | M28: =IFERROR(VLOOKUP(F28,Tabellen!H:I,2),0) | P28: =IF(E28>0,COUNTIF($E$17:E28,">0"),0) | Q28: =IF(OR(F28=47201,F28=47100,F28=47200,F28=47500),H28,0) | R28: =IF(OR(F28=87201,F28=87100,F28=87200,F28=87500),H28,0)
A29: =IFERROR(VLOOKUP(E29,Tabellen!A:F,4),0) | C29: =IFERROR(VLOOKUP(E29,Tabellen!A:F,5),0) | D29: =IFERROR(VLOOKUP(E29,Tabellen!A:F,6),0) | F29: =IFERROR(VLOOKUP(E29,Tabellen!A:H,8),0) | G29: =IFERROR(VLOOKUP(E29,Tabellen!A:F,2),0) | L29: =IF(E29>0,$H$4,0) | M29: =IFERROR(VLOOKUP(F29,Tabellen!H:I,2),0) | P29: =IF(E29>0,COUNTIF($E$17:E29,">0"),0) | Q29: =IF(OR(F29=47201,F29=47100,F29=47200,F29=47500),H29,0) | R29: =IF(OR(F29=87201,F29=87100,F29=87200,F29=87500),H29,0)
A30: =IFERROR(VLOOKUP(E30,Tabellen!A:F,4),0) | C30: =IFERROR(VLOOKUP(E30,Tabellen!A:F,5),0) | D30: =IFERROR(VLOOKUP(E30,Tabellen!A:F,6),0) | F30: =IFERROR(VLOOKUP(E30,Tabellen!A:H,8),0) | G30: =IFERROR(VLOOKUP(E30,Tabellen!A:F,2),0) | L30: =IF(E30>0,$H$4,0) | M30: =IFERROR(VLOOKUP(F30,Tabellen!H:I,2),0) | P30: =IF(E30>0,COUNTIF($E$17:E30,">0"),0) | Q30: =IF(OR(F30=47201,F30=47100,F30=47200,F30=47500),H30,0) | R30: =IF(OR(F30=87201,F30=87100,F30=87200,F30=87500),H30,0)
... A74: =IFERROR(VLOOKUP(E74,Tabellen!A:F,4),0) | C74: =IFERROR(VLOOKUP(E74,Tabellen!A:F,5),0) | D74: =IFERROR(VLOOKUP(E74,Tabellen!A:F,6),0) | F74: =IFERROR(VLOOKUP(E74,Tabellen!A:H,8),0) | G74: =IFERROR(VLOOKUP(E74,Tabellen!A:F,2),0) | L74: =IF(E74>0,$H$4,0) | M74: =IFERROR(VLOOKUP(F74,Tabellen!H:I,2),0) | P74: =IF(E74>0,COUNTIF($E$17:E74,">0"),0) | Q74: =IF(OR(F74=47201,F74=47100,F74=47200,F74=47500),H74,0) | R74: =IF(OR(F74=87201,F74=87100,F74=87200,F74=87500),H74,0)
A75: Saldo inkomsten en uitgaven | H75: =SUM(H17:H74) | I75: =SUM(I17:I74) | J75: =SUM(J17:J74) | K75: =SUM(K17:K74) | P75: =IF(E75>0,COUNTIF($E$17:E75,">0"),0) | Q75: =IF(OR(F75=47201,F75=47100,F75=47200,F75=47500),H75,0) | R75: =IF(OR(F75=87201,F75=87100,F75=87200,F75=87500),H75,0)
A112: Controle mutatie inkomsten en uitgaven (exploitatiemutaties -/- dekking = leeg) | H112: =IF(H75=0,"✓ Saldo = 0",TEXT(H75,"#.##0")) | I112: =IF(I75=0,"✓ Saldo = 0",TEXT(I75,"#.##0")) | J112: =IF(J75=0,"✓ Saldo = 0",TEXT(J75,"#.##0")) | K112: =IF(K75=0,"✓ Saldo = 0",TEXT(K75,"#.##0")) | P112: =IF(E112>0,COUNTIF($E$17:E112,">0"),0) | Q112: =IF(OR(L112=47201,L112=47100,L112=47200,L112=47500),H112,0) | R112: =IF(OR(L112=87201,L112=87100,L112=87200,L112=87500),H112,0)
P113: =IF(E113>0,COUNTIF($E$17:E113,">0"),0) | Q113: =IF(OR(L113=47201,L113=47100,L113=47200,L113=47500),H113,0) | R113: =IF(OR(L113=87201,L113=87100,L113=87200,L113=87500),H113,0)
P114: =IF(E114>0,COUNTIF($E$17:E114,">0"),0) | Q114: =IF(OR(L114=47201,L114=47100,L114=47200,L114=47500),H114,0) | R114: =IF(OR(L114=87201,L114=87100,L114=87200,L114=87500),H114,0)
A115: Mutaties in de balans (investerings- en financieringsstaat) | P115: =IF(E115>0,COUNTIF($E$17:E115,">0"),0) | Q115: =IF(OR(L115=47201,L115=47100,L115=47200,L115=47500),H115,0) | R115: =IF(OR(L115=87201,L115=87100,L115=87200,L115=87500),H115,0)
P116: =IF(E116>0,COUNTIF($E$17:E116,">0"),0) | Q116: =IF(OR(L116=47201,L116=47100,L116=47200,L116=47500),H116,0) | R116: =IF(OR(L116=87201,L116=87100,L116=87200,L116=87500),H116,0)
A117: Omschrijving balanspost | B117: nvt | C117: nvt | D117: nvt | G117: Omschrijving boeking | H117: Bgr.jaar | I117: MJR | J117: MJR | K117: MJR | L117: Kosten | M117: Omschrijving kostencategorie | N117: Nr ver- | O117: Omschrijving | P117: =IF(E117>0,COUNTIF($E$17:E117,">0"),0) | Q117: =IF(OR(L117=47201,L117=47100,L117=47200,L117=47500),H117,0) | R117: =IF(OR(L117=87201,L117=87100,L117=87200,L117=87500),H117,0)
H118: 2026 | I118: 2027 | J118: 2028 | K118: 2029 | L118: Cat | N118: bijzondering | O118: verbijzondering | P118: =IF(E118>0,COUNTIF($E$17:E118,">0"),0) | Q118: =IF(OR(L118=47201,L118=47100,L118=47200,L118=47500),H118,0) | R118: =IF(OR(L118=87201,L118=87100,L118=87200,L118=87500),H118,0)
P119: =IF(E119>0,COUNTIF($E$17:E119,">0"),0) | Q119: =IF(OR(L119=47201,L119=47100,L119=47200,L119=47500),H119,0) | R119: =IF(OR(L119=87201,L119=87100,L119=87200,L119=87500),H119,0)
A120: B. Investeringen | P120: =IF(E120>0,COUNTIF($E$17:E120,">0"),0) | Q120: =IF(OR(L120=47201,L120=47100,L120=47200,L120=47500),H120,0) | R120: =IF(OR(L120=87201,L120=87100,L120=87200,L120=87500),H120,0)
P121: =IF(E121>0,COUNTIF($E$17:E121,">0"),0) | Q121: =IF(OR(F121=47201,F121=47100,F121=47200,F121=47500),H121,0) | R121: =IF(OR(F121=87201,F121=87100,F121=87200,F121=87500),H121,0) | S121: =IF(E121>0,COUNTIF($E$121:E121,">0"),0)
A122: Activa | L122: =IF(E122>0,$H$4,0) | M122: =IFERROR(VLOOKUP(F122,Tabellen!H:I,2),0) | P122: =IF(E122>0,COUNTIF($E$17:E122,">0"),0) | Q122: =IF(OR(F122=47201,F122=47100,F122=47200,F122=47500),H122,0) | R122: =IF(OR(F122=87201,F122=87100,F122=87200,F122=87500),H122,0) | S122: =IF(E122>0,COUNTIF($E$121:E122,">0"),0)
L123: =IF(E123>0,$H$4,0) | M123: =IFERROR(VLOOKUP(F123,Tabellen!H:I,2),0) | P123: =IF(E123>0,COUNTIF($E$17:E123,">0"),0) | Q123: =IF(OR(F123=47201,F123=47100,F123=47200,F123=47500),H123,0) | R123: =IF(OR(F123=87201,F123=87100,F123=87200,F123=87500),H123,0) | S123: =IF(E123>0,COUNTIF($E$121:E123,">0"),0)
L124: =IF(E124>0,$H$4,0) | M124: =IFERROR(VLOOKUP(F124,Tabellen!H:I,2),0) | P124: =IF(E124>0,COUNTIF($E$17:E124,">0"),0) | Q124: =IF(OR(F124=47201,F124=47100,F124=47200,F124=47500),H124,0) | R124: =IF(OR(F124=87201,F124=87100,F124=87200,F124=87500),H124,0) | S124: =IF(E124>0,COUNTIF($E$121:E124,">0"),0)
L125: =IF(E125>0,$H$4,0) | M125: =IFERROR(VLOOKUP(F125,Tabellen!H:I,2),0) | P125: =IF(E125>0,COUNTIF($E$17:E125,">0"),0) | Q125: =IF(OR(F125=47201,F125=47100,F125=47200,F125=47500),H125,0) | R125: =IF(OR(F125=87201,F125=87100,F125=87200,F125=87500),H125,0) | S125: =IF(E125>0,COUNTIF($E$121:E125,">0"),0)
L126: =IF(E126>0,$H$4,0) | M126: =IFERROR(VLOOKUP(F126,Tabellen!H:I,2),0) | P126: =IF(E126>0,COUNTIF($E$17:E126,">0"),0) | Q126: =IF(OR(F126=47201,F126=47100,F126=47200,F126=47500),H126,0) | R126: =IF(OR(F126=87201,F126=87100,F126=87200,F126=87500),H126,0) | S126: =IF(E126>0,COUNTIF($E$121:E126,">0"),0)
L127: =IF(E127>0,$H$4,0) | M127: =IFERROR(VLOOKUP(F127,Tabellen!H:I,2),0) | P127: =IF(E127>0,COUNTIF($E$17:E127,">0"),0) | Q127: =IF(OR(F127=47201,F127=47100,F127=47200,F127=47500),H127,0) | R127: =IF(OR(F127=87201,F127=87100,F127=87200,F127=87500),H127,0) | S127: =IF(E127>0,COUNTIF($E$121:E127,">0"),0)
L128: =IF(E128>0,$H$4,0) | M128: =IFERROR(VLOOKUP(F128,Tabellen!H:I,2),0) | P128: =IF(E128>0,COUNTIF($E$17:E128,">0"),0) | Q128: =IF(OR(F128=47201,F128=47100,F128=47200,F128=47500),H128,0) | R128: =IF(OR(F128=87201,F128=87100,F128=87200,F128=87500),H128,0) | S128: =IF(E128>0,COUNTIF($E$121:E128,">0"),0)
L129: =IF(E129>0,$H$4,0) | M129: =IFERROR(VLOOKUP(F129,Tabellen!H:I,2),0) | P129: =IF(E129>0,COUNTIF($E$17:E129,">0"),0) | Q129: =IF(OR(F129=47201,F129=47100,F129=47200,F129=47500),H129,0) | R129: =IF(OR(F129=87201,F129=87100,F129=87200,F129=87500),H129,0) | S129: =IF(E129>0,COUNTIF($E$121:E129,">0"),0)
L130: =IF(E130>0,$H$4,0) | M130: =IFERROR(VLOOKUP(F130,Tabellen!H:I,2),0) | P130: =IF(E130>0,COUNTIF($E$17:E130,">0"),0) | Q130: =IF(OR(F130=47201,F130=47100,F130=47200,F130=47500),H130,0) | R130: =IF(OR(F130=87201,F130=87100,F130=87200,F130=87500),H130,0) | S130: =IF(E130>0,COUNTIF($E$121:E130,">0"),0)
L131: =IF(E131>0,$H$4,0) | M131: =IFERROR(VLOOKUP(F131,Tabellen!H:I,2),0) | P131: =IF(E131>0,COUNTIF($E$17:E131,">0"),0) | Q131: =IF(OR(F131=47201,F131=47100,F131=47200,F131=47500),H131,0) | R131: =IF(OR(F131=87201,F131=87100,F131=87200,F131=87500),H131,0) | S131: =IF(E131>0,COUNTIF($E$121:E131,">0"),0)
L132: =IF(E132>0,$H$4,0) | M132: =IFERROR(VLOOKUP(F132,Tabellen!H:I,2),0) | P132: =IF(E132>0,COUNTIF($E$17:E132,">0"),0) | Q132: =IF(OR(F132=47201,F132=47100,F132=47200,F132=47500),H132,0) | R132: =IF(OR(F132=87201,F132=87100,F132=87200,F132=87500),H132,0) | S132: =IF(E132>0,COUNTIF($E$121:E132,">0"),0)
L133: =IF(E133>0,$H$4,0) | M133: =IFERROR(VLOOKUP(F133,Tabellen!H:I,2),0) | P133: =IF(E133>0,COUNTIF($E$17:E133,">0"),0) | Q133: =IF(OR(F133=47201,F133=47100,F133=47200,F133=47500),H133,0) | R133: =IF(OR(F133=87201,F133=87100,F133=87200,F133=87500),H133,0) | S133: =IF(E133>0,COUNTIF($E$121:E133,">0"),0)
L134: =IF(E134>0,$H$4,0) | M134: =IFERROR(VLOOKUP(F134,Tabellen!H:I,2),0) | P134: =IF(E134>0,COUNTIF($E$17:E134,">0"),0) | Q134: =IF(OR(F134=47201,F134=47100,F134=47200,F134=47500),H134,0) | R134: =IF(OR(F134=87201,F134=87100,F134=87200,F134=87500),H134,0) | S134: =IF(E134>0,COUNTIF($E$121:E134,">0"),0)
... L167: =IF(E167>0,$H$4,0) | M167: =IFERROR(VLOOKUP(F167,Tabellen!H:I,2),0) | P167: =IF(E167>0,COUNTIF($E$17:E167,">0"),0) | Q167: =IF(OR(F167=47201,F167=47100,F167=47200,F167=47500),H167,0) | R167: =IF(OR(F167=87201,F167=87100,F167=87200,F167=87500),H167,0) | S167: =IF(E167>0,COUNTIF($E$121:E167,">0"),0)
A168: Saldo mutaties investeringen | H168: =SUM(H122:H167) | I168: =SUM(I122:I167) | J168: =SUM(J122:J167) | K168: =SUM(K122:K167) | P168: =IF(E168>0,COUNTIF($E$17:E168,">0"),0) | Q168: =IF(OR(F168=47201,F168=47100,F168=47200,F168=47500),H168,0) | R168: =IF(OR(F168=87201,F168=87100,F168=87200,F168=87500),H168,0) | S168: =IF(E168>0,COUNTIF($E$121:E168,">0"),0)
P169: =IF(E169>0,COUNTIF($E$17:E169,">0"),0) | Q169: =IF(OR(L169=47201,L169=47100,L169=47200,L169=47500),H169,0) | R169: =IF(OR(L169=87201,L169=87100,L169=87200,L169=87500),H169,0) | S169: =IF(E169>0,COUNTIF($E$121:E169,">0"),0)
A170: C. Reserves | P170: =IF(E170>0,COUNTIF($E$17:E170,">0"),0) | Q170: =IF(OR(L170=47201,L170=47100,L170=47200,L170=47500),H170,0) | R170: =IF(OR(L170=87201,L170=87100,L170=87200,L170=87500),H170,0) | S170: =IF(E170>0,COUNTIF($E$121:E170,">0"),0)
M171: =IFERROR(VLOOKUP(F172,Tabellen!H:I,2),0) | P171: =IF(E171>0,COUNTIF($E$17:E171,">0"),0) | Q171: =IF(OR(F172=47201,F172=47100,F172=47200,F172=47500),H172,0) | R171: =IF(OR(F172=87201,F172=87100,F172=87200,F172=87500),H172,0) | S171: =IF(E171>0,COUNTIF($E$121:E171,">0"),0)
A172: =IFERROR(VLOOKUP(E173,Tabellen!A:F,4),0) | C172: =IFERROR(VLOOKUP(E173,Tabellen!A:F,5),0) | D172: 0 | F172: =IFERROR(VLOOKUP(E173,Tabellen!A:H,8),0) | G172: =IFERROR(VLOOKUP(E173,Tabellen!A:F,2),0) | H172: 0 | I172: 0 | J172: 0 | K172: 0 | L172: =IF(E173>0,$H$4,0) | M172: =IFERROR(VLOOKUP(F173,Tabellen!H:I,2),0) | P172: =IF(E173>0,COUNTIF($E$17:E173,">0"),0) | Q172: =IF(OR(F173=47201,F173=47100,F173=47200,F173=47500),H173,0) | R172: =IF(OR(F173=87201,F173=87100,F173=87200,F173=87500),H173,0) | S172: =IF(E173>0,COUNTIF($E$121:E173,">0"),0)
A173: 0 | C173: 0 | D173: 0 | E173: 0 | F173: 0 | G173: 0 | H173: 0 | I173: 0 | J173: 0 | K173: 0 | L173: =IF(E174>0,$H$4,0) | M173: 0 | P173: =IF(E174>0,COUNTIF($E$17:E174,">0"),0) | Q173: =IF(OR(F174=47201,F174=47100,F174=47200,F174=47500),H174,0) | R173: =IF(OR(F174=87201,F174=87100,F174=87200,F174=87500),H174,0) | S173: =IF(E174>0,COUNTIF($E$121:E174,">0"),0)
A174: 0 | C174: 0 | D174: 0 | E174: 0 | F174: 0 | G174: 0 | H174: 0 | I174: 0 | J174: 0 | K174: 0 | L174: =IF(E175>0,$H$4,0) | M174: 0 | P174: =IF(E175>0,COUNTIF($E$17:E175,">0"),0) | Q174: =IF(OR(F175=47201,F175=47100,F175=47200,F175=47500),H175,0) | R174: =IF(OR(F175=87201,F175=87100,F175=87200,F175=87500),H175,0) | S174: =IF(E175>0,COUNTIF($E$121:E175,">0"),0)
A175: 0 | C175: 0 | D175: 0 | E175: 0 | F175: 0 | G175: 0 | H175: 0 | I175: 0 | J175: 0 | K175: 0 | L175: =IF(E176>0,$H$4,0) | M175: 0 | P175: =IF(E176>0,COUNTIF($E$17:E176,">0"),0) | Q175: =IF(OR(F176=47201,F176=47100,F176=47200,F176=47500),H176,0) | R175: =IF(OR(F176=87201,F176=87100,F176=87200,F176=87500),H176,0) | S175: =IF(E176>0,COUNTIF($E$121:E176,">0"),0)
A176: 0 | C176: 0 | D176: 0 | E176: 0 | F176: 0 | G176: 0 | H176: 0 | I176: 0 | J176: 0 | K176: 0 | L176: =IF(E177>0,$H$4,0) | M176: 0 | P176: =IF(E177>0,COUNTIF($E$17:E177,">0"),0) | Q176: =IF(OR(F177=47201,F177=47100,F177=47200,F177=47500),H177,0) | R176: =IF(OR(F177=87201,F177=87100,F177=87200,F177=87500),H177,0) | S176: =IF(E177>0,COUNTIF($E$121:E177,">0"),0)
A177: 0 | C177: 0 | D177: 0 | E177: 0 | F177: 0 | G177: 0 | H177: 0 | I177: 0 | J177: 0 | K177: 0 | L177: =IF(E178>0,$H$4,0) | M177: 0 | P177: =IF(E178>0,COUNTIF($E$17:E178,">0"),0) | Q177: =IF(OR(F178=47201,F178=47100,F178=47200,F178=47500),H178,0) | R177: =IF(OR(F178=87201,F178=87100,F178=87200,F178=87500),H178,0) | S177: =IF(E178>0,COUNTIF($E$121:E178,">0"),0)
A178: 0 | C178: 0 | D178: 0 | E178: 0 | F178: 0 | G178: 0 | H178: 0 | I178: 0 | J178: 0 | K178: 0 | L178: =IF(E179>0,$H$4,0) | M178: 0 | P178: =IF(E179>0,COUNTIF($E$17:E179,">0"),0) | Q178: =IF(OR(F179=47201,F179=47100,F179=47200,F179=47500),H179,0) | R178: =IF(OR(F179=87201,F179=87100,F179=87200,F179=87500),H179,0) | S178: =IF(E179>0,COUNTIF($E$121:E179,">0"),0)
A179: 0 | C179: 0 | D179: 0 | E179: 0 | F179: 0 | G179: 0 | H179: 0 | I179: 0 | J179: 0 | K179: 0 | L179: =IF(E180>0,$H$4,0) | M179: 0 | P179: =IF(E180>0,COUNTIF($E$17:E180,">0"),0) | Q179: =IF(OR(F180=47201,F180=47100,F180=47200,F180=47500),H180,0) | R179: =IF(OR(F180=87201,F180=87100,F180=87200,F180=87500),H180,0) | S179: =IF(E180>0,COUNTIF($E$121:E180,">0"),0)
A180: 0 | C180: 0 | D180: 0 | E180: 0 | F180: 0 | G180: 0 | H180: 0 | I180: 0 | J180: 0 | K180: 0 | L180: =IF(E181>0,$H$4,0) | M180: 0 | P180: =IF(E181>0,COUNTIF($E$17:E181,">0"),0) | Q180: =IF(OR(F181=47201,F181=47100,F181=47200,F181=47500),H181,0) | R180: =IF(OR(F181=87201,F181=87100,F181=87200,F181=87500),H181,0) | S180: =IF(E181>0,COUNTIF($E$121:E181,">0"),0)
A181: 0 | C181: 0 | D181: 0 | E181: 0 | F181: 0 | G181: 0 | H181: 0 | I181: 0 | J181: 0 | K181: 0 | L181: =IF(E182>0,$H$4,0) | M181: 0 | P181: =IF(E182>0,COUNTIF($E$17:E182,">0"),0) | Q181: =IF(OR(F182=47201,F182=47100,F182=47200,F182=47500),H182,0) | R181: =IF(OR(F182=87201,F182=87100,F182=87200,F182=87500),H182,0) | S181: =IF(E182>0,COUNTIF($E$121:E182,">0"),0)
A182: 0 | C182: 0 | D182: 0 | E182: 0 | F182: 0 | G182: =IFERROR(VLOOKUP(E183,Tabellen!A:F,2),0) | H182: 0 | I182: 0 | J182: 0 | K182: 0 | L182: =IF(E183>0,$H$4,0) | M182: 0 | P182: =IF(E183>0,COUNTIF($E$17:E183,">0"),0) | Q182: =IF(OR(F183=47201,F183=47100,F183=47200,F183=47500),H183,0) | R182: =IF(OR(F183=87201,F183=87100,F183=87200,F183=87500),H183,0) | S182: =IF(E183>0,COUNTIF($E$121:E183,">0"),0)
A183: 0 | C183: 0 | D183: 0 | E183: 0 | F183: 0 | G183: 0 | H183: 0 | I183: 0 | J183: 0 | K183: 0 | L183: =IF(E184>0,$H$4,0) | M183: 0 | P183: =IF(E184>0,COUNTIF($E$17:E184,">0"),0) | Q183: =IF(OR(F184=47201,F184=47100,F184=47200,F184=47500),H184,0) | R183: =IF(OR(F184=87201,F184=87100,F184=87200,F184=87500),H184,0) | S183: =IF(E184>0,COUNTIF($E$121:E184,">0"),0)
A184: 0 | C184: 0 | D184: 0 | E184: 0 | F184: 0 | G184: 0 | H184: 0 | I184: 0 | J184: 0 | K184: 0 | L184: =IF(E185>0,$H$4,0) | M184: 0 | P184: =IF(E185>0,COUNTIF($E$17:E185,">0"),0) | Q184: =IF(OR(F185=47201,F185=47100,F185=47200,F185=47500),H185,0) | R184: =IF(OR(F185=87201,F185=87100,F185=87200,F185=87500),H185,0) | S184: =IF(E185>0,COUNTIF($E$121:E185,">0"),0)
A185: 0 | C185: 0 | D185: 0 | E185: 0 | F185: 0 | G185: 0 | H185: 0 | I185: 0 | J185: 0 | K185: 0 | L185: =IF(E186>0,$H$4,0) | M185: 0 | P185: =IF(E186>0,COUNTIF($E$17:E186,">0"),0) | Q185: =IF(OR(F186=47201,F186=47100,F186=47200,F186=47500),H186,0) | R185: =IF(OR(F186=87201,F186=87100,F186=87200,F186=87500),H186,0) | S185: =IF(E186>0,COUNTIF($E$121:E186,">0"),0)
A186: 0 | C186: 0 | D186: 0 | E186: 0 | F186: 0 | G186: 0 | H186: 0 | I186: 0 | J186: 0 | K186: 0 | L186: =IF(E187>0,$H$4,0) | M186: 0 | P186: =IF(E187>0,COUNTIF($E$17:E187,">0"),0) | Q186: =IF(OR(F187=47201,F187=47100,F187=47200,F187=47500),H187,0) | R186: =IF(OR(F187=87201,F187=87100,F187=87200,F187=87500),H187,0) | S186: =IF(E187>0,COUNTIF($E$121:E187,">0"),0)
A187: 0 | C187: 0 | D187: 0 | E187: 0 | F187: 0 | G187: 0 | H187: 0 | I187: 0 | J187: 0 | K187: 0 | L187: =IF(E188>0,$H$4,0) | M187: 0 | P187: =IF(E188>0,COUNTIF($E$17:E188,">0"),0) | Q187: =IF(OR(F188=47201,F188=47100,F188=47200,F188=47500),H188,0) | R187: =IF(OR(F188=87201,F188=87100,F188=87200,F188=87500),H188,0) | S187: =IF(E188>0,COUNTIF($E$121:E188,">0"),0)
A188: 0 | C188: 0 | D188: 0 | E188: 0 | F188: 0 | G188: 0 | H188: 0 | I188: 0 | J188: 0 | K188: 0 | L188: =IF(E189>0,$H$4,0) | M188: 0 | P188: =IF(E189>0,COUNTIF($E$17:E189,">0"),0) | Q188: =IF(OR(F189=47201,F189=47100,F189=47200,F189=47500),H189,0) | R188: =IF(OR(F189=87201,F189=87100,F189=87200,F189=87500),H189,0) | S188: =IF(E189>0,COUNTIF($E$121:E189,">0"),0)
A189: 0 | C189: 0 | D189: 0 | E189: 0 | F189: 0 | G189: 0 | H189: 0 | I189: 0 | J189: 0 | K189: 0 | L189: =IF(E190>0,$H$4,0) | M189: 0 | P189: =IF(E190>0,COUNTIF($E$17:E190,">0"),0) | Q189: =IF(OR(F190=47201,F190=47100,F190=47200,F190=47500),H190,0) | R189: =IF(OR(F190=87201,F190=87100,F190=87200,F190=87500),H190,0) | S189: =IF(E190>0,COUNTIF($E$121:E190,">0"),0)
A190: 0 | C190: 0 | D190: 0 | E190: 0 | F190: 0 | G190: 0 | H190: 0 | I190: 0 | J190: 0 | K190: 0 | L190: =IF(E191>0,$H$4,0) | M190: 0 | P190: =IF(E191>0,COUNTIF($E$17:E191,">0"),0) | Q190: =IF(OR(F191=47201,F191=47100,F191=47200,F191=47500),H191,0) | R190: =IF(OR(F191=87201,F191=87100,F191=87200,F191=87500),H191,0) | S190: =IF(E191>0,COUNTIF($E$121:E191,">0"),0)
A191: 0 | C191: 0 | D191: 0 | E191: 0 | F191: 0 | G191: 0 | H191: 0 | I191: 0 | J191: 0 | K191: 0 | L191: =IF(E192>0,$H$4,0) | M191: 0 | P191: =IF(E192>0,COUNTIF($E$17:E192,">0"),0) | Q191: =IF(OR(F192=47201,F192=47100,F192=47200,F192=47500),H192,0) | R191: =IF(OR(F192=87201,F192=87100,F192=87200,F192=87500),H192,0) | S191: =IF(E192>0,COUNTIF($E$121:E192,">0"),0)
A192: 0 | C192: 0 | D192: 0 | E192: 0 | F192: 0 | G192: =G98 | H192: =H98 | I192: =I98 | J192: =J98 | K192: =K98 | L192: =IF(E193>0,$H$4,0) | M192: 0 | P192: =IF(E193>0,COUNTIF($E$17:E193,">0"),0) | Q192: =IF(OR(F193=47201,F193=47100,F193=47200,F193=47500),H193,0) | R192: =IF(OR(F193=87201,F193=87100,F193=87200,F193=87500),H193,0) | S192: =IF(E193>0,COUNTIF($E$121:E193,">0"),0)
A193: 0 | C193: 0 | D193: 0 | E193: 0 | F193: 0 | G193: =G99 | H193: =H99 | I193: =I99 | J193: =J99 | K193: =K99 | L193: =IF(E194>0,$H$4,0) | M193: 0 | P193: =IF(E194>0,COUNTIF($E$17:E194,">0"),0) | Q193: =IF(OR(F194=47201,F194=47100,F194=47200,F194=47500),H194,0) | R193: =IF(OR(F194=87201,F194=87100,F194=87200,F194=87500),H194,0) | S193: =IF(E194>0,COUNTIF($E$121:E194,">0"),0)
A194: 0 | C194: 0 | D194: 0 | E194: 0 | F194: 0 | G194: =G100 | H194: =H100 | I194: =I100 | J194: =J100 | K194: =K100 | L194: =IF(E195>0,$H$4,0) | M194: 0 | P194: =IF(E195>0,COUNTIF($E$17:E195,">0"),0) | Q194: =IF(OR(F195=47201,F195=47100,F195=47200,F195=47500),H195,0) | R194: =IF(OR(F195=87201,F195=87100,F195=87200,F195=87500),H195,0) | S194: =IF(E195>0,COUNTIF($E$121:E195,">0"),0)
A195: 0 | C195: 0 | D195: 0 | E195: 0 | F195: 0 | G195: =G101 | H195: =H101 | I195: =I101 | J195: =J101 | K195: =K101 | L195: =IF(E196>0,$H$4,0) | M195: 0 | P195: =IF(E196>0,COUNTIF($E$17:E196,">0"),0) | Q195: =IF(OR(F196=47201,F196=47100,F196=47200,F196=47500),H196,0) | R195: =IF(OR(F196=87201,F196=87100,F196=87200,F196=87500),H196,0) | S195: =IF(E196>0,COUNTIF($E$121:E196,">0"),0)
A196: 0 | C196: 0 | D196: 0 | E196: 0 | F196: 0 | G196: =G102 | H196: =H102 | I196: =I102 | J196: =J102 | K196: =K102 | L196: =IF(E197>0,$H$4,0) | M196: 0 | P196: =IF(E197>0,COUNTIF($E$17:E197,">0"),0) | Q196: =IF(OR(F197=47201,F197=47100,F197=47200,F197=47500),H197,0) | R196: =IF(OR(F197=87201,F197=87100,F197=87200,F197=87500),H197,0) | S196: =IF(E197>0,COUNTIF($E$121:E197,">0"),0)
A197: 0 | C197: 0 | D197: 0 | E197: 0 | F197: 0 | G197: =G103 | H197: =H103 | I197: =I103 | J197: =J103 | K197: =K103 | L197: =IF(E198>0,$H$4,0) | M197: 0 | P197: =IF(E198>0,COUNTIF($E$17:E198,">0"),0) | Q197: =IF(OR(F198=47201,F198=47100,F198=47200,F198=47500),H198,0) | R197: =IF(OR(F198=87201,F198=87100,F198=87200,F198=87500),H198,0) | S197: =IF(E198>0,COUNTIF($E$121:E198,">0"),0)
A198: 0 | C198: 0 | D198: 0 | E198: 0 | F198: 0 | G198: =G104 | H198: =H104 | I198: =I104 | J198: =J104 | K198: =K104 | L198: =IF(E199>0,$H$4,0) | M198: 0 | P198: =IF(E199>0,COUNTIF($E$17:E199,">0"),0) | Q198: =IF(OR(F199=47201,F199=47100,F199=47200,F199=47500),H199,0) | R198: =IF(OR(F199=87201,F199=87100,F199=87200,F199=87500),H199,0) | S198: =IF(E199>0,COUNTIF($E$121:E199,">0"),0)
A199: 0 | C199: 0 | D199: 0 | E199: 0 | F199: 0 | G199: =G105 | H199: =H105 | I199: =I105 | J199: =J105 | K199: =K105 | L199: =IF(E200>0,$H$4,0) | M199: 0 | P199: =IF(E200>0,COUNTIF($E$17:E200,">0"),0) | Q199: =IF(OR(F200=47201,F200=47100,F200=47200,F200=47500),H200,0) | R199: =IF(OR(F200=87201,F200=87100,F200=87200,F200=87500),H200,0) | S199: =IF(E200>0,COUNTIF($E$121:E200,">0"),0)
A200: 0 | C200: 0 | D200: 0 | E200: 0 | F200: 0 | G200: =G106 | H200: =H106 | I200: =I106 | J200: =J106 | K200: =K106 | L200: =IF(E201>0,$H$4,0) | M200: 0 | P200: =IF(E201>0,COUNTIF($E$17:E201,">0"),0) | Q200: =IF(OR(F201=47201,F201=47100,F201=47200,F201=47500),H201,0) | R200: =IF(OR(F201=87201,F201=87100,F201=87200,F201=87500),H201,0) | S200: =IF(E201>0,COUNTIF($E$121:E201,">0"),0)
A201: 0 | C201: 0 | D201: 0 | E201: 0 | F201: 0 | G201: =G107 | H201: =H107 | I201: =I107 | J201: =J107 | K201: =K107 | L201: =IF(E202>0,$H$4,0) | M201: 0 | P201: =IF(E202>0,COUNTIF($E$17:E202,">0"),0) | Q201: =IF(OR(F202=47201,F202=47100,F202=47200,F202=47500),H202,0) | R201: =IF(OR(F202=87201,F202=87100,F202=87200,F202=87500),H202,0) | S201: =IF(E202>0,COUNTIF($E$121:E202,">0"),0)
A202: 0 | C202: 0 | D202: 0 | E202: 0 | F202: 0 | G202: =IFERROR(VLOOKUP(E203,Tabellen!A:F,2),0) | H202: 0 | I202: 0 | J202: 0 | K202: 0 | L202: =IF(E203>0,$H$4,0) | M202: 0 | P202: =IF(E203>0,COUNTIF($E$17:E203,">0"),0) | Q202: =IF(OR(F203=47201,F203=47100,F203=47200,F203=47500),H203,0) | R202: =IF(OR(F203=87201,F203=87100,F203=87200,F203=87500),H203,0) | S202: =IF(E203>0,COUNTIF($E$121:E203,">0"),0)
A203: 0 | C203: 0 | D203: 0 | E203: 0 | F203: 0 | G203: 0 | H203: 0 | I203: 0 | J203: 0 | K203: 0 | L203: =IF(E204>0,$H$4,0) | M203: 0 | P203: =IF(E204>0,COUNTIF($E$17:E204,">0"),0) | Q203: =IF(OR(F204=47201,F204=47100,F204=47200,F204=47500),H204,0) | R203: =IF(OR(F204=87201,F204=87100,F204=87200,F204=87500),H204,0) | S203: =IF(E204>0,COUNTIF($E$121:E204,">0"),0)
L204: =IF(E205>0,$H$4,0) | M204: =IFERROR(VLOOKUP(F205,Tabellen!H:I,2),0) | P204: =IF(E205>0,COUNTIF($E$17:E205,">0"),0) | Q204: =IF(OR(F205=47201,F205=47100,F205=47200,F205=47500),H205,0) | R204: =IF(OR(F205=87201,F205=87100,F205=87200,F205=87500),H205,0) | S204: =IF(E205>0,COUNTIF($E$121:E205,">0"),0)
L205: =IF(E206>0,$H$4,0) | M205: =IFERROR(VLOOKUP(F206,Tabellen!H:I,2),0) | P205: =IF(E206>0,COUNTIF($E$17:E206,">0"),0) | Q205: =IF(OR(F206=47201,F206=47100,F206=47200,F206=47500),H206,0) | R205: =IF(OR(F206=87201,F206=87100,F206=87200,F206=87500),H206,0) | S205: =IF(E206>0,COUNTIF($E$121:E206,">0"),0)
L206: =IF(E207>0,$H$4,0) | M206: =IFERROR(VLOOKUP(F207,Tabellen!H:I,2),0) | P206: =IF(E207>0,COUNTIF($E$17:E207,">0"),0) | Q206: =IF(OR(F207=47201,F207=47100,F207=47200,F207=47500),H207,0) | R206: =IF(OR(F207=87201,F207=87100,F207=87200,F207=87500),H207,0) | S206: =IF(E207>0,COUNTIF($E$121:E207,">0"),0)
L207: =IF(E208>0,$H$4,0) | M207: =IFERROR(VLOOKUP(F208,Tabellen!H:I,2),0) | P207: =IF(E208>0,COUNTIF($E$17:E208,">0"),0) | Q207: =IF(OR(F208=47201,F208=47100,F208=47200,F208=47500),H208,0) | R207: =IF(OR(F208=87201,F208=87100,F208=87200,F208=87500),H208,0) | S207: =IF(E208>0,COUNTIF($E$121:E208,">0"),0)
L208: =IF(E209>0,$H$4,0) | M208: =IFERROR(VLOOKUP(F209,Tabellen!H:I,2),0) | P208: =IF(E209>0,COUNTIF($E$17:E209,">0"),0) | Q208: =IF(OR(F209=47201,F209=47100,F209=47200,F209=47500),H209,0) | R208: =IF(OR(F209=87201,F209=87100,F209=87200,F209=87500),H209,0) | S208: =IF(E209>0,COUNTIF($E$121:E209,">0"),0)
L209: =IF(E210>0,$H$4,0) | M209: =IFERROR(VLOOKUP(F210,Tabellen!H:I,2),0) | P209: =IF(E210>0,COUNTIF($E$17:E210,">0"),0) | Q209: =IF(OR(F210=47201,F210=47100,F210=47200,F210=47500),H210,0) | R209: =IF(OR(F210=87201,F210=87100,F210=87200,F210=87500),H210,0) | S209: =IF(E210>0,COUNTIF($E$121:E210,">0"),0)
L210: =IF(E211>0,$H$4,0) | M210: =IFERROR(VLOOKUP(F211,Tabellen!H:I,2),0) | P210: =IF(E211>0,COUNTIF($E$17:E211,">0"),0) | Q210: =IF(OR(F211=47201,F211=47100,F211=47200,F211=47500),H211,0) | R210: =IF(OR(F211=87201,F211=87100,F211=87200,F211=87500),H211,0) | S210: =IF(E211>0,COUNTIF($E$121:E211,">0"),0)
L211: =IF(E212>0,$H$4,0) | M211: =IFERROR(VLOOKUP(F212,Tabellen!H:I,2),0) | P211: =IF(E212>0,COUNTIF($E$17:E212,">0"),0) | Q211: =IF(OR(F212=47201,F212=47100,F212=47200,F212=47500),H212,0) | R211: =IF(OR(F212=87201,F212=87100,F212=87200,F212=87500),H212,0) | S211: =IF(E212>0,COUNTIF($E$121:E212,">0"),0)
L212: =IF(E213>0,$H$4,0) | M212: =IFERROR(VLOOKUP(F213,Tabellen!H:I,2),0) | P212: =IF(E213>0,COUNTIF($E$17:E213,">0"),0) | Q212: =IF(OR(F213=47201,F213=47100,F213=47200,F213=47500),H213,0) | R212: =IF(OR(F213=87201,F213=87100,F213=87200,F213=87500),H213,0) | S212: =IF(E213>0,COUNTIF($E$121:E213,">0"),0)
L213: =IF(E214>0,$H$4,0) | M213: =IFERROR(VLOOKUP(F214,Tabellen!H:I,2),0) | P213: =IF(E214>0,COUNTIF($E$17:E214,">0"),0) | Q213: =IF(OR(F214=47201,F214=47100,F214=47200,F214=47500),H214,0) | R213: =IF(OR(F214=87201,F214=87100,F214=87200,F214=87500),H214,0) | S213: =IF(E214>0,COUNTIF($E$121:E214,">0"),0)
L214: =IF(E215>0,$H$4,0) | M214: =IFERROR(VLOOKUP(F215,Tabellen!H:I,2),0) | P214: =IF(E215>0,COUNTIF($E$17:E215,">0"),0) | Q214: =IF(OR(F215=47201,F215=47100,F215=47200,F215=47500),H215,0) | R214: =IF(OR(F215=87201,F215=87100,F215=87200,F215=87500),H215,0) | S214: =IF(E215>0,COUNTIF($E$121:E215,">0"),0)
L215: =IF(E216>0,$H$4,0) | M215: =IFERROR(VLOOKUP(F216,Tabellen!H:I,2),0) | P215: =IF(E216>0,COUNTIF($E$17:E216,">0"),0) | Q215: =IF(OR(F216=47201,F216=47100,F216=47200,F216=47500),H216,0) | R215: =IF(OR(F216=87201,F216=87100,F216=87200,F216=87500),H216,0) | S215: =IF(E216>0,COUNTIF($E$121:E216,">0"),0)
...

Sheet Administratieve wijz en Coda
A1: Coda import — Begrotingswijziging | C1: ='Invullen groen'!H4 | K1: ='Invullen groen'!H4
F2: Baten en lasten: | G2: Baten en lasten: | H2: Baten en lasten: | I2: Baten en lasten:
F3: 2026 | G3: 2027 | H3: 2028 | I3: 2029
A4: Grootboek | B4: Econ.Categorie | C4: Verbijzondering | D4: Verdere verbijz. | E4: Omschrijving | F4: Bedrag: | G4: Bedrag: | H4: Bedrag: | I4: Bedrag:
A5: =IFERROR(IF($L5>0,INDEX('Invullen groen'!$E:$E,$L5),""),"") | B5: =IFERROR(IF($L5>0,IF(INDEX('Invullen groen'!$F:$F,$L5)>0,INDEX('Invullen groen'!$F:$F,$L5),""),""),"") | C5: =IFERROR(IF($L5>0,IF(INDEX('Invullen groen'!$N:$N,$L5)>0,INDEX('Invullen groen'!$N:$N,$L5),""),""),"") | E5: =IFERROR(IF(LEN(J5)<=36,J5,IFERROR(LEFT(J5,FIND(CHAR(1),SUBSTITUTE(LEFT(J5,36)," ",CHAR(1),LEN(LEFT(J5,36))-LEN(SUBSTITUTE(LEFT(J5,36)," ",""))))-1),LEFT(O5,36))),"") | F5: =IFERROR(IF($L5>0,IF(INDEX('Invullen groen'!$H:$H,$L5)=0,"",INT(INDEX('Invullen groen'!$H:$H,$L5))),""),"") | G5: =IFERROR(IF($L5>0,IF(INDEX('Invullen groen'!$I:$I,$L5)=0,"",INT(INDEX('Invullen groen'!$I:$I,$L5))),""),"") | H5: =IFERROR(IF($L5>0,IF(INDEX('Invullen groen'!$J:$J,$L5)=0,"",INT(INDEX('Invullen groen'!$J:$J,$L5))),""),"") | I5: =IFERROR(IF($L5>0,IF(INDEX('Invullen groen'!$K:$K,$L5)=0,"",INT(INDEX('Invullen groen'!$K:$K,$L5))),""),"") | J5: =IF($L5>0,IFERROR($K$1&" "&TRIM(SUBSTITUTE(SUBSTITUTE(SUBSTITUTE(SUBSTITUTE(SUBSTITUTE(SUBSTITUTE(SUBSTITUTE(SUBSTITUTE(SUBSTITUTE(SUBSTITUTE(SUBSTITUTE(SUBSTITUTE(LOWER(INDEX('Invullen groen'!$O:$O,$L5)),"2024",""),"2025",""),"2026",""),"2027",""),"2028",""),"2029",""),"taakveld ",""),"installaties","inst"),"ruwbouw","ruwb"),"afbouw","afb"),"bijstelling","bijst"),"investeringen","invest")),""),"") | L5: =IFERROR(MATCH(ROW()-4,'Invullen groen'!$P$17:$P$109,0)+16,0)
A6: =IFERROR(IF($L6>0,INDEX('Invullen groen'!$E:$E,$L6),""),"") | B6: =IFERROR(IF($L6>0,IF(INDEX('Invullen groen'!$F:$F,$L6)>0,INDEX('Invullen groen'!$F:$F,$L6),""),""),"") | C6: =IFERROR(IF($L6>0,IF(INDEX('Invullen groen'!$N:$N,$L6)>0,INDEX('Invullen groen'!$N:$N,$L6),""),""),"") | E6: =IFERROR(IF(LEN(J6)<=36,J6,IFERROR(LEFT(J6,FIND(CHAR(1),SUBSTITUTE(LEFT(J6,36)," ",CHAR(1),LEN(LEFT(J6,36))-LEN(SUBSTITUTE(LEFT(J6,36)," ",""))))-1),LEFT(J6,36))),"") | F6: =IFERROR(IF($L6>0,IF(INDEX('Invullen groen'!$H:$H,$L6)=0,"",INT(INDEX('Invullen groen'!$H:$H,$L6))),""),"") | G6: =IFERROR(IF($L6>0,IF(INDEX('Invullen groen'!$I:$I,$L6)=0,"",INT(INDEX('Invullen groen'!$I:$I,$L6))),""),"") | H6: =IFERROR(IF($L6>0,IF(INDEX('Invullen groen'!$J:$J,$L6)=0,"",INT(INDEX('Invullen groen'!$J:$J,$L6))),""),"") | I6: =IFERROR(IF($L6>0,IF(INDEX('Invullen groen'!$K:$K,$L6)=0,"",INT(INDEX('Invullen groen'!$K:$K,$L6))),""),"") | J6: =IF($L6>0,IFERROR($K$1&" "&TRIM(SUBSTITUTE(SUBSTITUTE(SUBSTITUTE(SUBSTITUTE(SUBSTITUTE(SUBSTITUTE(SUBSTITUTE(SUBSTITUTE(SUBSTITUTE(SUBSTITUTE(SUBSTITUTE(SUBSTITUTE(LOWER(INDEX('Invullen groen'!$O:$O,$L6)),"2024",""),"2025",""),"2026",""),"2027",""),"2028",""),"2029",""),"taakveld ",""),"installaties","inst"),"ruwbouw","ruwb"),"afbouw","afb"),"bijstelling","bijst"),"investeringen","invest")),""),"") | L6: =IFERROR(MATCH(ROW()-4,'Invullen groen'!$P$17:$P$109,0)+16,0)
A7: =IFERROR(IF($L7>0,INDEX('Invullen groen'!$E:$E,$L7),""),"") | B7: =IFERROR(IF($L7>0,IF(INDEX('Invullen groen'!$F:$F,$L7)>0,INDEX('Invullen groen'!$F:$F,$L7),""),""),"") | C7: =IFERROR(IF($L7>0,IF(INDEX('Invullen groen'!$N:$N,$L7)>0,INDEX('Invullen groen'!$N:$N,$L7),""),""),"") | E7: =IFERROR(IF(LEN(J7)<=36,J7,IFERROR(LEFT(J7,FIND(CHAR(1),SUBSTITUTE(LEFT(J7,36)," ",CHAR(1),LEN(LEFT(J7,36))-LEN(SUBSTITUTE(LEFT(J7,36)," ",""))))-1),LEFT(J7,36))),"") | F7: =IFERROR(IF($L7>0,IF(INDEX('Invullen groen'!$H:$H,$L7)=0,"",INT(INDEX('Invullen groen'!$H:$H,$L7))),""),"") | G7: =IFERROR(IF($L7>0,IF(INDEX('Invullen groen'!$I:$I,$L7)=0,"",INT(INDEX('Invullen groen'!$I:$I,$L7))),""),"") | H7: =IFERROR(IF($L7>0,IF(INDEX('Invullen groen'!$J:$J,$L7)=0,"",INT(INDEX('Invullen groen'!$J:$J,$L7))),""),"") | I7: =IFERROR(IF($L7>0,IF(INDEX('Invullen groen'!$K:$K,$L7)=0,"",INT(INDEX('Invullen groen'!$K:$K,$L7))),""),"") | J7: =IF($L7>0,IFERROR($K$1&" "&TRIM(SUBSTITUTE(SUBSTITUTE(SUBSTITUTE(SUBSTITUTE(SUBSTITUTE(SUBSTITUTE(SUBSTITUTE(SUBSTITUTE(SUBSTITUTE(SUBSTITUTE(SUBSTITUTE(SUBSTITUTE(LOWER(INDEX('Invullen groen'!$O:$O,$L7)),"2024",""),"2025",""),"2026",""),"2027",""),"2028",""),"2029",""),"taakveld ",""),"installaties","inst"),"ruwbouw","ruwb"),"afbouw","afb"),"bijstelling","bijst"),"investeringen","invest")),""),"") | L7: =IFERROR(MATCH(ROW()-4,'Invullen groen'!$P$17:$P$109,0)+16,0)
A8: =IFERROR(IF($L8>0,INDEX('Invullen groen'!$E:$E,$L8),""),"") | B8: =IFERROR(IF($L8>0,IF(INDEX('Invullen groen'!$F:$F,$L8)>0,INDEX('Invullen groen'!$F:$F,$L8),""),""),"") | C8: =IFERROR(IF($L8>0,IF(INDEX('Invullen groen'!$N:$N,$L8)>0,INDEX('Invullen groen'!$N:$N,$L8),""),""),"") | E8: =IFERROR(IF(LEN(J8)<=36,J8,IFERROR(LEFT(J8,FIND(CHAR(1),SUBSTITUTE(LEFT(J8,36)," ",CHAR(1),LEN(LEFT(J8,36))-LEN(SUBSTITUTE(LEFT(J8,36)," ",""))))-1),LEFT(J8,36))),"") | F8: =IFERROR(IF($L8>0,IF(INDEX('Invullen groen'!$H:$H,$L8)=0,"",INT(INDEX('Invullen groen'!$H:$H,$L8))),""),"") | G8: =IFERROR(IF($L8>0,IF(INDEX('Invullen groen'!$I:$I,$L8)=0,"",INT(INDEX('Invullen groen'!$I:$I,$L8))),""),"") | H8: =IFERROR(IF($L8>0,IF(INDEX('Invullen groen'!$J:$J,$L8)=0,"",INT(INDEX('Invullen groen'!$J:$J,$L8))),""),"") | I8: =IFERROR(IF($L8>0,IF(INDEX('Invullen groen'!$K:$K,$L8)=0,"",INT(INDEX('Invullen groen'!$K:$K,$L8))),""),"") | J8: =IF($L8>0,IFERROR($K$1&" "&TRIM(SUBSTITUTE(SUBSTITUTE(SUBSTITUTE(SUBSTITUTE(SUBSTITUTE(SUBSTITUTE(SUBSTITUTE(SUBSTITUTE(SUBSTITUTE(SUBSTITUTE(SUBSTITUTE(SUBSTITUTE(LOWER(INDEX('Invullen groen'!$O:$O,$L8)),"2024",""),"2025",""),"2026",""),"2027",""),"2028",""),"2029",""),"taakveld ",""),"installaties","inst"),"ruwbouw","ruwb"),"afbouw","afb"),"bijstelling","bijst"),"investeringen","invest")),""),"") | L8: =IFERROR(MATCH(ROW()-4,'Invullen groen'!$P$17:$P$109,0)+16,0)
A9: =IFERROR(IF($L9>0,INDEX('Invullen groen'!$E:$E,$L9),""),"") | B9: =IFERROR(IF($L9>0,IF(INDEX('Invullen groen'!$F:$F,$L9)>0,INDEX('Invullen groen'!$F:$F,$L9),""),""),"") | C9: =IFERROR(IF($L9>0,IF(INDEX('Invullen groen'!$N:$N,$L9)>0,INDEX('Invullen groen'!$N:$N,$L9),""),""),"") | E9: =IFERROR(IF(LEN(J9)<=36,J9,IFERROR(LEFT(J9,FIND(CHAR(1),SUBSTITUTE(LEFT(J9,36)," ",CHAR(1),LEN(LEFT(J9,36))-LEN(SUBSTITUTE(LEFT(J9,36)," ",""))))-1),LEFT(J9,36))),"") | F9: =IFERROR(IF($L9>0,IF(INDEX('Invullen groen'!$H:$H,$L9)=0,"",INT(INDEX('Invullen groen'!$H:$H,$L9))),""),"") | G9: =IFERROR(IF($L9>0,IF(INDEX('Invullen groen'!$I:$I,$L9)=0,"",INT(INDEX('Invullen groen'!$I:$I,$L9))),""),"") | H9: =IFERROR(IF($L9>0,IF(INDEX('Invullen groen'!$J:$J,$L9)=0,"",INT(INDEX('Invullen groen'!$J:$J,$L9))),""),"") | I9: =IFERROR(IF($L9>0,IF(INDEX('Invullen groen'!$K:$K,$L9)=0,"",INT(INDEX('Invullen groen'!$K:$K,$L9))),""),"") | J9: =IF($L9>0,IFERROR($K$1&" "&TRIM(SUBSTITUTE(SUBSTITUTE(SUBSTITUTE(SUBSTITUTE(SUBSTITUTE(SUBSTITUTE(SUBSTITUTE(SUBSTITUTE(SUBSTITUTE(SUBSTITUTE(SUBSTITUTE(SUBSTITUTE(LOWER(INDEX('Invullen groen'!$O:$O,$L9)),"2024",""),"2025",""),"2026",""),"2027",""),"2028",""),"2029",""),"taakveld ",""),"installaties","inst"),"ruwbouw","ruwb"),"afbouw","afb"),"bijstelling","bijst"),"investeringen","invest")),""),"") | L9: =IFERROR(MATCH(ROW()-4,'Invullen groen'!$P$17:$P$109,0)+16,0)
A10: =IFERROR(IF($L10>0,INDEX('Invullen groen'!$E:$E,$L10),""),"") | B10: =IFERROR(IF($L10>0,IF(INDEX('Invullen groen'!$F:$F,$L10)>0,INDEX('Invullen groen'!$F:$F,$L10),""),""),"") | C10: =IFERROR(IF($L10>0,IF(INDEX('Invullen groen'!$N:$N,$L10)>0,INDEX('Invullen groen'!$N:$N,$L10),""),""),"") | E10: =IFERROR(IF(LEN(J10)<=36,J10,IFERROR(LEFT(J10,FIND(CHAR(1),SUBSTITUTE(LEFT(J10,36)," ",CHAR(1),LEN(LEFT(J10,36))-LEN(SUBSTITUTE(LEFT(J10,36)," ",""))))-1),LEFT(J10,36))),"") | F10: =IFERROR(IF($L10>0,IF(INDEX('Invullen groen'!$H:$H,$L10)=0,"",INT(INDEX('Invullen groen'!$H:$H,$L10))),""),"") | G10: =IFERROR(IF($L10>0,IF(INDEX('Invullen groen'!$I:$I,$L10)=0,"",INT(INDEX('Invullen groen'!$I:$I,$L10))),""),"") | H10: =IFERROR(IF($L10>0,IF(INDEX('Invullen groen'!$J:$J,$L10)=0,"",INT(INDEX('Invullen groen'!$J:$J,$L10))),""),"") | I10: =IFERROR(IF($L10>0,IF(INDEX('Invullen groen'!$K:$K,$L10)=0,"",INT(INDEX('Invullen groen'!$K:$K,$L10))),""),"") | J10: =IF($L10>0,IFERROR($K$1&" "&TRIM(SUBSTITUTE(SUBSTITUTE(SUBSTITUTE(SUBSTITUTE(SUBSTITUTE(SUBSTITUTE(SUBSTITUTE(SUBSTITUTE(SUBSTITUTE(SUBSTITUTE(SUBSTITUTE(SUBSTITUTE(LOWER(INDEX('Invullen groen'!$O:$O,$L10)),"2024",""),"2025",""),"2026",""),"2027",""),"2028",""),"2029",""),"taakveld ",""),"installaties","inst"),"ruwbouw","ruwb"),"afbouw","afb"),"bijstelling","bijst"),"investeringen","invest")),""),"") | L10: =IFERROR(MATCH(ROW()-4,'Invullen groen'!$P$17:$P$109,0)+16,0)
A11: =IFERROR(IF($L11>0,INDEX('Invullen groen'!$E:$E,$L11),""),"") | B11: =IFERROR(IF($L11>0,IF(INDEX('Invullen groen'!$F:$F,$L11)>0,INDEX('Invullen groen'!$F:$F,$L11),""),""),"") | C11: =IFERROR(IF($L11>0,IF(INDEX('Invullen groen'!$N:$N,$L11)>0,INDEX('Invullen groen'!$N:$N,$L11),""),""),"") | E11: =IFERROR(IF(LEN(J11)<=36,J11,IFERROR(LEFT(J11,FIND(CHAR(1),SUBSTITUTE(LEFT(J11,36)," ",CHAR(1),LEN(LEFT(J11,36))-LEN(SUBSTITUTE(LEFT(J11,36)," ",""))))-1),LEFT(J11,36))),"") | F11: =IFERROR(IF($L11>0,IF(INDEX('Invullen groen'!$H:$H,$L11)=0,"",INT(INDEX('Invullen groen'!$H:$H,$L11))),""),"") | G11: =IFERROR(IF($L11>0,IF(INDEX('Invullen groen'!$I:$I,$L11)=0,"",INT(INDEX('Invullen groen'!$I:$I,$L11))),""),"") | H11: =IFERROR(IF($L11>0,IF(INDEX('Invullen groen'!$J:$J,$L11)=0,"",INT(INDEX('Invullen groen'!$J:$J,$L11))),""),"") | I11: =IFERROR(IF($L11>0,IF(INDEX('Invullen groen'!$K:$K,$L11)=0,"",INT(INDEX('Invullen groen'!$K:$K,$L11))),""),"") | J11: =IF($L11>0,IFERROR($K$1&" "&TRIM(SUBSTITUTE(SUBSTITUTE(SUBSTITUTE(SUBSTITUTE(SUBSTITUTE(SUBSTITUTE(SUBSTITUTE(SUBSTITUTE(SUBSTITUTE(SUBSTITUTE(SUBSTITUTE(SUBSTITUTE(LOWER(INDEX('Invullen groen'!$O:$O,$L11)),"2024",""),"2025",""),"2026",""),"2027",""),"2028",""),"2029",""),"taakveld ",""),"installaties","inst"),"ruwbouw","ruwb"),"afbouw","afb"),"bijstelling","bijst"),"investeringen","invest")),""),"") | L11: =IFERROR(MATCH(ROW()-4,'Invullen groen'!$P$17:$P$109,0)+16,0)
A12: =IFERROR(IF($L12>0,INDEX('Invullen groen'!$E:$E,$L12),""),"") | B12: =IFERROR(IF($L12>0,IF(INDEX('Invullen groen'!$F:$F,$L12)>0,INDEX('Invullen groen'!$F:$F,$L12),""),""),"") | C12: =IFERROR(IF($L12>0,IF(INDEX('Invullen groen'!$N:$N,$L12)>0,INDEX('Invullen groen'!$N:$N,$L12),""),""),"") | E12: =IFERROR(IF(LEN(J12)<=36,J12,IFERROR(LEFT(J12,FIND(CHAR(1),SUBSTITUTE(LEFT(J12,36)," ",CHAR(1),LEN(LEFT(J12,36))-LEN(SUBSTITUTE(LEFT(J12,36)," ",""))))-1),LEFT(J12,36))),"") | F12: =IFERROR(IF($L12>0,IF(INDEX('Invullen groen'!$H:$H,$L12)=0,"",INT(INDEX('Invullen groen'!$H:$H,$L12))),""),"") | G12: =IFERROR(IF($L12>0,IF(INDEX('Invullen groen'!$I:$I,$L12)=0,"",INT(INDEX('Invullen groen'!$I:$I,$L12))),""),"") | H12: =IFERROR(IF($L12>0,IF(INDEX('Invullen groen'!$J:$J,$L12)=0,"",INT(INDEX('Invullen groen'!$J:$J,$L12))),""),"") | I12: =IFERROR(IF($L12>0,IF(INDEX('Invullen groen'!$K:$K,$L12)=0,"",INT(INDEX('Invullen groen'!$K:$K,$L12))),""),"") | J12: =IF($L12>0,IFERROR($K$1&" "&TRIM(SUBSTITUTE(SUBSTITUTE(SUBSTITUTE(SUBSTITUTE(SUBSTITUTE(SUBSTITUTE(SUBSTITUTE(SUBSTITUTE(SUBSTITUTE(SUBSTITUTE(SUBSTITUTE(SUBSTITUTE(LOWER(INDEX('Invullen groen'!$O:$O,$L12)),"2024",""),"2025",""),"2026",""),"2027",""),"2028",""),"2029",""),"taakveld ",""),"installaties","inst"),"ruwbouw","ruwb"),"afbouw","afb"),"bijstelling","bijst"),"investeringen","invest")),""),"") | L12: =IFERROR(MATCH(ROW()-4,'Invullen groen'!$P$17:$P$109,0)+16,0)
A13: =IFERROR(IF($L13>0,INDEX('Invullen groen'!$E:$E,$L13),""),"") | B13: =IFERROR(IF($L13>0,IF(INDEX('Invullen groen'!$F:$F,$L13)>0,INDEX('Invullen groen'!$F:$F,$L13),""),""),"") | C13: =IFERROR(IF($L13>0,IF(INDEX('Invullen groen'!$N:$N,$L13)>0,INDEX('Invullen groen'!$N:$N,$L13),""),""),"") | E13: =IFERROR(IF(LEN(J13)<=36,J13,IFERROR(LEFT(J13,FIND(CHAR(1),SUBSTITUTE(LEFT(J13,36)," ",CHAR(1),LEN(LEFT(J13,36))-LEN(SUBSTITUTE(LEFT(J13,36)," ",""))))-1),LEFT(J13,36))),"") | F13: =IFERROR(IF($L13>0,IF(INDEX('Invullen groen'!$H:$H,$L13)=0,"",INT(INDEX('Invullen groen'!$H:$H,$L13))),""),"") | G13: =IFERROR(IF($L13>0,IF(INDEX('Invullen groen'!$I:$I,$L13)=0,"",INT(INDEX('Invullen groen'!$I:$I,$L13))),""),"") | H13: =IFERROR(IF($L13>0,IF(INDEX('Invullen groen'!$J:$J,$L13)=0,"",INT(INDEX('Invullen groen'!$J:$J,$L13))),""),"") | I13: =IFERROR(IF($L13>0,IF(INDEX('Invullen groen'!$K:$K,$L13)=0,"",INT(INDEX('Invullen groen'!$K:$K,$L13))),""),"") | J13: =IF($L13>0,IFERROR($K$1&" "&TRIM(SUBSTITUTE(SUBSTITUTE(SUBSTITUTE(SUBSTITUTE(SUBSTITUTE(SUBSTITUTE(SUBSTITUTE(SUBSTITUTE(SUBSTITUTE(SUBSTITUTE(SUBSTITUTE(SUBSTITUTE(LOWER(INDEX('Invullen groen'!$O:$O,$L13)),"2024",""),"2025",""),"2026",""),"2027",""),"2028",""),"2029",""),"taakveld ",""),"installaties","inst"),"ruwbouw","ruwb"),"afbouw","afb"),"bijstelling","bijst"),"investeringen","invest")),""),"") | L13: =IFERROR(MATCH(ROW()-4,'Invullen groen'!$P$17:$P$109,0)+16,0)
A14: =IFERROR(IF($L14>0,INDEX('Invullen groen'!$E:$E,$L14),""),"") | B14: =IFERROR(IF($L14>0,IF(INDEX('Invullen groen'!$F:$F,$L14)>0,INDEX('Invullen groen'!$F:$F,$L14),""),""),"") | C14: =IFERROR(IF($L14>0,IF(INDEX('Invullen groen'!$N:$N,$L14)>0,INDEX('Invullen groen'!$N:$N,$L14),""),""),"") | E14: =IFERROR(IF(LEN(J14)<=36,J14,IFERROR(LEFT(J14,FIND(CHAR(1),SUBSTITUTE(LEFT(J14,36)," ",CHAR(1),LEN(LEFT(J14,36))-LEN(SUBSTITUTE(LEFT(J14,36)," ",""))))-1),LEFT(J14,36))),"") | F14: =IFERROR(IF($L14>0,IF(INDEX('Invullen groen'!$H:$H,$L14)=0,"",INT(INDEX('Invullen groen'!$H:$H,$L14))),""),"") | G14: =IFERROR(IF($L14>0,IF(INDEX('Invullen groen'!$I:$I,$L14)=0,"",INT(INDEX('Invullen groen'!$I:$I,$L14))),""),"") | H14: =IFERROR(IF($L14>0,IF(INDEX('Invullen groen'!$J:$J,$L14)=0,"",INT(INDEX('Invullen groen'!$J:$J,$L14))),""),"") | I14: =IFERROR(IF($L14>0,IF(INDEX('Invullen groen'!$K:$K,$L14)=0,"",INT(INDEX('Invullen groen'!$K:$K,$L14))),""),"") | J14: =IF($L14>0,IFERROR($K$1&" "&TRIM(SUBSTITUTE(SUBSTITUTE(SUBSTITUTE(SUBSTITUTE(SUBSTITUTE(SUBSTITUTE(SUBSTITUTE(SUBSTITUTE(SUBSTITUTE(SUBSTITUTE(SUBSTITUTE(SUBSTITUTE(LOWER(INDEX('Invullen groen'!$O:$O,$L14)),"2024",""),"2025",""),"2026",""),"2027",""),"2028",""),"2029",""),"taakveld ",""),"installaties","inst"),"ruwbouw","ruwb"),"afbouw","afb"),"bijstelling","bijst"),"investeringen","invest")),""),"") | L14: =IFERROR(MATCH(ROW()-4,'Invullen groen'!$P$17:$P$109,0)+16,0)
A15: =IFERROR(IF($L15>0,INDEX('Invullen groen'!$E:$E,$L15),""),"") | B15: =IFERROR(IF($L15>0,IF(INDEX('Invullen groen'!$F:$F,$L15)>0,INDEX('Invullen groen'!$F:$F,$L15),""),""),"") | C15: =IFERROR(IF($L15>0,IF(INDEX('Invullen groen'!$N:$N,$L15)>0,INDEX('Invullen groen'!$N:$N,$L15),""),""),"") | E15: =IFERROR(IF(LEN(J15)<=36,J15,IFERROR(LEFT(J15,FIND(CHAR(1),SUBSTITUTE(LEFT(J15,36)," ",CHAR(1),LEN(LEFT(J15,36))-LEN(SUBSTITUTE(LEFT(J15,36)," ",""))))-1),LEFT(J15,36))),"") | F15: =IFERROR(IF($L15>0,IF(INDEX('Invullen groen'!$H:$H,$L15)=0,"",INT(INDEX('Invullen groen'!$H:$H,$L15))),""),"") | G15: =IFERROR(IF($L15>0,IF(INDEX('Invullen groen'!$I:$I,$L15)=0,"",INT(INDEX('Invullen groen'!$I:$I,$L15))),""),"") | H15: =IFERROR(IF($L15>0,IF(INDEX('Invullen groen'!$J:$J,$L15)=0,"",INT(INDEX('Invullen groen'!$J:$J,$L15))),""),"") | I15: =IFERROR(IF($L15>0,IF(INDEX('Invullen groen'!$K:$K,$L15)=0,"",INT(INDEX('Invullen groen'!$K:$K,$L15))),""),"") | J15: =IF($L15>0,IFERROR($K$1&" "&TRIM(SUBSTITUTE(SUBSTITUTE(SUBSTITUTE(SUBSTITUTE(SUBSTITUTE(SUBSTITUTE(SUBSTITUTE(SUBSTITUTE(SUBSTITUTE(SUBSTITUTE(SUBSTITUTE(SUBSTITUTE(LOWER(INDEX('Invullen groen'!$O:$O,$L15)),"2024",""),"2025",""),"2026",""),"2027",""),"2028",""),"2029",""),"taakveld ",""),"installaties","inst"),"ruwbouw","ruwb"),"afbouw","afb"),"bijstelling","bijst"),"investeringen","invest")),""),"") | L15: =IFERROR(MATCH(ROW()-4,'Invullen groen'!$P$17:$P$109,0)+16,0)
A16: =IFERROR(IF($L16>0,INDEX('Invullen groen'!$E:$E,$L16),""),"") | B16: =IFERROR(IF($L16>0,IF(INDEX('Invullen groen'!$F:$F,$L16)>0,INDEX('Invullen groen'!$F:$F,$L16),""),""),"") | C16: =IFERROR(IF($L16>0,IF(INDEX('Invullen groen'!$N:$N,$L16)>0,INDEX('Invullen groen'!$N:$N,$L16),""),""),"") | E16: =IFERROR(IF(LEN(J16)<=36,J16,IFERROR(LEFT(J16,FIND(CHAR(1),SUBSTITUTE(LEFT(J16,36)," ",CHAR(1),LEN(LEFT(J16,36))-LEN(SUBSTITUTE(LEFT(J16,36)," ",""))))-1),LEFT(J16,36))),"") | F16: =IFERROR(IF($L16>0,IF(INDEX('Invullen groen'!$H:$H,$L16)=0,"",INT(INDEX('Invullen groen'!$H:$H,$L16))),""),"") | G16: =IFERROR(IF($L16>0,IF(INDEX('Invullen groen'!$I:$I,$L16)=0,"",INT(INDEX('Invullen groen'!$I:$I,$L16))),""),"") | H16: =IFERROR(IF($L16>0,IF(INDEX('Invullen groen'!$J:$J,$L16)=0,"",INT(INDEX('Invullen groen'!$J:$J,$L16))),""),"") | I16: =IFERROR(IF($L16>0,IF(INDEX('Invullen groen'!$K:$K,$L16)=0,"",INT(INDEX('Invullen groen'!$K:$K,$L16))),""),"") | J16: =IF($L16>0,IFERROR($K$1&" "&TRIM(SUBSTITUTE(SUBSTITUTE(SUBSTITUTE(SUBSTITUTE(SUBSTITUTE(SUBSTITUTE(SUBSTITUTE(SUBSTITUTE(SUBSTITUTE(SUBSTITUTE(SUBSTITUTE(SUBSTITUTE(LOWER(INDEX('Invullen groen'!$O:$O,$L16)),"2024",""),"2025",""),"2026",""),"2027",""),"2028",""),"2029",""),"taakveld ",""),"installaties","inst"),"ruwbouw","ruwb"),"afbouw","afb"),"bijstelling","bijst"),"investeringen","invest")),""),"") | L16: =IFERROR(MATCH(ROW()-4,'Invullen groen'!$P$17:$P$109,0)+16,0)
A17: =IFERROR(IF($L17>0,INDEX('Invullen groen'!$E:$E,$L17),""),"") | B17: =IFERROR(IF($L17>0,IF(INDEX('Invullen groen'!$F:$F,$L17)>0,INDEX('Invullen groen'!$F:$F,$L17),""),""),"") | C17: =IFERROR(IF($L17>0,IF(INDEX('Invullen groen'!$N:$N,$L17)>0,INDEX('Invullen groen'!$N:$N,$L17),""),""),"") | E17: =IFERROR(IF(LEN(J17)<=36,J17,IFERROR(LEFT(J17,FIND(CHAR(1),SUBSTITUTE(LEFT(J17,36)," ",CHAR(1),LEN(LEFT(J17,36))-LEN(SUBSTITUTE(LEFT(J17,36)," ",""))))-1),LEFT(J17,36))),"") | F17: =IFERROR(IF($L17>0,IF(INDEX('Invullen groen'!$H:$H,$L17)=0,"",INT(INDEX('Invullen groen'!$H:$H,$L17))),""),"") | G17: =IFERROR(IF($L17>0,IF(INDEX('Invullen groen'!$I:$I,$L17)=0,"",INT(INDEX('Invullen groen'!$I:$I,$L17))),""),"") | H17: =IFERROR(IF($L17>0,IF(INDEX('Invullen groen'!$J:$J,$L17)=0,"",INT(INDEX('Invullen groen'!$J:$J,$L17))),""),"") | I17: =IFERROR(IF($L17>0,IF(INDEX('Invullen groen'!$K:$K,$L17)=0,"",INT(INDEX('Invullen groen'!$K:$K,$L17))),""),"") | J17: =IF($L17>0,IFERROR($K$1&" "&TRIM(SUBSTITUTE(SUBSTITUTE(SUBSTITUTE(SUBSTITUTE(SUBSTITUTE(SUBSTITUTE(SUBSTITUTE(SUBSTITUTE(SUBSTITUTE(SUBSTITUTE(SUBSTITUTE(SUBSTITUTE(LOWER(INDEX('Invullen groen'!$O:$O,$L17)),"2024",""),"2025",""),"2026",""),"2027",""),"2028",""),"2029",""),"taakveld ",""),"installaties","inst"),"ruwbouw","ruwb"),"afbouw","afb"),"bijstelling","bijst"),"investeringen","invest")),""),"") | L17: =IFERROR(MATCH(ROW()-4,'Invullen groen'!$P$17:$P$109,0)+16,0)
... A104: =IFERROR(IF($L104>0,INDEX('Invullen groen'!$E:$E,$L104),""),"") | B104: =IFERROR(IF($L104>0,IF(INDEX('Invullen groen'!$F:$F,$L104)>0,INDEX('Invullen groen'!$F:$F,$L104),""),""),"") | C104: =IFERROR(IF($L104>0,IF(INDEX('Invullen groen'!$N:$N,$L104)>0,INDEX('Invullen groen'!$N:$N,$L104),""),""),"") | E104: =IFERROR(IF(LEN(J104)<=36,J104,IFERROR(LEFT(J104,FIND(CHAR(1),SUBSTITUTE(LEFT(J104,36)," ",CHAR(1),LEN(LEFT(J104,36))-LEN(SUBSTITUTE(LEFT(J104,36)," ",""))))-1),LEFT(J104,36))),"") | F104: =IFERROR(IF($L104>0,IF(INDEX('Invullen groen'!$H:$H,$L104)=0,"",INT(INDEX('Invullen groen'!$H:$H,$L104))),""),"") | G104: =IFERROR(IF($L104>0,IF(INDEX('Invullen groen'!$I:$I,$L104)=0,"",INT(INDEX('Invullen groen'!$I:$I,$L104))),""),"") | H104: =IFERROR(IF($L104>0,IF(INDEX('Invullen groen'!$J:$J,$L104)=0,"",INT(INDEX('Invullen groen'!$J:$J,$L104))),""),"") | I104: =IFERROR(IF($L104>0,IF(INDEX('Invullen groen'!$K:$K,$L104)=0,"",INT(INDEX('Invullen groen'!$K:$K,$L104))),""),"") | J104: =IF($L104>0,IFERROR($K$1&" "&TRIM(SUBSTITUTE(SUBSTITUTE(SUBSTITUTE(SUBSTITUTE(SUBSTITUTE(SUBSTITUTE(SUBSTITUTE(SUBSTITUTE(SUBSTITUTE(SUBSTITUTE(SUBSTITUTE(SUBSTITUTE(LOWER(INDEX('Invullen groen'!$O:$O,$L104)),"2024",""),"2025",""),"2026",""),"2027",""),"2028",""),"2029",""),"taakveld ",""),"installaties","inst"),"ruwbouw","ruwb"),"afbouw","afb"),"bijstelling","bijst"),"investeringen","invest")),""),"") | L104: =IFERROR(MATCH(ROW()-4,'Invullen groen'!$P$17:$P$109,0)+16,0)
A105: =IF($L105>0,"+","") | B105: =IFERROR(IF($L105>0,IF(INDEX('Invullen groen'!$F:$F,$L105)>0,INDEX('Invullen groen'!$F:$F,$L105),""),""),"") | C105: =IFERROR(IF($L105>0,IF(INDEX('Invullen groen'!$N:$N,$L105)>0,INDEX('Invullen groen'!$N:$N,$L105),""),""),"") | E105: =IFERROR(IF(LEN(J105)<=36,J105,IFERROR(LEFT(J105,FIND(CHAR(1),SUBSTITUTE(LEFT(J105,36)," ",CHAR(1),LEN(LEFT(J105,36))-LEN(SUBSTITUTE(LEFT(J105,36)," ",""))))-1),LEFT(J105,36))),"") | F105: =IFERROR(IF($L105>0,IF(INDEX('Invullen groen'!$H:$H,$L105)=0,"",INT(INDEX('Invullen groen'!$H:$H,$L105))),""),"") | G105: =IFERROR(IF($L105>0,IF(INDEX('Invullen groen'!$I:$I,$L105)=0,"",INT(INDEX('Invullen groen'!$I:$I,$L105))),""),"") | H105: =IFERROR(IF($L105>0,IF(INDEX('Invullen groen'!$J:$J,$L105)=0,"",INT(INDEX('Invullen groen'!$J:$J,$L105))),""),"") | I105: =IFERROR(IF($L105>0,IF(INDEX('Invullen groen'!$K:$K,$L105)=0,"",INT(INDEX('Invullen groen'!$K:$K,$L105))),""),"") | J105: =IF($L105>0,IFERROR($K$1&" "&TRIM(SUBSTITUTE(SUBSTITUTE(SUBSTITUTE(SUBSTITUTE(SUBSTITUTE(SUBSTITUTE(SUBSTITUTE(SUBSTITUTE(SUBSTITUTE(SUBSTITUTE(SUBSTITUTE(SUBSTITUTE(LOWER(INDEX('Invullen groen'!$O:$O,$L105)),"2024",""),"2025",""),"2026",""),"2027",""),"2028",""),"2029",""),"taakveld ",""),"installaties","inst"),"ruwbouw","ruwb"),"afbouw","afb"),"bijstelling","bijst"),"investeringen","invest")),""),"") | L105: =IFERROR(MATCH(ROW()-104,'Invullen groen'!$S$121:$S$272,0)+120,0)
A106: =IF($L106>0,"+","") | B106: =IFERROR(IF($L106>0,IF(INDEX('Invullen groen'!$F:$F,$L106)>0,INDEX('Invullen groen'!$F:$F,$L106),""),""),"") | C106: =IFERROR(IF($L106>0,IF(INDEX('Invullen groen'!$N:$N,$L106)>0,INDEX('Invullen groen'!$N:$N,$L106),""),""),"") | E106: =IFERROR(IF(LEN(J106)<=36,J106,IFERROR(LEFT(J106,FIND(CHAR(1),SUBSTITUTE(LEFT(J106,36)," ",CHAR(1),LEN(LEFT(J106,36))-LEN(SUBSTITUTE(LEFT(J106,36)," ",""))))-1),LEFT(J106,36))),"") | F106: =IFERROR(IF($L106>0,IF(INDEX('Invullen groen'!$H:$H,$L106)=0,"",INT(INDEX('Invullen groen'!$H:$H,$L106))),""),"") | G106: =IFERROR(IF($L106>0,IF(INDEX('Invullen groen'!$I:$I,$L106)=0,"",INT(INDEX('Invullen groen'!$I:$I,$L106))),""),"") | H106: =IFERROR(IF($L106>0,IF(INDEX('Invullen groen'!$J:$J,$L106)=0,"",INT(INDEX('Invullen groen'!$J:$J,$L106))),""),"") | I106: =IFERROR(IF($L106>0,IF(INDEX('Invullen groen'!$K:$K,$L106)=0,"",INT(INDEX('Invullen groen'!$K:$K,$L106))),""),"") | J106: =IF($L106>0,IFERROR($K$1&" "&TRIM(SUBSTITUTE(SUBSTITUTE(SUBSTITUTE(SUBSTITUTE(SUBSTITUTE(SUBSTITUTE(SUBSTITUTE(SUBSTITUTE(SUBSTITUTE(SUBSTITUTE(SUBSTITUTE(SUBSTITUTE(LOWER(INDEX('Invullen groen'!$O:$O,$L106)),"2024",""),"2025",""),"2026",""),"2027",""),"2028",""),"2029",""),"taakveld ",""),"installaties","inst"),"ruwbouw","ruwb"),"afbouw","afb"),"bijstelling","bijst"),"investeringen","invest")),""),"") | L106: =IFERROR(MATCH(ROW()-104,'Invullen groen'!$S$121:$S$272,0)+120,0)
A107: =IF($L107>0,"+","") | B107: =IFERROR(IF($L107>0,IF(INDEX('Invullen groen'!$F:$F,$L107)>0,INDEX('Invullen groen'!$F:$F,$L107),""),""),"") | C107: =IFERROR(IF($L107>0,IF(INDEX('Invullen groen'!$N:$N,$L107)>0,INDEX('Invullen groen'!$N:$N,$L107),""),""),"") | E107: =IFERROR(IF(LEN(J107)<=36,J107,IFERROR(LEFT(J107,FIND(CHAR(1),SUBSTITUTE(LEFT(J107,36)," ",CHAR(1),LEN(LEFT(J107,36))-LEN(SUBSTITUTE(LEFT(J107,36)," ",""))))-1),LEFT(J107,36))),"") | F107: =IFERROR(IF($L107>0,IF(INDEX('Invullen groen'!$H:$H,$L107)=0,"",INT(INDEX('Invullen groen'!$H:$H,$L107))),""),"") | G107: =IFERROR(IF($L107>0,IF(INDEX('Invullen groen'!$I:$I,$L107)=0,"",INT(INDEX('Invullen groen'!$I:$I,$L107))),""),"") | H107: =IFERROR(IF($L107>0,IF(INDEX('Invullen groen'!$J:$J,$L107)=0,"",INT(INDEX('Invullen groen'!$J:$J,$L107))),""),"") | I107: =IFERROR(IF($L107>0,IF(INDEX('Invullen groen'!$K:$K,$L107)=0,"",INT(INDEX('Invullen groen'!$K:$K,$L107))),""),"") | J107: =IF($L107>0,IFERROR($K$1&" "&TRIM(SUBSTITUTE(SUBSTITUTE(SUBSTITUTE(SUBSTITUTE(SUBSTITUTE(SUBSTITUTE(SUBSTITUTE(SUBSTITUTE(SUBSTITUTE(SUBSTITUTE(SUBSTITUTE(SUBSTITUTE(LOWER(INDEX('Invullen groen'!$O:$O,$L107)),"2024",""),"2025",""),"2026",""),"2027",""),"2028",""),"2029",""),"taakveld ",""),"installaties","inst"),"ruwbouw","ruwb"),"afbouw","afb"),"bijstelling","bijst"),"investeringen","invest")),""),"") | L107: =IFERROR(MATCH(ROW()-104,'Invullen groen'!$S$121:$S$272,0)+120,0)
A108: =IF($L108>0,"+","") | B108: =IFERROR(IF($L108>0,IF(INDEX('Invullen groen'!$F:$F,$L108)>0,INDEX('Invullen groen'!$F:$F,$L108),""),""),"") | C108: =IFERROR(IF($L108>0,IF(INDEX('Invullen groen'!$N:$N,$L108)>0,INDEX('Invullen groen'!$N:$N,$L108),""),""),"") | E108: =IFERROR(IF(LEN(J108)<=36,J108,IFERROR(LEFT(J108,FIND(CHAR(1),SUBSTITUTE(LEFT(J108,36)," ",CHAR(1),LEN(LEFT(J108,36))-LEN(SUBSTITUTE(LEFT(J108,36)," ",""))))-1),LEFT(J108,36))),"") | F108: =IFERROR(IF($L108>0,IF(INDEX('Invullen groen'!$H:$H,$L108)=0,"",INT(INDEX('Invullen groen'!$H:$H,$L108))),""),"") | G108: =IFERROR(IF($L108>0,IF(INDEX('Invullen groen'!$I:$I,$L108)=0,"",INT(INDEX('Invullen groen'!$I:$I,$L108))),""),"") | H108: =IFERROR(IF($L108>0,IF(INDEX('Invullen groen'!$J:$J,$L108)=0,"",INT(INDEX('Invullen groen'!$J:$J,$L108))),""),"") | I108: =IFERROR(IF($L108>0,IF(INDEX('Invullen groen'!$K:$K,$L108)=0,"",INT(INDEX('Invullen groen'!$K:$K,$L108))),""),"") | J108: =IF($L108>0,IFERROR($K$1&" "&TRIM(SUBSTITUTE(SUBSTITUTE(SUBSTITUTE(SUBSTITUTE(SUBSTITUTE(SUBSTITUTE(SUBSTITUTE(SUBSTITUTE(SUBSTITUTE(SUBSTITUTE(SUBSTITUTE(SUBSTITUTE(LOWER(INDEX('Invullen groen'!$O:$O,$L108)),"2024",""),"2025",""),"2026",""),"2027",""),"2028",""),"2029",""),"taakveld ",""),"installaties","inst"),"ruwbouw","ruwb"),"afbouw","afb"),"bijstelling","bijst"),"investeringen","invest")),""),"") | L108: =IFERROR(MATCH(ROW()-104,'Invullen groen'!$S$121:$S$272,0)+120,0)
A109: =IF($L109>0,"+","") | B109: =IFERROR(IF($L109>0,IF(INDEX('Invullen groen'!$F:$F,$L109)>0,INDEX('Invullen groen'!$F:$F,$L109),""),""),"") | C109: =IFERROR(IF($L109>0,IF(INDEX('Invullen groen'!$N:$N,$L109)>0,INDEX('Invullen groen'!$N:$N,$L109),""),""),"") | E109: =IFERROR(IF(LEN(J109)<=36,J109,IFERROR(LEFT(J109,FIND(CHAR(1),SUBSTITUTE(LEFT(J109,36)," ",CHAR(1),LEN(LEFT(J109,36))-LEN(SUBSTITUTE(LEFT(J109,36)," ",""))))-1),LEFT(J109,36))),"") | F109: =IFERROR(IF($L109>0,IF(INDEX('Invullen groen'!$H:$H,$L109)=0,"",INT(INDEX('Invullen groen'!$H:$H,$L109))),""),"") | G109: =IFERROR(IF($L109>0,IF(INDEX('Invullen groen'!$I:$I,$L109)=0,"",INT(INDEX('Invullen groen'!$I:$I,$L109))),""),"") | H109: =IFERROR(IF($L109>0,IF(INDEX('Invullen groen'!$J:$J,$L109)=0,"",INT(INDEX('Invullen groen'!$J:$J,$L109))),""),"") | I109: =IFERROR(IF($L109>0,IF(INDEX('Invullen groen'!$K:$K,$L109)=0,"",INT(INDEX('Invullen groen'!$K:$K,$L109))),""),"") | J109: =IF($L109>0,IFERROR($K$1&" "&TRIM(SUBSTITUTE(SUBSTITUTE(SUBSTITUTE(SUBSTITUTE(SUBSTITUTE(SUBSTITUTE(SUBSTITUTE(SUBSTITUTE(SUBSTITUTE(SUBSTITUTE(SUBSTITUTE(SUBSTITUTE(LOWER(INDEX('Invullen groen'!$O:$O,$L109)),"2024",""),"2025",""),"2026",""),"2027",""),"2028",""),"2029",""),"taakveld ",""),"installaties","inst"),"ruwbouw","ruwb"),"afbouw","afb"),"bijstelling","bijst"),"investeringen","invest")),""),"") | L109: =IFERROR(MATCH(ROW()-104,'Invullen groen'!$S$121:$S$272,0)+120,0)
A110: =IF($L110>0,"+","") | B110: =IFERROR(IF($L110>0,IF(INDEX('Invullen groen'!$F:$F,$L110)>0,INDEX('Invullen groen'!$F:$F,$L110),""),""),"") | C110: =IFERROR(IF($L110>0,IF(INDEX('Invullen groen'!$N:$N,$L110)>0,INDEX('Invullen groen'!$N:$N,$L110),""),""),"") | E110: =IFERROR(IF(LEN(J110)<=36,J110,IFERROR(LEFT(J110,FIND(CHAR(1),SUBSTITUTE(LEFT(J110,36)," ",CHAR(1),LEN(LEFT(J110,36))-LEN(SUBSTITUTE(LEFT(J110,36)," ",""))))-1),LEFT(J110,36))),"") | F110: =IFERROR(IF($L110>0,IF(INDEX('Invullen groen'!$H:$H,$L110)=0,"",INT(INDEX('Invullen groen'!$H:$H,$L110))),""),"") | G110: =IFERROR(IF($L110>0,IF(INDEX('Invullen groen'!$I:$I,$L110)=0,"",INT(INDEX('Invullen groen'!$I:$I,$L110))),""),"") | H110: =IFERROR(IF($L110>0,IF(INDEX('Invullen groen'!$J:$J,$L110)=0,"",INT(INDEX('Invullen groen'!$J:$J,$L110))),""),"") | I110: =IFERROR(IF($L110>0,IF(INDEX('Invullen groen'!$K:$K,$L110)=0,"",INT(INDEX('Invullen groen'!$K:$K,$L110))),""),"") | J110: =IF($L110>0,IFERROR($K$1&" "&TRIM(SUBSTITUTE(SUBSTITUTE(SUBSTITUTE(SUBSTITUTE(SUBSTITUTE(SUBSTITUTE(SUBSTITUTE(SUBSTITUTE(SUBSTITUTE(SUBSTITUTE(SUBSTITUTE(SUBSTITUTE(LOWER(INDEX('Invullen groen'!$O:$O,$L110)),"2024",""),"2025",""),"2026",""),"2027",""),"2028",""),"2029",""),"taakveld ",""),"installaties","inst"),"ruwbouw","ruwb"),"afbouw","afb"),"bijstelling","bijst"),"investeringen","invest")),""),"") | L110: =IFERROR(MATCH(ROW()-104,'Invullen groen'!$S$121:$S$272,0)+120,0)
A111: =IF($L111>0,"+","") | B111: =IFERROR(IF($L111>0,IF(INDEX('Invullen groen'!$F:$F,$L111)>0,INDEX('Invullen groen'!$F:$F,$L111),""),""),"") | C111: =IFERROR(IF($L111>0,IF(INDEX('Invullen groen'!$N:$N,$L111)>0,INDEX('Invullen groen'!$N:$N,$L111),""),""),"") | E111: =IFERROR(IF(LEN(J111)<=36,J111,IFERROR(LEFT(J111,FIND(CHAR(1),SUBSTITUTE(LEFT(J111,36)," ",CHAR(1),LEN(LEFT(J111,36))-LEN(SUBSTITUTE(LEFT(J111,36)," ",""))))-1),LEFT(J111,36))),"") | F111: =IFERROR(IF($L111>0,IF(INDEX('Invullen groen'!$H:$H,$L111)=0,"",INT(INDEX('Invullen groen'!$H:$H,$L111))),""),"") | G111: =IFERROR(IF($L111>0,IF(INDEX('Invullen groen'!$I:$I,$L111)=0,"",INT(INDEX('Invullen groen'!$I:$I,$L111))),""),"") | H111: =IFERROR(IF($L111>0,IF(INDEX('Invullen groen'!$J:$J,$L111)=0,"",INT(INDEX('Invullen groen'!$J:$J,$L111))),""),"") | I111: =IFERROR(IF($L111>0,IF(INDEX('Invullen groen'!$K:$K,$L111)=0,"",INT(INDEX('Invullen groen'!$K:$K,$L111))),""),"") | J111: =IF($L111>0,IFERROR($K$1&" "&TRIM(SUBSTITUTE(SUBSTITUTE(SUBSTITUTE(SUBSTITUTE(SUBSTITUTE(SUBSTITUTE(SUBSTITUTE(SUBSTITUTE(SUBSTITUTE(SUBSTITUTE(SUBSTITUTE(SUBSTITUTE(LOWER(INDEX('Invullen groen'!$O:$O,$L111)),"2024",""),"2025",""),"2026",""),"2027",""),"2028",""),"2029",""),"taakveld ",""),"installaties","inst"),"ruwbouw","ruwb"),"afbouw","afb"),"bijstelling","bijst"),"investeringen","invest")),""),"") | L111: =IFERROR(MATCH(ROW()-104,'Invullen groen'!$S$121:$S$272,0)+120,0)
A112: =IF($L112>0,"+","") | B112: =IFERROR(IF($L112>0,IF(INDEX('Invullen groen'!$F:$F,$L112)>0,INDEX('Invullen groen'!$F:$F,$L112),""),""),"") | C112: =IFERROR(IF($L112>0,IF(INDEX('Invullen groen'!$N:$N,$L112)>0,INDEX('Invullen groen'!$N:$N,$L112),""),""),"") | E112: =IFERROR(IF(LEN(J112)<=36,J112,IFERROR(LEFT(J112,FIND(CHAR(1),SUBSTITUTE(LEFT(J112,36)," ",CHAR(1),LEN(LEFT(J112,36))-LEN(SUBSTITUTE(LEFT(J112,36)," ",""))))-1),LEFT(J112,36))),"") | F112: =IFERROR(IF($L112>0,IF(INDEX('Invullen groen'!$H:$H,$L112)=0,"",INT(INDEX('Invullen groen'!$H:$H,$L112))),""),"") | G112: =IFERROR(IF($L112>0,IF(INDEX('Invullen groen'!$I:$I,$L112)=0,"",INT(INDEX('Invullen groen'!$I:$I,$L112))),""),"") | H112: =IFERROR(IF($L112>0,IF(INDEX('Invullen groen'!$J:$J,$L112)=0,"",INT(INDEX('Invullen groen'!$J:$J,$L112))),""),"") | I112: =IFERROR(IF($L112>0,IF(INDEX('Invullen groen'!$K:$K,$L112)=0,"",INT(INDEX('Invullen groen'!$K:$K,$L112))),""),"") | J112: =IF($L112>0,IFERROR($K$1&" "&TRIM(SUBSTITUTE(SUBSTITUTE(SUBSTITUTE(SUBSTITUTE(SUBSTITUTE(SUBSTITUTE(SUBSTITUTE(SUBSTITUTE(SUBSTITUTE(SUBSTITUTE(SUBSTITUTE(SUBSTITUTE(LOWER(INDEX('Invullen groen'!$O:$O,$L112)),"2024",""),"2025",""),"2026",""),"2027",""),"2028",""),"2029",""),"taakveld ",""),"installaties","inst"),"ruwbouw","ruwb"),"afbouw","afb"),"bijstelling","bijst"),"investeringen","invest")),""),"") | L112: =IFERROR(MATCH(ROW()-104,'Invullen groen'!$S$121:$S$272,0)+120,0)
A113: =IF($L113>0,"+","") | B113: =IFERROR(IF($L113>0,IF(INDEX('Invullen groen'!$F:$F,$L113)>0,INDEX('Invullen groen'!$F:$F,$L113),""),""),"") | C113: =IFERROR(IF($L113>0,IF(INDEX('Invullen groen'!$N:$N,$L113)>0,INDEX('Invullen groen'!$N:$N,$L113),""),""),"") | E113: =IFERROR(IF(LEN(J113)<=36,J113,IFERROR(LEFT(J113,FIND(CHAR(1),SUBSTITUTE(LEFT(J113,36)," ",CHAR(1),LEN(LEFT(J113,36))-LEN(SUBSTITUTE(LEFT(J113,36)," ",""))))-1),LEFT(J113,36))),"") | F113: =IFERROR(IF($L113>0,IF(INDEX('Invullen groen'!$H:$H,$L113)=0,"",INT(INDEX('Invullen groen'!$H:$H,$L113))),""),"") | G113: =IFERROR(IF($L113>0,IF(INDEX('Invullen groen'!$I:$I,$L113)=0,"",INT(INDEX('Invullen groen'!$I:$I,$L113))),""),"") | H113: =IFERROR(IF($L113>0,IF(INDEX('Invullen groen'!$J:$J,$L113)=0,"",INT(INDEX('Invullen groen'!$J:$J,$L113))),""),"") | I113: =IFERROR(IF($L113>0,IF(INDEX('Invullen groen'!$K:$K,$L113)=0,"",INT(INDEX('Invullen groen'!$K:$K,$L113))),""),"") | J113: =IF($L113>0,IFERROR($K$1&" "&TRIM(SUBSTITUTE(SUBSTITUTE(SUBSTITUTE(SUBSTITUTE(SUBSTITUTE(SUBSTITUTE(SUBSTITUTE(SUBSTITUTE(SUBSTITUTE(SUBSTITUTE(SUBSTITUTE(SUBSTITUTE(LOWER(INDEX('Invullen groen'!$O:$O,$L113)),"2024",""),"2025",""),"2026",""),"2027",""),"2028",""),"2029",""),"taakveld ",""),"installaties","inst"),"ruwbouw","ruwb"),"afbouw","afb"),"bijstelling","bijst"),"investeringen","invest")),""),"") | L113: =IFERROR(MATCH(ROW()-104,'Invullen groen'!$S$121:$S$272,0)+120,0)
A114: =IF($L114>0,"+","") | B114: =IFERROR(IF($L114>0,IF(INDEX('Invullen groen'!$F:$F,$L114)>0,INDEX('Invullen groen'!$F:$F,$L114),""),""),"") | C114: =IFERROR(IF($L114>0,IF(INDEX('Invullen groen'!$N:$N,$L114)>0,INDEX('Invullen groen'!$N:$N,$L114),""),""),"") | E114: =IFERROR(IF(LEN(J114)<=36,J114,IFERROR(LEFT(J114,FIND(CHAR(1),SUBSTITUTE(LEFT(J114,36)," ",CHAR(1),LEN(LEFT(J114,36))-LEN(SUBSTITUTE(LEFT(J114,36)," ",""))))-1),LEFT(J114,36))),"") | F114: =IFERROR(IF($L114>0,IF(INDEX('Invullen groen'!$H:$H,$L114)=0,"",INT(INDEX('Invullen groen'!$H:$H,$L114))),""),"") | G114: =IFERROR(IF($L114>0,IF(INDEX('Invullen groen'!$I:$I,$L114)=0,"",INT(INDEX('Invullen groen'!$I:$I,$L114))),""),"") | H114: =IFERROR(IF($L114>0,IF(INDEX('Invullen groen'!$J:$J,$L114)=0,"",INT(INDEX('Invullen groen'!$J:$J,$L114))),""),"") | I114: =IFERROR(IF($L114>0,IF(INDEX('Invullen groen'!$K:$K,$L114)=0,"",INT(INDEX('Invullen groen'!$K:$K,$L114))),""),"") | J114: =IF($L114>0,IFERROR($K$1&" "&TRIM(SUBSTITUTE(SUBSTITUTE(SUBSTITUTE(SUBSTITUTE(SUBSTITUTE(SUBSTITUTE(SUBSTITUTE(SUBSTITUTE(SUBSTITUTE(SUBSTITUTE(SUBSTITUTE(SUBSTITUTE(LOWER(INDEX('Invullen groen'!$O:$O,$L114)),"2024",""),"2025",""),"2026",""),"2027",""),"2028",""),"2029",""),"taakveld ",""),"installaties","inst"),"ruwbouw","ruwb"),"afbouw","afb"),"bijstelling","bijst"),"investeringen","invest")),""),"") | L114: =IFERROR(MATCH(ROW()-104,'Invullen groen'!$S$121:$S$272,0)+120,0)
A115: =IF($L115>0,"+","") | B115: =IFERROR(IF($L115>0,IF(INDEX('Invullen groen'!$F:$F,$L115)>0,INDEX('Invullen groen'!$F:$F,$L115),""),""),"") | C115: =IFERROR(IF($L115>0,IF(INDEX('Invullen groen'!$N:$N,$L115)>0,INDEX('Invullen groen'!$N:$N,$L115),""),""),"") | E115: =IFERROR(IF(LEN(J115)<=36,J115,IFERROR(LEFT(J115,FIND(CHAR(1),SUBSTITUTE(LEFT(J115,36)," ",CHAR(1),LEN(LEFT(J115,36))-LEN(SUBSTITUTE(LEFT(J115,36)," ",""))))-1),LEFT(J115,36))),"") | F115: =IFERROR(IF($L115>0,IF(INDEX('Invullen groen'!$H:$H,$L115)=0,"",INT(INDEX('Invullen groen'!$H:$H,$L115))),""),"") | G115: =IFERROR(IF($L115>0,IF(INDEX('Invullen groen'!$I:$I,$L115)=0,"",INT(INDEX('Invullen groen'!$I:$I,$L115))),""),"") | H115: =IFERROR(IF($L115>0,IF(INDEX('Invullen groen'!$J:$J,$L115)=0,"",INT(INDEX('Invullen groen'!$J:$J,$L115))),""),"") | I115: =IFERROR(IF($L115>0,IF(INDEX('Invullen groen'!$K:$K,$L115)=0,"",INT(INDEX('Invullen groen'!$K:$K,$L115))),""),"") | J115: =IF($L115>0,IFERROR($K$1&" "&TRIM(SUBSTITUTE(SUBSTITUTE(SUBSTITUTE(SUBSTITUTE(SUBSTITUTE(SUBSTITUTE(SUBSTITUTE(SUBSTITUTE(SUBSTITUTE(SUBSTITUTE(SUBSTITUTE(SUBSTITUTE(LOWER(INDEX('Invullen groen'!$O:$O,$L115)),"2024",""),"2025",""),"2026",""),"2027",""),"2028",""),"2029",""),"taakveld ",""),"installaties","inst"),"ruwbouw","ruwb"),"afbouw","afb"),"bijstelling","bijst"),"investeringen","invest")),""),"") | L115: =IFERROR(MATCH(ROW()-104,'Invullen groen'!$S$121:$S$272,0)+120,0)
A116: =IF($L116>0,"+","") | B116: =IFERROR(IF($L116>0,IF(INDEX('Invullen groen'!$F:$F,$L116)>0,INDEX('Invullen groen'!$F:$F,$L116),""),""),"") | C116: =IFERROR(IF($L116>0,IF(INDEX('Invullen groen'!$N:$N,$L116)>0,INDEX('Invullen groen'!$N:$N,$L116),""),""),"") | E116: =IFERROR(IF(LEN(J116)<=36,J116,IFERROR(LEFT(J116,FIND(CHAR(1),SUBSTITUTE(LEFT(J116,36)," ",CHAR(1),LEN(LEFT(J116,36))-LEN(SUBSTITUTE(LEFT(J116,36)," ",""))))-1),LEFT(J116,36))),"") | F116: =IFERROR(IF($L116>0,IF(INDEX('Invullen groen'!$H:$H,$L116)=0,"",INT(INDEX('Invullen groen'!$H:$H,$L116))),""),"") | G116: =IFERROR(IF($L116>0,IF(INDEX('Invullen groen'!$I:$I,$L116)=0,"",INT(INDEX('Invullen groen'!$I:$I,$L116))),""),"") | H116: =IFERROR(IF($L116>0,IF(INDEX('Invullen groen'!$J:$J,$L116)=0,"",INT(INDEX('Invullen groen'!$J:$J,$L116))),""),"") | I116: =IFERROR(IF($L116>0,IF(INDEX('Invullen groen'!$K:$K,$L116)=0,"",INT(INDEX('Invullen groen'!$K:$K,$L116))),""),"") | J116: =IF($L116>0,IFERROR($K$1&" "&TRIM(SUBSTITUTE(SUBSTITUTE(SUBSTITUTE(SUBSTITUTE(SUBSTITUTE(SUBSTITUTE(SUBSTITUTE(SUBSTITUTE(SUBSTITUTE(SUBSTITUTE(SUBSTITUTE(SUBSTITUTE(LOWER(INDEX('Invullen groen'!$O:$O,$L116)),"2024",""),"2025",""),"2026",""),"2027",""),"2028",""),"2029",""),"taakveld ",""),"installaties","inst"),"ruwbouw","ruwb"),"afbouw","afb"),"bijstelling","bijst"),"investeringen","invest")),""),"") | L116: =IFERROR(MATCH(ROW()-104,'Invullen groen'!$S$121:$S$272,0)+120,0)
... A250: =IF($L250>0,"+","") | B250: =IFERROR(IF($L250>0,IF(INDEX('Invullen groen'!$F:$F,$L250)>0,INDEX('Invullen groen'!$F:$F,$L250),""),""),"") | C250: =IFERROR(IF($L250>0,IF(INDEX('Invullen groen'!$N:$N,$L250)>0,INDEX('Invullen groen'!$N:$N,$L250),""),""),"") | E250: =IFERROR(IF(LEN(J250)<=36,J250,IFERROR(LEFT(J250,FIND(CHAR(1),SUBSTITUTE(LEFT(J250,36)," ",CHAR(1),LEN(LEFT(J250,36))-LEN(SUBSTITUTE(LEFT(J250,36)," ",""))))-1),LEFT(J250,36))),"") | F250: =IFERROR(IF($L250>0,IF(INDEX('Invullen groen'!$H:$H,$L250)=0,"",INT(INDEX('Invullen groen'!$H:$H,$L250))),""),"") | G250: =IFERROR(IF($L250>0,IF(INDEX('Invullen groen'!$I:$I,$L250)=0,"",INT(INDEX('Invullen groen'!$I:$I,$L250))),""),"") | H250: =IFERROR(IF($L250>0,IF(INDEX('Invullen groen'!$J:$J,$L250)=0,"",INT(INDEX('Invullen groen'!$J:$J,$L250))),""),"") | I250: =IFERROR(IF($L250>0,IF(INDEX('Invullen groen'!$K:$K,$L250)=0,"",INT(INDEX('Invullen groen'!$K:$K,$L250))),""),"") | J250: =IF($L250>0,IFERROR($K$1&" "&TRIM(SUBSTITUTE(SUBSTITUTE(SUBSTITUTE(SUBSTITUTE(SUBSTITUTE(SUBSTITUTE(SUBSTITUTE(SUBSTITUTE(SUBSTITUTE(SUBSTITUTE(SUBSTITUTE(SUBSTITUTE(LOWER(INDEX('Invullen groen'!$O:$O,$L250)),"2024",""),"2025",""),"2026",""),"2027",""),"2028",""),"2029",""),"taakveld ",""),"installaties","inst"),"ruwbouw","ruwb"),"afbouw","afb"),"bijstelling","bijst"),"investeringen","invest")),""),"") | L250: =IFERROR(MATCH(ROW()-104,'Invullen groen'!$S$121:$S$272,0)+120,0)
A251: =IF(SUM(F105:I250)=0,"",2999999) | B251: =IF(SUM(F105:I250)=0,"",86100) | E251: =IF(SUM(F105:I250)=0,"",$K$1&" sluitrekening balans") | F251: =IFERROR(IF(SUM(F105:F250)=0,"",-SUM(F105:F250)),"") | G251: =IFERROR(IF(SUM(G105:G250)=0,"",-SUM(G105:G250)),"") | H251: =IFERROR(IF(SUM(H105:H250)=0,"",-SUM(H105:H250)),"") | I251: =IFERROR(IF(SUM(I105:I250)=0,"",-SUM(I105:I250)),"")

Sheet Raad
A1: =+'Invullen groen'!A4 | F1: =+'Invullen groen'!I4 | G1: =+'Invullen groen'!J4 | H1: =+'Invullen groen'!K4 | I1: =+'Invullen groen'!AW4 | J1: =+'Invullen groen'!AX4 | K1: =+'Invullen groen'!AY4 | L1: =+'Invullen groen'!AZ4 | M1: =+'Invullen groen'!BA4 | N1: =+'Invullen groen'!BB4 | O1: =+'Invullen groen'!BC4 | P1: =+'Invullen groen'!BD4
A2: Omschrijving wijziging | B2: =+'Invullen groen'!C5 | C2: =+'Invullen groen'!D5 | F2: =+'Invullen groen'!I5 | G2: =+'Invullen groen'!J5 | H2: =+'Invullen groen'!K5 | I2: =+'Invullen groen'!AW5 | J2: =+'Invullen groen'!AX5 | K2: =+'Invullen groen'!AY5 | L2: =+'Invullen groen'!AZ5 | M2: =+'Invullen groen'!BA5 | N2: =+'Invullen groen'!BB5 | O2: =+'Invullen groen'!BC5 | P2: =+'Invullen groen'!BD5
A3: =+'Invullen groen'!G4 | B3: =+'Invullen groen'!H4
A5: =+'Invullen groen'!G6 | B5: =+'Invullen groen'!H6 | F5: =+'Invullen groen'!I7 | G5: =+'Invullen groen'!J7 | H5: =+'Invullen groen'!K7 | I5: =+'Invullen groen'!AW7 | J5: =+'Invullen groen'!AX7 | K5: =+'Invullen groen'!AY7 | L5: =+'Invullen groen'!AZ7 | M5: =+'Invullen groen'!BA7 | N5: =+'Invullen groen'!BB7 | O5: =+'Invullen groen'!BC7 | P5: =+'Invullen groen'!BD7
A6: ='Invullen groen'!G7 | B6: ='Invullen groen'!H7 | F6: =+'Invullen groen'!I8 | G6: =+'Invullen groen'!J8 | H6: =+'Invullen groen'!K8 | I6: =+'Invullen groen'!AW8 | J6: =+'Invullen groen'!AX8 | K6: =+'Invullen groen'!AY8 | L6: =+'Invullen groen'!AZ8 | M6: =+'Invullen groen'!BA8 | N6: =+'Invullen groen'!BB8 | O6: =+'Invullen groen'!BC8 | P6: =+'Invullen groen'!BD8
A7: =+'Invullen groen'!A9 | B7: =+'Invullen groen'!C9 | C7: =+'Invullen groen'!G9 | D7: =+'Invullen groen'!M9 | E7: =+'Invullen groen'!H9 | F7: =+'Invullen groen'!I9 | G7: =+'Invullen groen'!J9 | H7: =+'Invullen groen'!K9 | I7: =+'Invullen groen'!AW9 | J7: =+'Invullen groen'!AX9 | K7: =+'Invullen groen'!AY9 | L7: =+'Invullen groen'!AZ9 | M7: =+'Invullen groen'!BA9 | N7: =+'Invullen groen'!BB9 | O7: =+'Invullen groen'!BC9 | P7: =+'Invullen groen'!BD9
A8: =+'Invullen groen'!A11 | D8: =+'Invullen groen'!M11 | E8: =+'Invullen groen'!H11 | F8: =+'Invullen groen'!I11 | G8: =+'Invullen groen'!J11 | H8: =+'Invullen groen'!K11 | I8: =+'Invullen groen'!AW11 | J8: =+'Invullen groen'!AX11 | K8: =+'Invullen groen'!AY11 | L8: =+'Invullen groen'!AZ11 | M8: =+'Invullen groen'!BA11 | N8: =+'Invullen groen'!BB11 | O8: =+'Invullen groen'!BC11 | P8: =+'Invullen groen'!BD11
A9: =+'Invullen groen'!A12 | B9: =+'Invullen groen'!C12 | C9: =+'Invullen groen'!G12 | D9: =+'Invullen groen'!M12 | E9: =+'Invullen groen'!H12 | F9: =+'Invullen groen'!I12 | G9: =+'Invullen groen'!J12 | H9: =+'Invullen groen'!K12 | I9: =+'Invullen groen'!AW12 | J9: =+'Invullen groen'!AX12 | K9: =+'Invullen groen'!AY12 | L9: =+'Invullen groen'!AZ12 | M9: =+'Invullen groen'!BA12 | N9: =+'Invullen groen'!BB12 | O9: =+'Invullen groen'!BC12 | P9: =+'Invullen groen'!BD12
A10: =+'Invullen groen'!A13 | B10: =+'Invullen groen'!C13 | C10: Omschrijving boekingspost | D10: =+'Invullen groen'!M13 | E10: =+'Invullen groen'!H13 | F10: =+'Invullen groen'!I13 | G10: =+'Invullen groen'!J13 | H10: =+'Invullen groen'!K13 | I10: =+'Invullen groen'!AW13 | J10: =+'Invullen groen'!AX13 | K10: =+'Invullen groen'!AY13 | L10: =+'Invullen groen'!AZ13 | M10: =+'Invullen groen'!BA13 | N10: =+'Invullen groen'!BB13 | O10: =+'Invullen groen'!BC13 | P10: =+'Invullen groen'!BD13
A11: =+'Invullen groen'!A14 | B11: =+'Invullen groen'!C14 | C11: =+'Invullen groen'!G14 | D11: =+'Invullen groen'!M14 | E11: =+'Invullen groen'!H14 | F11: =+'Invullen groen'!I14 | G11: =+'Invullen groen'!J14 | H11: =+'Invullen groen'!K14 | I11: =+'Invullen groen'!AW14 | J11: =+'Invullen groen'!AX14 | K11: =+'Invullen groen'!AY14 | L11: =+'Invullen groen'!AZ14 | M11: =+'Invullen groen'!BA14 | N11: =+'Invullen groen'!BB14 | O11: =+'Invullen groen'!BC14 | P11: =+'Invullen groen'!BD14
A12: =+'Invullen groen'!A15 | B12: =+'Invullen groen'!C15 | C12: =+'Invullen groen'!G15 | D12: =+'Invullen groen'!M15 | E12: =+'Invullen groen'!H15 | F12: =+'Invullen groen'!I15 | G12: =+'Invullen groen'!J15 | H12: =+'Invullen groen'!K15 | I12: =+'Invullen groen'!AW15 | J12: =+'Invullen groen'!AX15 | K12: =+'Invullen groen'!AY15 | L12: =+'Invullen groen'!AZ15 | M12: =+'Invullen groen'!BA15 | N12: =+'Invullen groen'!BB15 | O12: =+'Invullen groen'!BC15 | P12: =+'Invullen groen'!BD15
A13: =+'Invullen groen'!A16 | B13: =+'Invullen groen'!C16 | C13: =+'Invullen groen'!G16 | D13: =+'Invullen groen'!M16 | E13: =+'Invullen groen'!H16 | F13: =+'Invullen groen'!I16 | G13: =+'Invullen groen'!J16 | H13: =+'Invullen groen'!K16 | I13: =+'Invullen groen'!AW16 | J13: =+'Invullen groen'!AX16 | K13: =+'Invullen groen'!AY16 | L13: =+'Invullen groen'!AZ16 | M13: =+'Invullen groen'!BA16 | N13: =+'Invullen groen'!BB16 | O13: =+'Invullen groen'!BC16 | P13: =+'Invullen groen'!BD16
A14: =+'Invullen groen'!A17 | B14: =+'Invullen groen'!C17 | C14: =+'Invullen groen'!G17 | D14: =+'Invullen groen'!M17 | E14: =+'Invullen groen'!H17 | F14: =+'Invullen groen'!I17 | G14: =+'Invullen groen'!J17 | H14: =+'Invullen groen'!K17 | I14: =+'Invullen groen'!AW17 | J14: =+'Invullen groen'!AX17 | K14: =+'Invullen groen'!AY17 | L14: =+'Invullen groen'!AZ17 | M14: =+'Invullen groen'!BA17 | N14: =+'Invullen groen'!BB17 | O14: =+'Invullen groen'!BC17 | P14: =+'Invullen groen'!BD17
A15: =+'Invullen groen'!A18 | B15: =+'Invullen groen'!C18 | C15: =+'Invullen groen'!G18 | D15: =+'Invullen groen'!M18 | E15: =+'Invullen groen'!H18 | F15: =+'Invullen groen'!I18 | G15: =+'Invullen groen'!J18 | H15: =+'Invullen groen'!K18 | I15: =+'Invullen groen'!AW18 | J15: =+'Invullen groen'!AX18 | K15: =+'Invullen groen'!AY18 | L15: =+'Invullen groen'!AZ18 | M15: =+'Invullen groen'!BA18 | N15: =+'Invullen groen'!BB18 | O15: =+'Invullen groen'!BC18 | P15: =+'Invullen groen'!BD18
A16: =+'Invullen groen'!A19 | B16: =+'Invullen groen'!C19 | C16: =+'Invullen groen'!G19 | D16: =+'Invullen groen'!M19 | E16: =+'Invullen groen'!H19 | F16: =+'Invullen groen'!I19 | G16: =+'Invullen groen'!J19 | H16: =+'Invullen groen'!K19 | I16: =+'Invullen groen'!AW19 | J16: =+'Invullen groen'!AX19 | K16: =+'Invullen groen'!AY19 | L16: =+'Invullen groen'!AZ19 | M16: =+'Invullen groen'!BA19 | N16: =+'Invullen groen'!BB19 | O16: =+'Invullen groen'!BC19 | P16: =+'Invullen groen'!BD19
A17: =+'Invullen groen'!A20 | B17: =+'Invullen groen'!C20 | C17: =+'Invullen groen'!G20 | D17: =+'Invullen groen'!M20 | E17: =+'Invullen groen'!H20 | F17: =+'Invullen groen'!I20 | G17: =+'Invullen groen'!J20 | H17: =+'Invullen groen'!K20 | I17: =+'Invullen groen'!AW20 | J17: =+'Invullen groen'!AX20 | K17: =+'Invullen groen'!AY20 | L17: =+'Invullen groen'!AZ20 | M17: =+'Invullen groen'!BA20 | N17: =+'Invullen groen'!BB20 | O17: =+'Invullen groen'!BC20 | P17: =+'Invullen groen'!BD20
A18: =+'Invullen groen'!A21 | B18: =+'Invullen groen'!C21 | C18: =+'Invullen groen'!G21 | D18: =+'Invullen groen'!M21 | E18: =+'Invullen groen'!H21 | F18: =+'Invullen groen'!I21 | G18: =+'Invullen groen'!J21 | H18: =+'Invullen groen'!K21 | I18: =+'Invullen groen'!AW21 | J18: =+'Invullen groen'!AX21 | K18: =+'Invullen groen'!AY21 | L18: =+'Invullen groen'!AZ21 | M18: =+'Invullen groen'!BA21 | N18: =+'Invullen groen'!BB21 | O18: =+'Invullen groen'!BC21 | P18: =+'Invullen groen'!BD21
A19: =+'Invullen groen'!A22 | B19: =+'Invullen groen'!C22 | C19: =+'Invullen groen'!G22 | D19: =+'Invullen groen'!M22 | E19: =+'Invullen groen'!H22 | F19: =+'Invullen groen'!I22 | G19: =+'Invullen groen'!J22 | H19: =+'Invullen groen'!K22 | I19: =+'Invullen groen'!AW22 | J19: =+'Invullen groen'!AX22 | K19: =+'Invullen groen'!AY22 | L19: =+'Invullen groen'!AZ22 | M19: =+'Invullen groen'!BA22 | N19: =+'Invullen groen'!BB22 | O19: =+'Invullen groen'!BC22 | P19: =+'Invullen groen'!BD22
A20: =+'Invullen groen'!A23 | B20: =+'Invullen groen'!C23 | C20: =+'Invullen groen'!G23 | D20: =+'Invullen groen'!M23 | E20: =+'Invullen groen'!H23 | F20: =+'Invullen groen'!I23 | G20: =+'Invullen groen'!J23 | H20: =+'Invullen groen'!K23 | I20: =+'Invullen groen'!AW23 | J20: =+'Invullen groen'!AX23 | K20: =+'Invullen groen'!AY23 | L20: =+'Invullen groen'!AZ23 | M20: =+'Invullen groen'!BA23 | N20: =+'Invullen groen'!BB23 | O20: =+'Invullen groen'!BC23 | P20: =+'Invullen groen'!BD23
A21: =+'Invullen groen'!A24 | B21: =+'Invullen groen'!C24 | C21: =+'Invullen groen'!G24 | D21: =+'Invullen groen'!M24 | E21: =+'Invullen groen'!H24 | F21: =+'Invullen groen'!I24 | G21: =+'Invullen groen'!J24 | H21: =+'Invullen groen'!K24 | I21: =+'Invullen groen'!AW24 | J21: =+'Invullen groen'!AX24 | K21: =+'Invullen groen'!AY24 | L21: =+'Invullen groen'!AZ24 | M21: =+'Invullen groen'!BA24 | N21: =+'Invullen groen'!BB24 | O21: =+'Invullen groen'!BC24 | P21: =+'Invullen groen'!BD24
A22: =+'Invullen groen'!A25 | B22: =+'Invullen groen'!C25 | C22: =+'Invullen groen'!G25 | D22: =+'Invullen groen'!M25 | E22: =+'Invullen groen'!H25 | F22: =+'Invullen groen'!I25 | G22: =+'Invullen groen'!J25 | H22: =+'Invullen groen'!K25 | I22: =+'Invullen groen'!AW25 | J22: =+'Invullen groen'!AX25 | K22: =+'Invullen groen'!AY25 | L22: =+'Invullen groen'!AZ25 | M22: =+'Invullen groen'!BA25 | N22: =+'Invullen groen'!BB25 | O22: =+'Invullen groen'!BC25 | P22: =+'Invullen groen'!BD25
... A72: =+'Invullen groen'!A75 | B72: =+'Invullen groen'!C75 | C72: =+'Invullen groen'!G75 | D72: =+'Invullen groen'!M75 | E72: =+'Invullen groen'!H75 | F72: =+'Invullen groen'!I75 | G72: =+'Invullen groen'!J75 | H72: =+'Invullen groen'!K75 | I72: =+'Invullen groen'!AW75 | J72: =+'Invullen groen'!AX75 | K72: =+'Invullen groen'!AY75 | L72: =+'Invullen groen'!AZ75 | M72: =+'Invullen groen'!BA75 | N72: =+'Invullen groen'!BB75 | O72: =+'Invullen groen'!BC75 | P72: =+'Invullen groen'!BD75
A73: =+'Invullen groen'!A77 | B73: =+'Invullen groen'!C77 | C73: =+'Invullen groen'!G77 | D73: =+'Invullen groen'!M77 | E73: =+'Invullen groen'!H77 | F73: =+'Invullen groen'!I77 | G73: =+'Invullen groen'!J77 | H73: =+'Invullen groen'!K77 | I73: =+'Invullen groen'!AW77 | J73: =+'Invullen groen'!AX77 | K73: =+'Invullen groen'!AY77 | L73: =+'Invullen groen'!AZ77 | M73: =+'Invullen groen'!BA77 | N73: =+'Invullen groen'!BB77 | O73: =+'Invullen groen'!BC77 | P73: =+'Invullen groen'!BD77
A74: =+'Invullen groen'!A78 | B74: =+'Invullen groen'!C78 | C74: =+'Invullen groen'!G78 | D74: =+'Invullen groen'!M78 | E74: =+'Invullen groen'!H78 | F74: =+'Invullen groen'!I78 | G74: =+'Invullen groen'!J78 | H74: =+'Invullen groen'!K78 | I74: =+'Invullen groen'!AW78 | J74: =+'Invullen groen'!AX78 | K74: =+'Invullen groen'!AY78 | L74: =+'Invullen groen'!AZ78 | M74: =+'Invullen groen'!BA78 | N74: =+'Invullen groen'!BB78 | O74: =+'Invullen groen'!BC78 | P74: =+'Invullen groen'!BD78
A75: =+'Invullen groen'!A79 | B75: =+'Invullen groen'!C79 | C75: =+'Invullen groen'!G79 | D75: =+'Invullen groen'!M79 | E75: =+'Invullen groen'!H79 | F75: =+'Invullen groen'!I79 | G75: =+'Invullen groen'!J79 | H75: =+'Invullen groen'!K79 | I75: =+'Invullen groen'!AW79 | J75: =+'Invullen groen'!AX79 | K75: =+'Invullen groen'!AY79 | L75: =+'Invullen groen'!AZ79 | M75: =+'Invullen groen'!BA79 | N75: =+'Invullen groen'!BB79 | O75: =+'Invullen groen'!BC79 | P75: =+'Invullen groen'!BD79
A76: =+'Invullen groen'!A80 | B76: =+'Invullen groen'!C80 | C76: =+'Invullen groen'!G80 | D76: =+'Invullen groen'!M80 | E76: =+'Invullen groen'!H80 | F76: =+'Invullen groen'!I80 | G76: =+'Invullen groen'!J80 | H76: =+'Invullen groen'!K80 | I76: =+'Invullen groen'!AW80 | J76: =+'Invullen groen'!AX80 | K76: =+'Invullen groen'!AY80 | L76: =+'Invullen groen'!AZ80 | M76: =+'Invullen groen'!BA80 | N76: =+'Invullen groen'!BB80 | O76: =+'Invullen groen'!BC80 | P76: =+'Invullen groen'!BD80
A77: =+'Invullen groen'!A81 | B77: =+'Invullen groen'!C81 | C77: =+'Invullen groen'!G81 | D77: =+'Invullen groen'!M81 | E77: =+'Invullen groen'!H81 | F77: =+'Invullen groen'!I81 | G77: =+'Invullen groen'!J81 | H77: =+'Invullen groen'!K81 | I77: =+'Invullen groen'!AW81 | J77: =+'Invullen groen'!AX81 | K77: =+'Invullen groen'!AY81 | L77: =+'Invullen groen'!AZ81 | M77: =+'Invullen groen'!BA81 | N77: =+'Invullen groen'!BB81 | O77: =+'Invullen groen'!BC81 | P77: =+'Invullen groen'!BD81
A78: =+'Invullen groen'!A82 | B78: =+'Invullen groen'!C82 | C78: =+'Invullen groen'!G82 | D78: =+'Invullen groen'!M82 | E78: =+'Invullen groen'!H82 | F78: =+'Invullen groen'!I82 | G78: =+'Invullen groen'!J82 | H78: =+'Invullen groen'!K82 | I78: =+'Invullen groen'!AW82 | J78: =+'Invullen groen'!AX82 | K78: =+'Invullen groen'!AY82 | L78: =+'Invullen groen'!AZ82 | M78: =+'Invullen groen'!BA82 | N78: =+'Invullen groen'!BB82 | O78: =+'Invullen groen'!BC82 | P78: =+'Invullen groen'!BD82
A79: =+'Invullen groen'!A83 | B79: =+'Invullen groen'!C83 | C79: =+'Invullen groen'!G83 | D79: =+'Invullen groen'!M83 | E79: =+'Invullen groen'!H83 | F79: =+'Invullen groen'!I83 | G79: =+'Invullen groen'!J83 | H79: =+'Invullen groen'!K83 | I79: =+'Invullen groen'!AW83 | J79: =+'Invullen groen'!AX83 | K79: =+'Invullen groen'!AY83 | L79: =+'Invullen groen'!AZ83 | M79: =+'Invullen groen'!BA83 | N79: =+'Invullen groen'!BB83 | O79: =+'Invullen groen'!BC83 | P79: =+'Invullen groen'!BD83
A80: =+'Invullen groen'!A84 | B80: =+'Invullen groen'!C84 | C80: =+'Invullen groen'!G84 | D80: =+'Invullen groen'!M84 | E80: =+'Invullen groen'!H84 | F80: =+'Invullen groen'!I84 | G80: =+'Invullen groen'!J84 | H80: =+'Invullen groen'!K84 | I80: =+'Invullen groen'!AW84 | J80: =+'Invullen groen'!AX84 | K80: =+'Invullen groen'!AY84 | L80: =+'Invullen groen'!AZ84 | M80: =+'Invullen groen'!BA84 | N80: =+'Invullen groen'!BB84 | O80: =+'Invullen groen'!BC84 | P80: =+'Invullen groen'!BD84
A81: =+'Invullen groen'!A85 | B81: =+'Invullen groen'!C85 | C81: =+'Invullen groen'!G85 | D81: =+'Invullen groen'!M85 | E81: =+'Invullen groen'!H85 | F81: =+'Invullen groen'!I85 | G81: =+'Invullen groen'!J85 | H81: =+'Invullen groen'!K85 | I81: =+'Invullen groen'!AW85 | J81: =+'Invullen groen'!AX85 | K81: =+'Invullen groen'!AY85 | L81: =+'Invullen groen'!AZ85 | M81: =+'Invullen groen'!BA85 | N81: =+'Invullen groen'!BB85 | O81: =+'Invullen groen'!BC85 | P81: =+'Invullen groen'!BD85
A82: =+'Invullen groen'!A86 | B82: =+'Invullen groen'!C86 | C82: =+'Invullen groen'!G86 | D82: =+'Invullen groen'!M86 | E82: =+'Invullen groen'!H86 | F82: =+'Invullen groen'!I86 | G82: =+'Invullen groen'!J86 | H82: =+'Invullen groen'!K86 | I82: =+'Invullen groen'!AW86 | J82: =+'Invullen groen'!AX86 | K82: =+'Invullen groen'!AY86 | L82: =+'Invullen groen'!AZ86 | M82: =+'Invullen groen'!BA86 | N82: =+'Invullen groen'!BB86 | O82: =+'Invullen groen'!BC86 | P82: =+'Invullen groen'!BD86
A83: =+'Invullen groen'!A87 | B83: =+'Invullen groen'!C87 | C83: =+'Invullen groen'!G87 | D83: =+'Invullen groen'!M87 | E83: =+'Invullen groen'!H87 | F83: =+'Invullen groen'!I87 | G83: =+'Invullen groen'!J87 | H83: =+'Invullen groen'!K87 | I83: =+'Invullen groen'!AW87 | J83: =+'Invullen groen'!AX87 | K83: =+'Invullen groen'!AY87 | L83: =+'Invullen groen'!AZ87 | M83: =+'Invullen groen'!BA87 | N83: =+'Invullen groen'!BB87 | O83: =+'Invullen groen'!BC87 | P83: =+'Invullen groen'!BD87
A84: =+'Invullen groen'!A88 | B84: =+'Invullen groen'!C88 | C84: =+'Invullen groen'!G88 | D84: =+'Invullen groen'!M88 | E84: =+'Invullen groen'!H88 | F84: =+'Invullen groen'!I88 | G84: =+'Invullen groen'!J88 | H84: =+'Invullen groen'!K88 | I84: =+'Invullen groen'!AW88 | J84: =+'Invullen groen'!AX88 | K84: =+'Invullen groen'!AY88 | L84: =+'Invullen groen'!AZ88 | M84: =+'Invullen groen'!BA88 | N84: =+'Invullen groen'!BB88 | O84: =+'Invullen groen'!BC88 | P84: =+'Invullen groen'!BD88
... A105: =+'Invullen groen'!A109 | B105: =+'Invullen groen'!C109 | C105: =+'Invullen groen'!G109 | D105: =+'Invullen groen'!M109 | E105: =+'Invullen groen'!H109 | F105: =+'Invullen groen'!I109 | G105: =+'Invullen groen'!J109 | H105: =+'Invullen groen'!K109 | I105: =+'Invullen groen'!AW109 | J105: =+'Invullen groen'!AX109 | K105: =+'Invullen groen'!AY109 | L105: =+'Invullen groen'!AZ109 | M105: =+'Invullen groen'!BA109 | N105: =+'Invullen groen'!BB109 | O105: =+'Invullen groen'!BC109 | P105: =+'Invullen groen'!BD109
A106: =+'Invullen groen'!A110 | C106: =+'Invullen groen'!G110 | D106: =+'Invullen groen'!M110 | E106: =+'Invullen groen'!H110 | F106: =+'Invullen groen'!I110 | G106: =+'Invullen groen'!J110 | H106: =+'Invullen groen'!K110 | I106: =+'Invullen groen'!AW110 | J106: =+'Invullen groen'!AX110 | K106: =+'Invullen groen'!AY110 | L106: =+'Invullen groen'!AZ110 | M106: =+'Invullen groen'!BA110 | N106: =+'Invullen groen'!BB110 | O106: =+'Invullen groen'!BC110 | P106: =+'Invullen groen'!BD110
A107: =+'Invullen groen'!A112 | B107: =+'Invullen groen'!C114 | C107: =+'Invullen groen'!G114 | D107: =+'Invullen groen'!M114 | E107: =+'Invullen groen'!H112 | F107: =+'Invullen groen'!I114 | G107: =+'Invullen groen'!J114 | H107: =+'Invullen groen'!K114 | I107: =+'Invullen groen'!AW114 | J107: =+'Invullen groen'!AX114 | K107: =+'Invullen groen'!AY114 | L107: =+'Invullen groen'!AZ114 | M107: =+'Invullen groen'!BA114 | N107: =+'Invullen groen'!BB114 | O107: =+'Invullen groen'!BC114 | P107: =+'Invullen groen'!BD114
A108: =+'Invullen groen'!A115 | D108: =+'Invullen groen'!M115 | E108: =+'Invullen groen'!H115 | F108: =+'Invullen groen'!I115 | G108: =+'Invullen groen'!J115 | H108: =+'Invullen groen'!K115 | I108: =+'Invullen groen'!AW115 | J108: =+'Invullen groen'!AX115 | K108: =+'Invullen groen'!AY115 | L108: =+'Invullen groen'!AZ115 | M108: =+'Invullen groen'!BA115 | N108: =+'Invullen groen'!BB115 | O108: =+'Invullen groen'!BC115 | P108: =+'Invullen groen'!BD115
A109: =+'Invullen groen'!A116 | B109: =+'Invullen groen'!C116 | C109: =+'Invullen groen'!G116 | D109: =+'Invullen groen'!M116 | E109: =+'Invullen groen'!H116 | F109: =+'Invullen groen'!I116 | G109: =+'Invullen groen'!J116 | H109: =+'Invullen groen'!K116 | I109: =+'Invullen groen'!AW116 | J109: =+'Invullen groen'!AX116 | K109: =+'Invullen groen'!AY116 | L109: =+'Invullen groen'!AZ116 | M109: =+'Invullen groen'!BA116 | N109: =+'Invullen groen'!BB116 | O109: =+'Invullen groen'!BC116 | P109: =+'Invullen groen'!BD116
A110: =+'Invullen groen'!A117 | B110: =+'Invullen groen'!C117 | D110: =+'Invullen groen'!M117 | E110: =+'Invullen groen'!H117 | F110: =+'Invullen groen'!I117 | G110: =+'Invullen groen'!J117 | H110: =+'Invullen groen'!K117 | I110: =+'Invullen groen'!AW117 | J110: =+'Invullen groen'!AX117 | K110: =+'Invullen groen'!AY117 | L110: =+'Invullen groen'!AZ117 | M110: =+'Invullen groen'!BA117 | N110: =+'Invullen groen'!BB117 | O110: =+'Invullen groen'!BC117 | P110: =+'Invullen groen'!BD117
A111: =+'Invullen groen'!A118 | B111: =+'Invullen groen'!C118 | C111: =+'Invullen groen'!G118 | D111: =+'Invullen groen'!M118 | E111: =+'Invullen groen'!H118 | F111: =+'Invullen groen'!I118 | G111: =+'Invullen groen'!J118 | H111: =+'Invullen groen'!K118 | I111: =+'Invullen groen'!AW118 | J111: =+'Invullen groen'!AX118 | K111: =+'Invullen groen'!AY118 | L111: =+'Invullen groen'!AZ118 | M111: =+'Invullen groen'!BA118 | N111: =+'Invullen groen'!BB118 | O111: =+'Invullen groen'!BC118 | P111: =+'Invullen groen'!BD118
A112: =+'Invullen groen'!A119 | B112: =+'Invullen groen'!C119 | C112: =+'Invullen groen'!G119 | D112: =+'Invullen groen'!M119 | E112: =+'Invullen groen'!H119 | F112: =+'Invullen groen'!I119 | G112: =+'Invullen groen'!J119 | H112: =+'Invullen groen'!K119 | I112: =+'Invullen groen'!AW119 | J112: =+'Invullen groen'!AX119 | K112: =+'Invullen groen'!AY119 | L112: =+'Invullen groen'!AZ119 | M112: =+'Invullen groen'!BA119 | N112: =+'Invullen groen'!BB119 | O112: =+'Invullen groen'!BC119 | P112: =+'Invullen groen'!BD119
A113: =+'Invullen groen'!A120 | B113: =+'Invullen groen'!C120 | C113: =+'Invullen groen'!G120 | D113: =+'Invullen groen'!M120 | E113: =+'Invullen groen'!H120 | F113: =+'Invullen groen'!I120 | G113: =+'Invullen groen'!J120 | H113: =+'Invullen groen'!K120 | I113: =+'Invullen groen'!AW120 | J113: =+'Invullen groen'!AX120 | K113: =+'Invullen groen'!AY120 | L113: =+'Invullen groen'!AZ120 | M113: =+'Invullen groen'!BA120 | N113: =+'Invullen groen'!BB120 | O113: =+'Invullen groen'!BC120 | P113: =+'Invullen groen'!BD120
A114: =+'Invullen groen'!A121 | B114: =+'Invullen groen'!C121 | C114: =+'Invullen groen'!G121 | D114: =+'Invullen groen'!M121 | E114: =+'Invullen groen'!H121 | F114: =+'Invullen groen'!I121 | G114: =+'Invullen groen'!J121 | H114: =+'Invullen groen'!K121 | I114: =+'Invullen groen'!AW121 | J114: =+'Invullen groen'!AX121 | K114: =+'Invullen groen'!AY121 | L114: =+'Invullen groen'!AZ121 | M114: =+'Invullen groen'!BA121 | N114: =+'Invullen groen'!BB121 | O114: =+'Invullen groen'!BC121 | P114: =+'Invullen groen'!BD121
A115: =+'Invullen groen'!A122 | B115: =+'Invullen groen'!C122 | C115: =+'Invullen groen'!G122 | D115: =+'Invullen groen'!M122 | E115: =+'Invullen groen'!H122 | F115: =+'Invullen groen'!I122 | G115: =+'Invullen groen'!J122 | H115: =+'Invullen groen'!K122 | I115: =+'Invullen groen'!AW122 | J115: =+'Invullen groen'!AX122 | K115: =+'Invullen groen'!AY122 | L115: =+'Invullen groen'!AZ122 | M115: =+'Invullen groen'!BA122 | N115: =+'Invullen groen'!BB122 | O115: =+'Invullen groen'!BC122 | P115: =+'Invullen groen'!BD122
A116: =+'Invullen groen'!A123 | B116: =+'Invullen groen'!C123 | C116: =+'Invullen groen'!G123 | D116: =+'Invullen groen'!M123 | E116: =+'Invullen groen'!H123 | F116: =+'Invullen groen'!I123 | G116: =+'Invullen groen'!J123 | H116: =+'Invullen groen'!K123 | I116: =+'Invullen groen'!AW123 | J116: =+'Invullen groen'!AX123 | K116: =+'Invullen groen'!AY123 | L116: =+'Invullen groen'!AZ123 | M116: =+'Invullen groen'!BA123 | N116: =+'Invullen groen'!BB123 | O116: =+'Invullen groen'!BC123 | P116: =+'Invullen groen'!BD123
A117: =+'Invullen groen'!A124 | B117: =+'Invullen groen'!C124 | C117: =+'Invullen groen'!G124 | D117: =+'Invullen groen'!M124 | E117: =+'Invullen groen'!H124 | F117: =+'Invullen groen'!I124 | G117: =+'Invullen groen'!J124 | H117: =+'Invullen groen'!K124 | I117: =+'Invullen groen'!AW124 | J117: =+'Invullen groen'!AX124 | K117: =+'Invullen groen'!AY124 | L117: =+'Invullen groen'!AZ124 | M117: =+'Invullen groen'!BA124 | N117: =+'Invullen groen'!BB124 | O117: =+'Invullen groen'!BC124 | P117: =+'Invullen groen'!BD124
A118: =+'Invullen groen'!A125 | B118: =+'Invullen groen'!C125 | C118: =+'Invullen groen'!G125 | D118: =+'Invullen groen'!M125 | E118: =+'Invullen groen'!H125 | F118: =+'Invullen groen'!I125 | G118: =+'Invullen groen'!J125 | H118: =+'Invullen groen'!K125 | I118: =+'Invullen groen'!AW125 | J118: =+'Invullen groen'!AX125 | K118: =+'Invullen groen'!AY125 | L118: =+'Invullen groen'!AZ125 | M118: =+'Invullen groen'!BA125 | N118: =+'Invullen groen'!BB125 | O118: =+'Invullen groen'!BC125 | P118: =+'Invullen groen'!BD125
A119: =+'Invullen groen'!A126 | B119: =+'Invullen groen'!C126 | C119: =+'Invullen groen'!G126 | D119: =+'Invullen groen'!M126 | E119: =+'Invullen groen'!H126 | F119: =+'Invullen groen'!I126 | G119: =+'Invullen groen'!J126 | H119: =+'Invullen groen'!K126 | I119: =+'Invullen groen'!AW126 | J119: =+'Invullen groen'!AX126 | K119: =+'Invullen groen'!AY126 | L119: =+'Invullen groen'!AZ126 | M119: =+'Invullen groen'!BA126 | N119: =+'Invullen groen'!BB126 | O119: =+'Invullen groen'!BC126 | P119: =+'Invullen groen'!BD126
A120: =+'Invullen groen'!A127 | B120: =+'Invullen groen'!C127 | C120: =+'Invullen groen'!G127 | D120: =+'Invullen groen'!M127 | E120: =+'Invullen groen'!H127 | F120: =+'Invullen groen'!I127 | G120: =+'Invullen groen'!J127 | H120: =+'Invullen groen'!K127 | I120: =+'Invullen groen'!AW127 | J120: =+'Invullen groen'!AX127 | K120: =+'Invullen groen'!AY127 | L120: =+'Invullen groen'!AZ127 | M120: =+'Invullen groen'!BA127 | N120: =+'Invullen groen'!BB127 | O120: =+'Invullen groen'!BC127 | P120: =+'Invullen groen'!BD127
A121: =+'Invullen groen'!A128 | B121: =+'Invullen groen'!C128 | C121: =+'Invullen groen'!G128 | D121: =+'Invullen groen'!M128 | E121: =+'Invullen groen'!H128 | F121: =+'Invullen groen'!I128 | G121: =+'Invullen groen'!J128 | H121: =+'Invullen groen'!K128 | I121: =+'Invullen groen'!AW128 | J121: =+'Invullen groen'!AX128 | K121: =+'Invullen groen'!AY128 | L121: =+'Invullen groen'!AZ128 | M121: =+'Invullen groen'!BA128 | N121: =+'Invullen groen'!BB128 | O121: =+'Invullen groen'!BC128 | P121: =+'Invullen groen'!BD128
A122: =+'Invullen groen'!A129 | B122: =+'Invullen groen'!C129 | C122: =+'Invullen groen'!G129 | D122: =+'Invullen groen'!M129 | E122: =+'Invullen groen'!H129 | F122: =+'Invullen groen'!I129 | G122: =+'Invullen groen'!J129 | H122: =+'Invullen groen'!K129 | I122: =+'Invullen groen'!AW129 | J122: =+'Invullen groen'!AX129 | K122: =+'Invullen groen'!AY129 | L122: =+'Invullen groen'!AZ129 | M122: =+'Invullen groen'!BA129 | N122: =+'Invullen groen'!BB129 | O122: =+'Invullen groen'!BC129 | P122: =+'Invullen groen'!BD129
... A164: =+'Invullen groen'!A171 | B164: =+'Invullen groen'!C171 | C164: =+'Invullen groen'!G171 | D164: =+'Invullen groen'!M171 | E164: =+'Invullen groen'!H171 | F164: =+'Invullen groen'!I171 | G164: =+'Invullen groen'!J171 | H164: =+'Invullen groen'!K171 | I164: =+'Invullen groen'!AW171 | J164: =+'Invullen groen'!AX171 | K164: =+'Invullen groen'!AY171 | L164: =+'Invullen groen'!AZ171 | M164: =+'Invullen groen'!BA171 | N164: =+'Invullen groen'!BB171 | O164: =+'Invullen groen'!BC171 | P164: =+'Invullen groen'!BD171
A165: =+'Invullen groen'!A171 | B165: =+'Invullen groen'!C171 | C165: =+'Invullen groen'!G171 | D165: =+'Invullen groen'!M171 | E165: =+'Invullen groen'!H171 | F165: =+'Invullen groen'!I171 | G165: =+'Invullen groen'!J171 | H165: =+'Invullen groen'!K171 | I165: =+'Invullen groen'!AW171 | J165: =+'Invullen groen'!AX171 | K165: =+'Invullen groen'!AY171 | L165: =+'Invullen groen'!AZ171 | M165: =+'Invullen groen'!BA171 | N165: =+'Invullen groen'!BB171 | O165: =+'Invullen groen'!BC171 | P165: =+'Invullen groen'!BD171
A166: =+'Invullen groen'!A172 | B166: =+'Invullen groen'!C172 | C166: =+'Invullen groen'!G172 | D166: =+'Invullen groen'!M172 | E166: =+'Invullen groen'!H172 | F166: =+'Invullen groen'!I172 | G166: =+'Invullen groen'!J172 | H166: =+'Invullen groen'!K172 | I166: =+'Invullen groen'!AW172 | J166: =+'Invullen groen'!AX172 | K166: =+'Invullen groen'!AY172 | L166: =+'Invullen groen'!AZ172 | M166: =+'Invullen groen'!BA172 | N166: =+'Invullen groen'!BB172 | O166: =+'Invullen groen'!BC172 | P166: =+'Invullen groen'!BD172
A167: =+'Invullen groen'!A173 | B167: =+'Invullen groen'!C173 | C167: =+'Invullen groen'!G173 | D167: =+'Invullen groen'!M173 | E167: =+'Invullen groen'!H173 | F167: =+'Invullen groen'!I173 | G167: =+'Invullen groen'!J173 | H167: =+'Invullen groen'!K173 | I167: =+'Invullen groen'!AW173 | J167: =+'Invullen groen'!AX173 | K167: =+'Invullen groen'!AY173 | L167: =+'Invullen groen'!AZ173 | M167: =+'Invullen groen'!BA173 | N167: =+'Invullen groen'!BB173 | O167: =+'Invullen groen'!BC173 | P167: =+'Invullen groen'!BD173
A168: =+'Invullen groen'!A174 | B168: =+'Invullen groen'!C174 | C168: =+'Invullen groen'!G174 | D168: =+'Invullen groen'!M174 | E168: =+'Invullen groen'!H174 | F168: =+'Invullen groen'!I174 | G168: =+'Invullen groen'!J174 | H168: =+'Invullen groen'!K174 | I168: =+'Invullen groen'!AW174 | J168: =+'Invullen groen'!AX174 | K168: =+'Invullen groen'!AY174 | L168: =+'Invullen groen'!AZ174 | M168: =+'Invullen groen'!BA174 | N168: =+'Invullen groen'!BB174 | O168: =+'Invullen groen'!BC174 | P168: =+'Invullen groen'!BD174
A169: =+'Invullen groen'!A175 | B169: =+'Invullen groen'!C175 | C169: =+'Invullen groen'!G175 | D169: =+'Invullen groen'!M175 | E169: =+'Invullen groen'!H175 | F169: =+'Invullen groen'!I175 | G169: =+'Invullen groen'!J175 | H169: =+'Invullen groen'!K175 | I169: =+'Invullen groen'!AW175 | J169: =+'Invullen groen'!AX175 | K169: =+'Invullen groen'!AY175 | L169: =+'Invullen groen'!AZ175 | M169: =+'Invullen groen'!BA175 | N169: =+'Invullen groen'!BB175 | O169: =+'Invullen groen'!BC175 | P169: =+'Invullen groen'!BD175
A170: =+'Invullen groen'!A176 | B170: =+'Invullen groen'!C176 | C170: =+'Invullen groen'!G176 | D170: =+'Invullen groen'!M176 | E170: =+'Invullen groen'!H176 | F170: =+'Invullen groen'!I176 | G170: =+'Invullen groen'!J176 | H170: =+'Invullen groen'!K176 | I170: =+'Invullen groen'!AW176 | J170: =+'Invullen groen'!AX176 | K170: =+'Invullen groen'!AY176 | L170: =+'Invullen groen'!AZ176 | M170: =+'Invullen groen'!BA176 | N170: =+'Invullen groen'!BB176 | O170: =+'Invullen groen'!BC176 | P170: =+'Invullen groen'!BD176
A171: =+'Invullen groen'!A177 | B171: =+'Invullen groen'!C177 | C171: =+'Invullen groen'!G177 | D171: =+'Invullen groen'!M177 | E171: =+'Invullen groen'!H177 | F171: =+'Invullen groen'!I177 | G171: =+'Invullen groen'!J177 | H171: =+'Invullen groen'!K177 | I171: =+'Invullen groen'!AW177 | J171: =+'Invullen groen'!AX177 | K171: =+'Invullen groen'!AY177 | L171: =+'Invullen groen'!AZ177 | M171: =+'Invullen groen'!BA177 | N171: =+'Invullen groen'!BB177 | O171: =+'Invullen groen'!BC177 | P171: =+'Invullen groen'!BD177
A172: =+'Invullen groen'!A178 | B172: =+'Invullen groen'!C178 | C172: =+'Invullen groen'!G178 | D172: =+'Invullen groen'!M178 | E172: =+'Invullen groen'!H178 | F172: =+'Invullen groen'!I178 | G172: =+'Invullen groen'!J178 | H172: =+'Invullen groen'!K178 | I172: =+'Invullen groen'!AW178 | J172: =+'Invullen groen'!AX178 | K172: =+'Invullen groen'!AY178 | L172: =+'Invullen groen'!AZ178 | M172: =+'Invullen groen'!BA178 | N172: =+'Invullen groen'!BB178 | O172: =+'Invullen groen'!BC178 | P172: =+'Invullen groen'!BD178
A173: =+'Invullen groen'!A179 | B173: =+'Invullen groen'!C179 | C173: =+'Invullen groen'!G179 | D173: =+'Invullen groen'!M179 | E173: =+'Invullen groen'!H179 | F173: =+'Invullen groen'!I179 | G173: =+'Invullen groen'!J179 | H173: =+'Invullen groen'!K179 | I173: =+'Invullen groen'!AW179 | J173: =+'Invullen groen'!AX179 | K173: =+'Invullen groen'!AY179 | L173: =+'Invullen groen'!AZ179 | M173: =+'Invullen groen'!BA179 | N173: =+'Invullen groen'!BB179 | O173: =+'Invullen groen'!BC179 | P173: =+'Invullen groen'!BD179
A174: =+'Invullen groen'!A180 | B174: =+'Invullen groen'!C180 | C174: =+'Invullen groen'!G180 | D174: =+'Invullen groen'!M180 | E174: =+'Invullen groen'!H180 | F174: =+'Invullen groen'!I180 | G174: =+'Invullen groen'!J180 | H174: =+'Invullen groen'!K180 | I174: =+'Invullen groen'!AW180 | J174: =+'Invullen groen'!AX180 | K174: =+'Invullen groen'!AY180 | L174: =+'Invullen groen'!AZ180 | M174: =+'Invullen groen'!BA180 | N174: =+'Invullen groen'!BB180 | O174: =+'Invullen groen'!BC180 | P174: =+'Invullen groen'!BD180
A175: =+'Invullen groen'!A181 | B175: =+'Invullen groen'!C181 | C175: =+'Invullen groen'!G181 | D175: =+'Invullen groen'!M181 | E175: =+'Invullen groen'!H181 | F175: =+'Invullen groen'!I181 | G175: =+'Invullen groen'!J181 | H175: =+'Invullen groen'!K181 | I175: =+'Invullen groen'!AW181 | J175: =+'Invullen groen'!AX181 | K175: =+'Invullen groen'!AY181 | L175: =+'Invullen groen'!AZ181 | M175: =+'Invullen groen'!BA181 | N175: =+'Invullen groen'!BB181 | O175: =+'Invullen groen'!BC181 | P175: =+'Invullen groen'!BD181
A176: =+'Invullen groen'!A182 | B176: =+'Invullen groen'!C182 | C176: =+'Invullen groen'!G182 | D176: =+'Invullen groen'!M182 | E176: =+'Invullen groen'!H182 | F176: =+'Invullen groen'!I182 | G176: =+'Invullen groen'!J182 | H176: =+'Invullen groen'!K182 | I176: =+'Invullen groen'!AW182 | J176: =+'Invullen groen'!AX182 | K176: =+'Invullen groen'!AY182 | L176: =+'Invullen groen'!AZ182 | M176: =+'Invullen groen'!BA182 | N176: =+'Invullen groen'!BB182 | O176: =+'Invullen groen'!BC182 | P176: =+'Invullen groen'!BD182
... A268: =+'Invullen groen'!A274 | B268: =+'Invullen groen'!C274 | C268: =+'Invullen groen'!G274 | D268: =+'Invullen groen'!M274 | E268: =+'Invullen groen'!H274 | F268: =+'Invullen groen'!I274 | G268: =+'Invullen groen'!J274 | H268: =+'Invullen groen'!K274 | I268: =+'Invullen groen'!AW274 | J268: =+'Invullen groen'!AX274 | K268: =+'Invullen groen'!AY274 | L268: =+'Invullen groen'!AZ274 | M268: =+'Invullen groen'!BA274 | N268: =+'Invullen groen'!BB274 | O268: =+'Invullen groen'!BC274 | P268: =+'Invullen groen'!BD274
A269: =+'Invullen groen'!A279 | B269: =+'Invullen groen'!C279 | C269: =+'Invullen groen'!G279 | D269: =+'Invullen groen'!M279 | E269: =+'Invullen groen'!H279 | F269: =+'Invullen groen'!I279 | G269: =+'Invullen groen'!J279 | H269: =+'Invullen groen'!K279 | I269: =+'Invullen groen'!AW279 | J269: =+'Invullen groen'!AX279 | K269: =+'Invullen groen'!AY279 | L269: =+'Invullen groen'!AZ279 | M269: =+'Invullen groen'!BA279 | N269: =+'Invullen groen'!BB279 | O269: =+'Invullen groen'!BC279 | P269: =+'Invullen groen'!BD279
A270: Aldus vastgesteld in de raadsvergadering van: | C270: x-xx-2026 | J270: =+'Invullen groen'!AX280 | K270: =+'Invullen groen'!AY280 | L270: =+'Invullen groen'!AZ280 | M270: =+'Invullen groen'!BA280 | N270: =+'Invullen groen'!BB280 | O270: =+'Invullen groen'!BC280 | P270: =+'Invullen groen'!BD280
J271: =+'Invullen groen'!AX281 | K271: =+'Invullen groen'!AY281 | L271: =+'Invullen groen'!AZ281 | M271: =+'Invullen groen'!BA281 | N271: =+'Invullen groen'!BB281 | O271: =+'Invullen groen'!BC281 | P271: =+'Invullen groen'!BD281
A272: De Gemeenteraad, | J272: =+'Invullen groen'!AX282 | K272: =+'Invullen groen'!AY282 | L272: =+'Invullen groen'!AZ282 | M272: =+'Invullen groen'!BA282 | N272: =+'Invullen groen'!BB282 | O272: =+'Invullen groen'!BC282 | P272: =+'Invullen groen'!BD282
J273: =+'Invullen groen'!AX283 | K273: =+'Invullen groen'!AY283 | L273: =+'Invullen groen'!AZ283 | M273: =+'Invullen groen'!BA283 | N273: =+'Invullen groen'!BB283 | O273: =+'Invullen groen'!BC283 | P273: =+'Invullen groen'!BD283
A274: De Griffier, | C274: De voorzitter, | J274: =+'Invullen groen'!AX284 | K274: =+'Invullen groen'!AY284 | L274: =+'Invullen groen'!AZ284 | M274: =+'Invullen groen'!BA284 | N274: =+'Invullen groen'!BB284 | O274: =+'Invullen groen'!BC284 | P274: =+'Invullen groen'!BD284
J275: =+'Invullen groen'!AX285 | K275: =+'Invullen groen'!AY285 | L275: =+'Invullen groen'!AZ285 | M275: =+'Invullen groen'!BA285 | N275: =+'Invullen groen'!BB285 | O275: =+'Invullen groen'!BC285 | P275: =+'Invullen groen'!BD285
J276: =+'Invullen groen'!AX286 | K276: =+'Invullen groen'!AY286 | L276: =+'Invullen groen'!AZ286 | M276: =+'Invullen groen'!BA286 | N276: =+'Invullen groen'!BB286 | O276: =+'Invullen groen'!BC286 | P276: =+'Invullen groen'!BD286
J277: =+'Invullen groen'!AX287 | K277: =+'Invullen groen'!AY287 | L277: =+'Invullen groen'!AZ287 | M277: =+'Invullen groen'!BA287 | N277: =+'Invullen groen'!BB287 | O277: =+'Invullen groen'!BC287 | P277: =+'Invullen groen'!BD287
J278: =+'Invullen groen'!AX288 | K278: =+'Invullen groen'!AY288 | L278: =+'Invullen groen'!AZ288 | M278: =+'Invullen groen'!BA288 | N278: =+'Invullen groen'!BB288 | O278: =+'Invullen groen'!BC288 | P278: =+'Invullen groen'!BD288
J279: =+'Invullen groen'!AX289 | K279: =+'Invullen groen'!AY289 | L279: =+'Invullen groen'!AZ289 | M279: =+'Invullen groen'!BA289 | N279: =+'Invullen groen'!BB289 | O279: =+'Invullen groen'!BC289 | P279: =+'Invullen groen'!BD289
A280: R. Swinkels- van de Laar | C280: R. Donders- de Leest | J280: =+'Invullen groen'!AX290 | K280: =+'Invullen groen'!AY290 | L280: =+'Invullen groen'!AZ290 | M280: =+'Invullen groen'!BA290 | N280: =+'Invullen groen'!BB290 | O280: =+'Invullen groen'!BC290 | P280: =+'Invullen groen'!BD290
J281: =+'Invullen groen'!AX291 | K281: =+'Invullen groen'!AY291 | L281: =+'Invullen groen'!AZ291 | M281: =+'Invullen groen'!BA291 | N281: =+'Invullen groen'!BB291 | O281: =+'Invullen groen'!BC291 | P281: =+'Invullen groen'!BD291
J282: =+'Invullen groen'!AX292 | K282: =+'Invullen groen'!AY292 | L282: =+'Invullen groen'!AZ292 | M282: =+'Invullen groen'!BA292 | N282: =+'Invullen groen'!BB292 | O282: =+'Invullen groen'!BC292 | P282: =+'Invullen groen'!BD292
J283: =+'Invullen groen'!AX293 | K283: =+'Invullen groen'!AY293 | L283: =+'Invullen groen'!AZ293 | M283: =+'Invullen groen'!BA293 | N283: =+'Invullen groen'!BB293 | O283: =+'Invullen groen'!BC293 | P283: =+'Invullen groen'!BD293
J284: =+'Invullen groen'!AX294 | K284: =+'Invullen groen'!AY294 | L284: =+'Invullen groen'!AZ294 | M284: =+'Invullen groen'!BA294 | N284: =+'Invullen groen'!BB294 | O284: =+'Invullen groen'!BC294 | P284: =+'Invullen groen'!BD294
J285: =+'Invullen groen'!AX295 | K285: =+'Invullen groen'!AY295 | L285: =+'Invullen groen'!AZ295 | M285: =+'Invullen groen'!BA295 | N285: =+'Invullen groen'!BB295 | O285: =+'Invullen groen'!BC295 | P285: =+'Invullen groen'!BD295
J286: =+'Invullen groen'!AX296 | K286: =+'Invullen groen'!AY296 | L286: =+'Invullen groen'!AZ296 | M286: =+'Invullen groen'!BA296 | N286: =+'Invullen groen'!BB296 | O286: =+'Invullen groen'!BC296 | P286: =+'Invullen groen'!BD296
J287: =+'Invullen groen'!AX297 | K287: =+'Invullen groen'!AY297 | L287: =+'Invullen groen'!AZ297 | M287: =+'Invullen groen'!BA297 | N287: =+'Invullen groen'!BB297 | O287: =+'Invullen groen'!BC297 | P287: =+'Invullen groen'!BD297
J288: =+'Invullen groen'!AX298 | K288: =+'Invullen groen'!AY298 | L288: =+'Invullen groen'!AZ298 | M288: =+'Invullen groen'!BA298 | N288: =+'Invullen groen'!BB298 | O288: =+'Invullen groen'!BC298 | P288: =+'Invullen groen'!BD298
A289: =+'Invullen groen'!A299 | B289: =+'Invullen groen'!C299 | C289: =+'Invullen groen'!G299 | D289: =+'Invullen groen'!M299 | E289: =+'Invullen groen'!H299 | F289: =+'Invullen groen'!I299 | G289: =+'Invullen groen'!J299 | H289: =+'Invullen groen'!K299 | I289: =+'Invullen groen'!AW299 | J289: =+'Invullen groen'!AX299 | K289: =+'Invullen groen'!AY299 | L289: =+'Invullen groen'!AZ299 | M289: =+'Invullen groen'!BA299 | N289: =+'Invullen groen'!BB299 | O289: =+'Invullen groen'!BC299 | P289: =+'Invullen groen'!BD299
A290: =+'Invullen groen'!A300 | B290: =+'Invullen groen'!C300 | C290: =+'Invullen groen'!G300 | D290: =+'Invullen groen'!M300 | E290: =+'Invullen groen'!H300 | F290: =+'Invullen groen'!I300 | G290: =+'Invullen groen'!J300 | H290: =+'Invullen groen'!K300 | I290: =+'Invullen groen'!AW300 | J290: =+'Invullen groen'!AX300 | K290: =+'Invullen groen'!AY300 | L290: =+'Invullen groen'!AZ300 | M290: =+'Invullen groen'!BA300 | N290: =+'Invullen groen'!BB300 | O290: =+'Invullen groen'!BC300 | P290: =+'Invullen groen'!BD300
A291: =+'Invullen groen'!A301 | B291: =+'Invullen groen'!C301 | C291: =+'Invullen groen'!G301 | D291: =+'Invullen groen'!M301 | E291: =+'Invullen groen'!H301 | F291: =+'Invullen groen'!I301 | G291: =+'Invullen groen'!J301 | H291: =+'Invullen groen'!K301 | I291: =+'Invullen groen'!AW301 | J291: =+'Invullen groen'!AX301 | K291: =+'Invullen groen'!AY301 | L291: =+'Invullen groen'!AZ301 | M291: =+'Invullen groen'!BA301 | N291: =+'Invullen groen'!BB301 | O291: =+'Invullen groen'!BC301 | P291: =+'Invullen groen'!BD301
A292: =+'Invullen groen'!A302 | B292: =+'Invullen groen'!C302 | C292: =+'Invullen groen'!G302 | D292: =+'Invullen groen'!M302 | E292: =+'Invullen groen'!H302 | F292: =+'Invullen groen'!I302 | G292: =+'Invullen groen'!J302 | H292: =+'Invullen groen'!K302 | I292: =+'Invullen groen'!AW302 | J292: =+'Invullen groen'!AX302 | K292: =+'Invullen groen'!AY302 | L292: =+'Invullen groen'!AZ302 | M292: =+'Invullen groen'!BA302 | N292: =+'Invullen groen'!BB302 | O292: =+'Invullen groen'!BC302 | P292: =+'Invullen groen'!BD302
A293: =+'Invullen groen'!A303 | B293: =+'Invullen groen'!C303 | C293: =+'Invullen groen'!G303 | D293: =+'Invullen groen'!M303 | E293: =+'Invullen groen'!H303 | F293: =+'Invullen groen'!I303 | G293: =+'Invullen groen'!J303 | H293: =+'Invullen groen'!K303 | I293: =+'Invullen groen'!AW303 | J293: =+'Invullen groen'!AX303 | K293: =+'Invullen groen'!AY303 | L293: =+'Invullen groen'!AZ303 | M293: =+'Invullen groen'!BA303 | N293: =+'Invullen groen'!BB303 | O293: =+'Invullen groen'!BC303 | P293: =+'Invullen groen'!BD303
A294: =+'Invullen groen'!A304 | B294: =+'Invullen groen'!C304 | C294: =+'Invullen groen'!G304 | D294: =+'Invullen groen'!M304 | E294: =+'Invullen groen'!H304 | F294: =+'Invullen groen'!I304 | G294: =+'Invullen groen'!J304 | H294: =+'Invullen groen'!K304 | I294: =+'Invullen groen'!AW304 | J294: =+'Invullen groen'!AX304 | K294: =+'Invullen groen'!AY304 | L294: =+'Invullen groen'!AZ304 | M294: =+'Invullen groen'!BA304 | N294: =+'Invullen groen'!BB304 | O294: =+'Invullen groen'!BC304 | P294: =+'Invullen groen'!BD304
A295: =+'Invullen groen'!A305 | B295: =+'Invullen groen'!C305 | C295: =+'Invullen groen'!G305 | D295: =+'Invullen groen'!M305 | E295: =+'Invullen groen'!H305 | F295: =+'Invullen groen'!I305 | G295: =+'Invullen groen'!J305 | H295: =+'Invullen groen'!K305 | I295: =+'Invullen groen'!AW305 | J295: =+'Invullen groen'!AX305 | K295: =+'Invullen groen'!AY305 | L295: =+'Invullen groen'!AZ305 | M295: =+'Invullen groen'!BA305 | N295: =+'Invullen groen'!BB305 | O295: =+'Invullen groen'!BC305 | P295: =+'Invullen groen'!BD305
A296: =+'Invullen groen'!A306 | B296: =+'Invullen groen'!C306 | C296: =+'Invullen groen'!G306 | D296: =+'Invullen groen'!M306 | E296: =+'Invullen groen'!H306 | F296: =+'Invullen groen'!I306 | G296: =+'Invullen groen'!J306 | H296: =+'Invullen groen'!K306 | I296: =+'Invullen groen'!AW306 | J296: =+'Invullen groen'!AX306 | K296: =+'Invullen groen'!AY306 | L296: =+'Invullen groen'!AZ306 | M296: =+'Invullen groen'!BA306 | N296: =+'Invullen groen'!BB306 | O296: =+'Invullen groen'!BC306 | P296: =+'Invullen groen'!BD306
A297: =+'Invullen groen'!A307 | B297: =+'Invullen groen'!C307 | C297: =+'Invullen groen'!G307 | D297: =+'Invullen groen'!M307 | E297: =+'Invullen groen'!H307 | F297: =+'Invullen groen'!I307 | G297: =+'Invullen groen'!J307 | H297: =+'Invullen groen'!K307 | I297: =+'Invullen groen'!AW307 | J297: =+'Invullen groen'!AX307 | K297: =+'Invullen groen'!AY307 | L297: =+'Invullen groen'!AZ307 | M297: =+'Invullen groen'!BA307 | N297: =+'Invullen groen'!BB307 | O297: =+'Invullen groen'!BC307 | P297: =+'Invullen groen'!BD307
A298: =+'Invullen groen'!A308 | B298: =+'Invullen groen'!C308 | C298: =+'Invullen groen'!G308 | D298: =+'Invullen groen'!M308 | E298: =+'Invullen groen'!H308 | F298: =+'Invullen groen'!I308 | G298: =+'Invullen groen'!J308 | H298: =+'Invullen groen'!K308 | I298: =+'Invullen groen'!AW308 | J298: =+'Invullen groen'!AX308 | K298: =+'Invullen groen'!AY308 | L298: =+'Invullen groen'!AZ308 | M298: =+'Invullen groen'!BA308 | N298: =+'Invullen groen'!BB308 | O298: =+'Invullen groen'!BC308 | P298: =+'Invullen groen'!BD308
A299: =+'Invullen groen'!A309 | B299: =+'Invullen groen'!C309 | C299: =+'Invullen groen'!G309 | D299: =+'Invullen groen'!M309 | E299: =+'Invullen groen'!H309 | F299: =+'Invullen groen'!I309 | G299: =+'Invullen groen'!J309 | H299: =+'Invullen groen'!K309 | I299: =+'Invullen groen'!AW309 | J299: =+'Invullen groen'!AX309 | K299: =+'Invullen groen'!AY309 | L299: =+'Invullen groen'!AZ309 | M299: =+'Invullen groen'!BA309 | N299: =+'Invullen groen'!BB309 | O299: =+'Invullen groen'!BC309 | P299: =+'Invullen groen'!BD309
A300: =+'Invullen groen'!A310 | B300: =+'Invullen groen'!C310 | C300: =+'Invullen groen'!G310 | D300: =+'Invullen groen'!M310 | E300: =+'Invullen groen'!H310 | F300: =+'Invullen groen'!I310 | G300: =+'Invullen groen'!J310 | H300: =+'Invullen groen'!K310 | I300: =+'Invullen groen'!AW310 | J300: =+'Invullen groen'!AX310 | K300: =+'Invullen groen'!AY310 | L300: =+'Invullen groen'!AZ310 | M300: =+'Invullen groen'!BA310 | N300: =+'Invullen groen'!BB310 | O300: =+'Invullen groen'!BC310 | P300: =+'Invullen groen'!BD310
... A1135: =+'Invullen groen'!A1145 | B1135: =+'Invullen groen'!C1145 | C1135: =+'Invullen groen'!G1145 | D1135: =+'Invullen groen'!M1145 | E1135: =+'Invullen groen'!H1145 | F1135: =+'Invullen groen'!I1145 | G1135: =+'Invullen groen'!J1145 | H1135: =+'Invullen groen'!K1145 | I1135: =+'Invullen groen'!AW1145 | J1135: =+'Invullen groen'!AX1145 | K1135: =+'Invullen groen'!AY1145 | L1135: =+'Invullen groen'!AZ1145 | M1135: =+'Invullen groen'!BA1145 | N1135: =+'Invullen groen'!BB1145 | O1135: =+'Invullen groen'!BC1145 | P1135: =+'Invullen groen'!BD1145

Sheet Totaaloverzicht
A1: Totaaloverzicht begrotingswijziging
A2: ='Invullen groen'!A4 | G2: Corsanr.:
A4: Nr. | B4: Programma | C4: Taakveld | D4: Omschrijving taakveld | E4: Omschrijving grootboek | F4: Bgr.jaar | G4: MJR 2027 | H4: MJR 2028 | I4: MJR 2029
A5: =IFERROR(IF($J5>0,ROW()-4,""),"") | B5: =IFERROR(IF($J5>0,INDEX('Invullen groen'!$A:$A,$J5),""),"") | C5: =IFERROR(IF($J5>0,INDEX('Invullen groen'!$C:$C,$J5),""),"") | D5: =IFERROR(IF($J5>0,INDEX('Invullen groen'!$D:$D,$J5),""),"") | E5: =IFERROR(IF($J5>0,INDEX('Invullen groen'!$G:$G,$J5),""),"") | F5: =IFERROR(IF($J5>0,IF(INDEX('Invullen groen'!$H:$H,$J5)<>0,INDEX('Invullen groen'!$H:$H,$J5),""),""),"") | G5: =IFERROR(IF($J5>0,IF(INDEX('Invullen groen'!$I:$I,$J5)<>0,INDEX('Invullen groen'!$I:$I,$J5),""),""),"") | H5: =IFERROR(IF($J5>0,IF(INDEX('Invullen groen'!$J:$J,$J5)<>0,INDEX('Invullen groen'!$J:$J,$J5),""),""),"") | I5: =IFERROR(IF($J5>0,IF(INDEX('Invullen groen'!$K:$K,$J5)<>0,INDEX('Invullen groen'!$K:$K,$J5),""),""),"") | J5: =IFERROR(MATCH(ROW()-4,'Invullen groen'!$P$17:$P$272,0)+16,0)
A6: =IFERROR(IF($J6>0,ROW()-4,""),"") | B6: =IFERROR(IF($J6>0,INDEX('Invullen groen'!$A:$A,$J6),""),"") | C6: =IFERROR(IF($J6>0,INDEX('Invullen groen'!$C:$C,$J6),""),"") | D6: =IFERROR(IF($J6>0,INDEX('Invullen groen'!$D:$D,$J6),""),"") | E6: =IFERROR(IF($J6>0,INDEX('Invullen groen'!$G:$G,$J6),""),"") | F6: =IFERROR(IF($J6>0,IF(INDEX('Invullen groen'!$H:$H,$J6)<>0,INDEX('Invullen groen'!$H:$H,$J6),""),""),"") | G6: =IFERROR(IF($J6>0,IF(INDEX('Invullen groen'!$I:$I,$J6)<>0,INDEX('Invullen groen'!$I:$I,$J6),""),""),"") | H6: =IFERROR(IF($J6>0,IF(INDEX('Invullen groen'!$J:$J,$J6)<>0,INDEX('Invullen groen'!$J:$J,$J6),""),""),"") | I6: =IFERROR(IF($J6>0,IF(INDEX('Invullen groen'!$K:$K,$J6)<>0,INDEX('Invullen groen'!$K:$K,$J6),""),""),"") | J6: =IFERROR(MATCH(ROW()-4,'Invullen groen'!$P$17:$P$272,0)+16,0)
A7: =IFERROR(IF($J7>0,ROW()-4,""),"") | B7: =IFERROR(IF($J7>0,INDEX('Invullen groen'!$A:$A,$J7),""),"") | C7: =IFERROR(IF($J7>0,INDEX('Invullen groen'!$C:$C,$J7),""),"") | D7: =IFERROR(IF($J7>0,INDEX('Invullen groen'!$D:$D,$J7),""),"") | E7: =IFERROR(IF($J7>0,INDEX('Invullen groen'!$G:$G,$J7),""),"") | F7: =IFERROR(IF($J7>0,IF(INDEX('Invullen groen'!$H:$H,$J7)<>0,INDEX('Invullen groen'!$H:$H,$J7),""),""),"") | G7: =IFERROR(IF($J7>0,IF(INDEX('Invullen groen'!$I:$I,$J7)<>0,INDEX('Invullen groen'!$I:$I,$J7),""),""),"") | H7: =IFERROR(IF($J7>0,IF(INDEX('Invullen groen'!$J:$J,$J7)<>0,INDEX('Invullen groen'!$J:$J,$J7),""),""),"") | I7: =IFERROR(IF($J7>0,IF(INDEX('Invullen groen'!$K:$K,$J7)<>0,INDEX('Invullen groen'!$K:$K,$J7),""),""),"") | J7: =IFERROR(MATCH(ROW()-4,'Invullen groen'!$P$17:$P$272,0)+16,0)
A8: =IFERROR(IF($J8>0,ROW()-4,""),"") | B8: =IFERROR(IF($J8>0,INDEX('Invullen groen'!$A:$A,$J8),""),"") | C8: =IFERROR(IF($J8>0,INDEX('Invullen groen'!$C:$C,$J8),""),"") | D8: =IFERROR(IF($J8>0,INDEX('Invullen groen'!$D:$D,$J8),""),"") | E8: =IFERROR(IF($J8>0,INDEX('Invullen groen'!$G:$G,$J8),""),"") | F8: =IFERROR(IF($J8>0,IF(INDEX('Invullen groen'!$H:$H,$J8)<>0,INDEX('Invullen groen'!$H:$H,$J8),""),""),"") | G8: =IFERROR(IF($J8>0,IF(INDEX('Invullen groen'!$I:$I,$J8)<>0,INDEX('Invullen groen'!$I:$I,$J8),""),""),"") | H8: =IFERROR(IF($J8>0,IF(INDEX('Invullen groen'!$J:$J,$J8)<>0,INDEX('Invullen groen'!$J:$J,$J8),""),""),"") | I8: =IFERROR(IF($J8>0,IF(INDEX('Invullen groen'!$K:$K,$J8)<>0,INDEX('Invullen groen'!$K:$K,$J8),""),""),"") | J8: =IFERROR(MATCH(ROW()-4,'Invullen groen'!$P$17:$P$272,0)+16,0)
A9: =IFERROR(IF($J9>0,ROW()-4,""),"") | B9: =IFERROR(IF($J9>0,INDEX('Invullen groen'!$A:$A,$J9),""),"") | C9: =IFERROR(IF($J9>0,INDEX('Invullen groen'!$C:$C,$J9),""),"") | D9: =IFERROR(IF($J9>0,INDEX('Invullen groen'!$D:$D,$J9),""),"") | E9: =IFERROR(IF($J9>0,INDEX('Invullen groen'!$G:$G,$J9),""),"") | F9: =IFERROR(IF($J9>0,IF(INDEX('Invullen groen'!$H:$H,$J9)<>0,INDEX('Invullen groen'!$H:$H,$J9),""),""),"") | G9: =IFERROR(IF($J9>0,IF(INDEX('Invullen groen'!$I:$I,$J9)<>0,INDEX('Invullen groen'!$I:$I,$J9),""),""),"") | H9: =IFERROR(IF($J9>0,IF(INDEX('Invullen groen'!$J:$J,$J9)<>0,INDEX('Invullen groen'!$J:$J,$J9),""),""),"") | I9: =IFERROR(IF($J9>0,IF(INDEX('Invullen groen'!$K:$K,$J9)<>0,INDEX('Invullen groen'!$K:$K,$J9),""),""),"") | J9: =IFERROR(MATCH(ROW()-4,'Invullen groen'!$P$17:$P$272,0)+16,0)
A10: =IFERROR(IF($J10>0,ROW()-4,""),"") | B10: =IFERROR(IF($J10>0,INDEX('Invullen groen'!$A:$A,$J10),""),"") | C10: =IFERROR(IF($J10>0,INDEX('Invullen groen'!$C:$C,$J10),""),"") | D10: =IFERROR(IF($J10>0,INDEX('Invullen groen'!$D:$D,$J10),""),"") | E10: =IFERROR(IF($J10>0,INDEX('Invullen groen'!$G:$G,$J10),""),"") | F10: =IFERROR(IF($J10>0,IF(INDEX('Invullen groen'!$H:$H,$J10)<>0,INDEX('Invullen groen'!$H:$H,$J10),""),""),"") | G10: =IFERROR(IF($J10>0,IF(INDEX('Invullen groen'!$I:$I,$J10)<>0,INDEX('Invullen groen'!$I:$I,$J10),""),""),"") | H10: =IFERROR(IF($J10>0,IF(INDEX('Invullen groen'!$J:$J,$J10)<>0,INDEX('Invullen groen'!$J:$J,$J10),""),""),"") | I10: =IFERROR(IF($J10>0,IF(INDEX('Invullen groen'!$K:$K,$J10)<>0,INDEX('Invullen groen'!$K:$K,$J10),""),""),"") | J10: =IFERROR(MATCH(ROW()-4,'Invullen groen'!$P$17:$P$272,0)+16,0)
A11: =IFERROR(IF($J11>0,ROW()-4,""),"") | B11: =IFERROR(IF($J11>0,INDEX('Invullen groen'!$A:$A,$J11),""),"") | C11: =IFERROR(IF($J11>0,INDEX('Invullen groen'!$C:$C,$J11),""),"") | D11: =IFERROR(IF($J11>0,INDEX('Invullen groen'!$D:$D,$J11),""),"") | E11: =IFERROR(IF($J11>0,INDEX('Invullen groen'!$G:$G,$J11),""),"") | F11: =IFERROR(IF($J11>0,IF(INDEX('Invullen groen'!$H:$H,$J11)<>0,INDEX('Invullen groen'!$H:$H,$J11),""),""),"") | G11: =IFERROR(IF($J11>0,IF(INDEX('Invullen groen'!$I:$I,$J11)<>0,INDEX('Invullen groen'!$I:$I,$J11),""),""),"") | H11: =IFERROR(IF($J11>0,IF(INDEX('Invullen groen'!$J:$J,$J11)<>0,INDEX('Invullen groen'!$J:$J,$J11),""),""),"") | I11: =IFERROR(IF($J11>0,IF(INDEX('Invullen groen'!$K:$K,$J11)<>0,INDEX('Invullen groen'!$K:$K,$J11),""),""),"") | J11: =IFERROR(MATCH(ROW()-4,'Invullen groen'!$P$17:$P$272,0)+16,0)
A12: =IFERROR(IF($J12>0,ROW()-4,""),"") | B12: =IFERROR(IF($J12>0,INDEX('Invullen groen'!$A:$A,$J12),""),"") | C12: =IFERROR(IF($J12>0,INDEX('Invullen groen'!$C:$C,$J12),""),"") | D12: =IFERROR(IF($J12>0,INDEX('Invullen groen'!$D:$D,$J12),""),"") | E12: =IFERROR(IF($J12>0,INDEX('Invullen groen'!$G:$G,$J12),""),"") | F12: =IFERROR(IF($J12>0,IF(INDEX('Invullen groen'!$H:$H,$J12)<>0,INDEX('Invullen groen'!$H:$H,$J12),""),""),"") | G12: =IFERROR(IF($J12>0,IF(INDEX('Invullen groen'!$I:$I,$J12)<>0,INDEX('Invullen groen'!$I:$I,$J12),""),""),"") | H12: =IFERROR(IF($J12>0,IF(INDEX('Invullen groen'!$J:$J,$J12)<>0,INDEX('Invullen groen'!$J:$J,$J12),""),""),"") | I12: =IFERROR(IF($J12>0,IF(INDEX('Invullen groen'!$K:$K,$J12)<>0,INDEX('Invullen groen'!$K:$K,$J12),""),""),"") | J12: =IFERROR(MATCH(ROW()-4,'Invullen groen'!$P$17:$P$272,0)+16,0)
A13: =IFERROR(IF($J13>0,ROW()-4,""),"") | B13: =IFERROR(IF($J13>0,INDEX('Invullen groen'!$A:$A,$J13),""),"") | C13: =IFERROR(IF($J13>0,INDEX('Invullen groen'!$C:$C,$J13),""),"") | D13: =IFERROR(IF($J13>0,INDEX('Invullen groen'!$D:$D,$J13),""),"") | E13: =IFERROR(IF($J13>0,INDEX('Invullen groen'!$G:$G,$J13),""),"") | F13: =IFERROR(IF($J13>0,IF(INDEX('Invullen groen'!$H:$H,$J13)<>0,INDEX('Invullen groen'!$H:$H,$J13),""),""),"") | G13: =IFERROR(IF($J13>0,IF(INDEX('Invullen groen'!$I:$I,$J13)<>0,INDEX('Invullen groen'!$I:$I,$J13),""),""),"") | H13: =IFERROR(IF($J13>0,IF(INDEX('Invullen groen'!$J:$J,$J13)<>0,INDEX('Invullen groen'!$J:$J,$J13),""),""),"") | I13: =IFERROR(IF($J13>0,IF(INDEX('Invullen groen'!$K:$K,$J13)<>0,INDEX('Invullen groen'!$K:$K,$J13),""),""),"") | J13: =IFERROR(MATCH(ROW()-4,'Invullen groen'!$P$17:$P$272,0)+16,0)
A14: =IFERROR(IF($J14>0,ROW()-4,""),"") | B14: =IFERROR(IF($J14>0,INDEX('Invullen groen'!$A:$A,$J14),""),"") | C14: =IFERROR(IF($J14>0,INDEX('Invullen groen'!$C:$C,$J14),""),"") | D14: =IFERROR(IF($J14>0,INDEX('Invullen groen'!$D:$D,$J14),""),"") | E14: =IFERROR(IF($J14>0,INDEX('Invullen groen'!$G:$G,$J14),""),"") | F14: =IFERROR(IF($J14>0,IF(INDEX('Invullen groen'!$H:$H,$J14)<>0,INDEX('Invullen groen'!$H:$H,$J14),""),""),"") | G14: =IFERROR(IF($J14>0,IF(INDEX('Invullen groen'!$I:$I,$J14)<>0,INDEX('Invullen groen'!$I:$I,$J14),""),""),"") | H14: =IFERROR(IF($J14>0,IF(INDEX('Invullen groen'!$J:$J,$J14)<>0,INDEX('Invullen groen'!$J:$J,$J14),""),""),"") | I14: =IFERROR(IF($J14>0,IF(INDEX('Invullen groen'!$K:$K,$J14)<>0,INDEX('Invullen groen'!$K:$K,$J14),""),""),"") | J14: =IFERROR(MATCH(ROW()-4,'Invullen groen'!$P$17:$P$272,0)+16,0)
A15: =IFERROR(IF($J15>0,ROW()-4,""),"") | B15: =IFERROR(IF($J15>0,INDEX('Invullen groen'!$A:$A,$J15),""),"") | C15: =IFERROR(IF($J15>0,INDEX('Invullen groen'!$C:$C,$J15),""),"") | D15: =IFERROR(IF($J15>0,INDEX('Invullen groen'!$D:$D,$J15),""),"") | E15: =IFERROR(IF($J15>0,INDEX('Invullen groen'!$G:$G,$J15),""),"") | F15: =IFERROR(IF($J15>0,IF(INDEX('Invullen groen'!$H:$H,$J15)<>0,INDEX('Invullen groen'!$H:$H,$J15),""),""),"") | G15: =IFERROR(IF($J15>0,IF(INDEX('Invullen groen'!$I:$I,$J15)<>0,INDEX('Invullen groen'!$I:$I,$J15),""),""),"") | H15: =IFERROR(IF($J15>0,IF(INDEX('Invullen groen'!$J:$J,$J15)<>0,INDEX('Invullen groen'!$J:$J,$J15),""),""),"") | I15: =IFERROR(IF($J15>0,IF(INDEX('Invullen groen'!$K:$K,$J15)<>0,INDEX('Invullen groen'!$K:$K,$J15),""),""),"") | J15: =IFERROR(MATCH(ROW()-4,'Invullen groen'!$P$17:$P$272,0)+16,0)
A16: =IFERROR(IF($J16>0,ROW()-4,""),"") | B16: =IFERROR(IF($J16>0,INDEX('Invullen groen'!$A:$A,$J16),""),"") | C16: =IFERROR(IF($J16>0,INDEX('Invullen groen'!$C:$C,$J16),""),"") | D16: =IFERROR(IF($J16>0,INDEX('Invullen groen'!$D:$D,$J16),""),"") | E16: =IFERROR(IF($J16>0,INDEX('Invullen groen'!$G:$G,$J16),""),"") | F16: =IFERROR(IF($J16>0,IF(INDEX('Invullen groen'!$H:$H,$J16)<>0,INDEX('Invullen groen'!$H:$H,$J16),""),""),"") | G16: =IFERROR(IF($J16>0,IF(INDEX('Invullen groen'!$I:$I,$J16)<>0,INDEX('Invullen groen'!$I:$I,$J16),""),""),"") | H16: =IFERROR(IF($J16>0,IF(INDEX('Invullen groen'!$J:$J,$J16)<>0,INDEX('Invullen groen'!$J:$J,$J16),""),""),"") | I16: =IFERROR(IF($J16>0,IF(INDEX('Invullen groen'!$K:$K,$J16)<>0,INDEX('Invullen groen'!$K:$K,$J16),""),""),"") | J16: =IFERROR(MATCH(ROW()-4,'Invullen groen'!$P$17:$P$272,0)+16,0)
... A239: =IFERROR(IF($J239>0,ROW()-4,""),"") | B239: =IFERROR(IF($J239>0,INDEX('Invullen groen'!$A:$A,$J239),""),"") | C239: =IFERROR(IF($J239>0,INDEX('Invullen groen'!$C:$C,$J239),""),"") | D239: =IFERROR(IF($J239>0,INDEX('Invullen groen'!$D:$D,$J239),""),"") | E239: =IFERROR(IF($J239>0,INDEX('Invullen groen'!$G:$G,$J239),""),"") | F239: =IFERROR(IF($J239>0,IF(INDEX('Invullen groen'!$H:$H,$J239)<>0,INDEX('Invullen groen'!$H:$H,$J239),""),""),"") | G239: =IFERROR(IF($J239>0,IF(INDEX('Invullen groen'!$I:$I,$J239)<>0,INDEX('Invullen groen'!$I:$I,$J239),""),""),"") | H239: =IFERROR(IF($J239>0,IF(INDEX('Invullen groen'!$J:$J,$J239)<>0,INDEX('Invullen groen'!$J:$J,$J239),""),""),"") | I239: =IFERROR(IF($J239>0,IF(INDEX('Invullen groen'!$K:$K,$J239)<>0,INDEX('Invullen groen'!$K:$K,$J239),""),""),"") | J239: =IFERROR(MATCH(ROW()-4,'Invullen groen'!$P$17:$P$272,0)+16,0)
A241: Totaal lasten | F241: =SUMIF('Invullen groen'!Q17:Q272,">0",'Invullen groen'!Q17:Q272) | G241: =SUMIF('Invullen groen'!Q17:Q272,">0",'Invullen groen'!I17:I272) | H241: =SUMIF('Invullen groen'!Q17:Q272,">0",'Invullen groen'!J17:J272) | I241: =SUMIF('Invullen groen'!Q17:Q272,">0",'Invullen groen'!K17:K272)
A242: Totaal baten | F242: =SUMIF('Invullen groen'!R17:R272,"<>0",'Invullen groen'!R17:R272)
A243: Saldo (lasten + baten) | F243: =F241+F242 | G243: =G241 | H243: =H241 | I243: =I241
A245: Automatisch bijgewerkt vanuit tabblad 'Invullen groen' — geen invoer vereist

Sheet Samenvatting
A1: Samenvatting per programma
A2: ='Invullen groen'!A4
A4: Programma | B4: Lasten | C4: Baten | D4: Saldo | E4: MJR 2027 | F4: MJR 2028 | G4: MJR 2029
A5: Bestuur en Ondersteuning | B5: =SUMPRODUCT((LOWER('Invullen groen'!A17:A74)="bestuur en ondersteuning")*('Invullen groen'!H17:H74>0)*'Invullen groen'!H17:H74) | C5: =SUMPRODUCT((LOWER('Invullen groen'!A17:A74)="bestuur en ondersteuning")*('Invullen groen'!H17:H74<0)*'Invullen groen'!H17:H74) | D5: =B5+C5 | E5: =SUMPRODUCT((LOWER('Invullen groen'!A17:A74)="bestuur en ondersteuning")*IFERROR('Invullen groen'!I17:I74*1,0)) | F5: =SUMPRODUCT((LOWER('Invullen groen'!A17:A74)="bestuur en ondersteuning")*IFERROR('Invullen groen'!J17:J74*1,0)) | G5: =SUMPRODUCT((LOWER('Invullen groen'!A17:A74)="bestuur en ondersteuning")*IFERROR('Invullen groen'!K17:K74*1,0))
A6: Veiligheid | B6: =SUMPRODUCT((LOWER('Invullen groen'!A17:A74)="veiligheid")*('Invullen groen'!H17:H74>0)*'Invullen groen'!H17:H74) | C6: =SUMPRODUCT((LOWER('Invullen groen'!A17:A74)="veiligheid")*('Invullen groen'!H17:H74<0)*'Invullen groen'!H17:H74) | D6: =B6+C6 | E6: =SUMPRODUCT((LOWER('Invullen groen'!A17:A74)="veiligheid")*IFERROR('Invullen groen'!I17:I74*1,0)) | F6: =SUMPRODUCT((LOWER('Invullen groen'!A17:A74)="veiligheid")*IFERROR('Invullen groen'!J17:J74*1,0)) | G6: =SUMPRODUCT((LOWER('Invullen groen'!A17:A74)="veiligheid")*IFERROR('Invullen groen'!K17:K74*1,0))
A7: Verkeer, Vervoer en Waterstaat | B7: =SUMPRODUCT((LOWER('Invullen groen'!A17:A74)="verkeer, vervoer en waterstaat")*('Invullen groen'!H17:H74>0)*'Invullen groen'!H17:H74) | C7: =SUMPRODUCT((LOWER('Invullen groen'!A17:A74)="verkeer, vervoer en waterstaat")*('Invullen groen'!H17:H74<0)*'Invullen groen'!H17:H74) | D7: =B7+C7 | E7: =SUMPRODUCT((LOWER('Invullen groen'!A17:A74)="verkeer, vervoer en waterstaat")*IFERROR('Invullen groen'!I17:I74*1,0)) | F7: =SUMPRODUCT((LOWER('Invullen groen'!A17:A74)="verkeer, vervoer en waterstaat")*IFERROR('Invullen groen'!J17:J74*1,0)) | G7: =SUMPRODUCT((LOWER('Invullen groen'!A17:A74)="verkeer, vervoer en waterstaat")*IFERROR('Invullen groen'!K17:K74*1,0))
A8: Economie | B8: =SUMPRODUCT((LOWER('Invullen groen'!A17:A74)="economie")*('Invullen groen'!H17:H74>0)*'Invullen groen'!H17:H74) | C8: =SUMPRODUCT((LOWER('Invullen groen'!A17:A74)="economie")*('Invullen groen'!H17:H74<0)*'Invullen groen'!H17:H74) | D8: =B8+C8 | E8: =SUMPRODUCT((LOWER('Invullen groen'!A17:A74)="economie")*IFERROR('Invullen groen'!I17:I74*1,0)) | F8: =SUMPRODUCT((LOWER('Invullen groen'!A17:A74)="economie")*IFERROR('Invullen groen'!J17:J74*1,0)) | G8: =SUMPRODUCT((LOWER('Invullen groen'!A17:A74)="economie")*IFERROR('Invullen groen'!K17:K74*1,0))
A9: Onderwijs | B9: =SUMPRODUCT((LOWER('Invullen groen'!A17:A74)="onderwijs")*('Invullen groen'!H17:H74>0)*'Invullen groen'!H17:H74) | C9: =SUMPRODUCT((LOWER('Invullen groen'!A17:A74)="onderwijs")*('Invullen groen'!H17:H74<0)*'Invullen groen'!H17:H74) | D9: =B9+C9 | E9: =SUMPRODUCT((LOWER('Invullen groen'!A17:A74)="onderwijs")*IFERROR('Invullen groen'!I17:I74*1,0)) | F9: =SUMPRODUCT((LOWER('Invullen groen'!A17:A74)="onderwijs")*IFERROR('Invullen groen'!J17:J74*1,0)) | G9: =SUMPRODUCT((LOWER('Invullen groen'!A17:A74)="onderwijs")*IFERROR('Invullen groen'!K17:K74*1,0))
A10: Sport, Cultuur en Recreatie | B10: =SUMPRODUCT((LOWER('Invullen groen'!A17:A74)="sport, cultuur en recreatie")*('Invullen groen'!H17:H74>0)*'Invullen groen'!H17:H74) | C10: =SUMPRODUCT((LOWER('Invullen groen'!A17:A74)="sport, cultuur en recreatie")*('Invullen groen'!H17:H74<0)*'Invullen groen'!H17:H74) | D10: =B10+C10 | E10: =SUMPRODUCT((LOWER('Invullen groen'!A17:A74)="sport, cultuur en recreatie")*IFERROR('Invullen groen'!I17:I74*1,0)) | F10: =SUMPRODUCT((LOWER('Invullen groen'!A17:A74)="sport, cultuur en recreatie")*IFERROR('Invullen groen'!J17:J74*1,0)) | G10: =SUMPRODUCT((LOWER('Invullen groen'!A17:A74)="sport, cultuur en recreatie")*IFERROR('Invullen groen'!K17:K74*1,0))
A11: Sociaal Domein | B11: =SUMPRODUCT((LOWER('Invullen groen'!A17:A74)="sociaal domein")*('Invullen groen'!H17:H74>0)*'Invullen groen'!H17:H74) | C11: =SUMPRODUCT((LOWER('Invullen groen'!A17:A74)="sociaal domein")*('Invullen groen'!H17:H74<0)*'Invullen groen'!H17:H74) | D11: =B11+C11 | E11: =SUMPRODUCT((LOWER('Invullen groen'!A17:A74)="sociaal domein")*IFERROR('Invullen groen'!I17:I74*1,0)) | F11: =SUMPRODUCT((LOWER('Invullen groen'!A17:A74)="sociaal domein")*IFERROR('Invullen groen'!J17:J74*1,0)) | G11: =SUMPRODUCT((LOWER('Invullen groen'!A17:A74)="sociaal domein")*IFERROR('Invullen groen'!K17:K74*1,0))
A12: Volksgezondheid en Milieu | B12: =SUMPRODUCT((LOWER('Invullen groen'!A17:A74)="volksgezondheid en milieu")*('Invullen groen'!H17:H74>0)*'Invullen groen'!H17:H74) | C12: =SUMPRODUCT((LOWER('Invullen groen'!A17:A74)="volksgezondheid en milieu")*('Invullen groen'!H17:H74<0)*'Invullen groen'!H17:H74) | D12: =B12+C12 | E12: =SUMPRODUCT((LOWER('Invullen groen'!A17:A74)="volksgezondheid en milieu")*IFERROR('Invullen groen'!I17:I74*1,0)) | F12: =SUMPRODUCT((LOWER('Invullen groen'!A17:A74)="volksgezondheid en milieu")*IFERROR('Invullen groen'!J17:J74*1,0)) | G12: =SUMPRODUCT((LOWER('Invullen groen'!A17:A74)="volksgezondheid en milieu")*IFERROR('Invullen groen'!K17:K74*1,0))
A13: Volkshuisvesting, RO en Stedelijke Vernieuwing | B13: =SUMPRODUCT((LOWER('Invullen groen'!A17:A74)="volkshuisv., ro en stedelijke vernieuwing")*('Invullen groen'!H17:H74>0)*'Invullen groen'!H17:H74) | C13: =SUMPRODUCT((LOWER('Invullen groen'!A17:A74)="volkshuisv., ro en stedelijke vernieuwing")*('Invullen groen'!H17:H74<0)*'Invullen groen'!H17:H74) | D13: =B13+C13 | E13: =SUMPRODUCT((LOWER('Invullen groen'!A17:A74)="volkshuisv., ro en stedelijke vernieuwing")*IFERROR('Invullen groen'!I17:I74*1,0)) | F13: =SUMPRODUCT((LOWER('Invullen groen'!A17:A74)="volkshuisv., ro en stedelijke vernieuwing")*IFERROR('Invullen groen'!J17:J74*1,0)) | G13: =SUMPRODUCT((LOWER('Invullen groen'!A17:A74)="volkshuisv., ro en stedelijke vernieuwing")*IFERROR('Invullen groen'!K17:K74*1,0))
A14: Totaal begrotingswijziging | B14: =SUM(B5:B13) | C14: =SUM(C5:C13) | D14: =SUM(D5:D13) | E14: =SUM(E5:E13) | F14: =SUM(F5:F13) | G14: =SUM(G5:G13)
A15: Financiële foto
A16: Begin saldo financiële foto (vóór wijziging)
A17: Eind saldo financiële foto (ná wijziging) | B17: =B16+B14 | C17: =C16+C14 | D17: =D16+D14 | E17: =E16+E14 | F17: =F16+F14 | G17: =G16+G14
A18: Begin saldo: handmatig invullen vanuit de meest recente financiële foto (vóór de wijziging) | − = positief saldo
A20: Controle exploitatie (moet 0 zijn) | B20: =IFERROR('Invullen groen'!H112,0)

Sheet Dekking
A1: Dekkingsoverzicht begrotingswijziging
A2: ='Invullen groen'!A4
A4: WAARVOOR — Uitgaven / Lasten | F4: WAARMEE GEDEKT — Baten / Onttrekkingen
A5: Nr. | B5: Programma | C5: Omschrijving | D5: Bedrag | F5: Programma | G5: Omschrijving / bron | H5: Bedrag
A6: =IFERROR(IF('Invullen groen'!H17>0,1,""),"") | B6: =IFERROR(IF('Invullen groen'!H17>0,'Invullen groen'!A17,""),"") | C6: =IFERROR(IF('Invullen groen'!H17>0,'Invullen groen'!G17,""),"") | D6: =IFERROR(IF('Invullen groen'!H17>0,'Invullen groen'!H17,""),"") | F6: =IFERROR(IF('Invullen groen'!H122<>0,'Invullen groen'!A122,""),"") | G6: =IFERROR(IF('Invullen groen'!H122<>0,'Invullen groen'!G122,""),"") | H6: =IFERROR(IF('Invullen groen'!H122<>0,'Invullen groen'!H122,""),"")
A7: =IFERROR(IF('Invullen groen'!H18>0,2,""),"") | B7: =IFERROR(IF('Invullen groen'!H18>0,'Invullen groen'!A18,""),"") | C7: =IFERROR(IF('Invullen groen'!H18>0,'Invullen groen'!G18,""),"") | D7: =IFERROR(IF('Invullen groen'!H18>0,'Invullen groen'!H18,""),"") | F7: =IFERROR(IF('Invullen groen'!H123<>0,'Invullen groen'!A123,""),"") | G7: =IFERROR(IF('Invullen groen'!H123<>0,'Invullen groen'!G123,""),"") | H7: =IFERROR(IF('Invullen groen'!H123<>0,'Invullen groen'!H123,""),"")
A8: =IFERROR(IF('Invullen groen'!H19>0,3,""),"") | B8: =IFERROR(IF('Invullen groen'!H19>0,'Invullen groen'!A19,""),"") | C8: =IFERROR(IF('Invullen groen'!H19>0,'Invullen groen'!G19,""),"") | D8: =IFERROR(IF('Invullen groen'!H19>0,'Invullen groen'!H19,""),"") | F8: =IFERROR(IF('Invullen groen'!H124<>0,'Invullen groen'!A124,""),"") | G8: =IFERROR(IF('Invullen groen'!H124<>0,'Invullen groen'!G124,""),"") | H8: =IFERROR(IF('Invullen groen'!H124<>0,'Invullen groen'!H124,""),"")
A9: =IFERROR(IF('Invullen groen'!H20>0,4,""),"") | B9: =IFERROR(IF('Invullen groen'!H20>0,'Invullen groen'!A20,""),"") | C9: =IFERROR(IF('Invullen groen'!H20>0,'Invullen groen'!G20,""),"") | D9: =IFERROR(IF('Invullen groen'!H20>0,'Invullen groen'!H20,""),"") | F9: =IFERROR(IF('Invullen groen'!H125<>0,'Invullen groen'!A125,""),"") | G9: =IFERROR(IF('Invullen groen'!H125<>0,'Invullen groen'!G125,""),"") | H9: =IFERROR(IF('Invullen groen'!H125<>0,'Invullen groen'!H125,""),"")
A10: =IFERROR(IF('Invullen groen'!H21>0,5,""),"") | B10: =IFERROR(IF('Invullen groen'!H21>0,'Invullen groen'!A21,""),"") | C10: =IFERROR(IF('Invullen groen'!H21>0,'Invullen groen'!G21,""),"") | D10: =IFERROR(IF('Invullen groen'!H21>0,'Invullen groen'!H21,""),"") | F10: =IFERROR(IF('Invullen groen'!H126<>0,'Invullen groen'!A126,""),"") | G10: =IFERROR(IF('Invullen groen'!H126<>0,'Invullen groen'!G126,""),"") | H10: =IFERROR(IF('Invullen groen'!H126<>0,'Invullen groen'!H126,""),"")
A11: =IFERROR(IF('Invullen groen'!H22>0,6,""),"") | B11: =IFERROR(IF('Invullen groen'!H22>0,'Invullen groen'!A22,""),"") | C11: =IFERROR(IF('Invullen groen'!H22>0,'Invullen groen'!G22,""),"") | D11: =IFERROR(IF('Invullen groen'!H22>0,'Invullen groen'!H22,""),"") | F11: =IFERROR(IF('Invullen groen'!H127<>0,'Invullen groen'!A127,""),"") | G11: =IFERROR(IF('Invullen groen'!H127<>0,'Invullen groen'!G127,""),"") | H11: =IFERROR(IF('Invullen groen'!H127<>0,'Invullen groen'!H127,""),"")
A12: =IFERROR(IF('Invullen groen'!H23>0,7,""),"") | B12: =IFERROR(IF('Invullen groen'!H23>0,'Invullen groen'!A23,""),"") | C12: =IFERROR(IF('Invullen groen'!H23>0,'Invullen groen'!G23,""),"") | D12: =IFERROR(IF('Invullen groen'!H23>0,'Invullen groen'!H23,""),"") | F12: =IFERROR(IF('Invullen groen'!H128<>0,'Invullen groen'!A128,""),"") | G12: =IFERROR(IF('Invullen groen'!H128<>0,'Invullen groen'!G128,""),"") | H12: =IFERROR(IF('Invullen groen'!H128<>0,'Invullen groen'!H128,""),"")
A13: =IFERROR(IF('Invullen groen'!H24>0,8,""),"") | B13: =IFERROR(IF('Invullen groen'!H24>0,'Invullen groen'!A24,""),"") | C13: =IFERROR(IF('Invullen groen'!H24>0,'Invullen groen'!G24,""),"") | D13: =IFERROR(IF('Invullen groen'!H24>0,'Invullen groen'!H24,""),"") | F13: =IFERROR(IF('Invullen groen'!H129<>0,'Invullen groen'!A129,""),"") | G13: =IFERROR(IF('Invullen groen'!H129<>0,'Invullen groen'!G129,""),"") | H13: =IFERROR(IF('Invullen groen'!H129<>0,'Invullen groen'!H129,""),"")
A14: =IFERROR(IF('Invullen groen'!H25>0,9,""),"") | B14: =IFERROR(IF('Invullen groen'!H25>0,'Invullen groen'!A25,""),"") | C14: =IFERROR(IF('Invullen groen'!H25>0,'Invullen groen'!G25,""),"") | D14: =IFERROR(IF('Invullen groen'!H25>0,'Invullen groen'!H25,""),"") | F14: =IFERROR(IF('Invullen groen'!H130<>0,'Invullen groen'!A130,""),"") | G14: =IFERROR(IF('Invullen groen'!H130<>0,'Invullen groen'!G130,""),"") | H14: =IFERROR(IF('Invullen groen'!H130<>0,'Invullen groen'!H130,""),"")
A15: =IFERROR(IF('Invullen groen'!H26>0,10,""),"") | B15: =IFERROR(IF('Invullen groen'!H26>0,'Invullen groen'!A26,""),"") | C15: =IFERROR(IF('Invullen groen'!H26>0,'Invullen groen'!G26,""),"") | D15: =IFERROR(IF('Invullen groen'!H26>0,'Invullen groen'!H26,""),"") | F15: =IFERROR(IF('Invullen groen'!H131<>0,'Invullen groen'!A131,""),"") | G15: =IFERROR(IF('Invullen groen'!H131<>0,'Invullen groen'!G131,""),"") | H15: =IFERROR(IF('Invullen groen'!H131<>0,'Invullen groen'!H131,""),"")
A16: =IFERROR(IF('Invullen groen'!H27>0,11,""),"") | B16: =IFERROR(IF('Invullen groen'!H27>0,'Invullen groen'!A27,""),"") | C16: =IFERROR(IF('Invullen groen'!H27>0,'Invullen groen'!G27,""),"") | D16: =IFERROR(IF('Invullen groen'!H27>0,'Invullen groen'!H27,""),"") | F16: =IFERROR(IF('Invullen groen'!H171<>0,'Invullen groen'!A171,""),"") | G16: =IFERROR(IF('Invullen groen'!H171<>0,'Invullen groen'!G171,""),"") | H16: =IFERROR(IF('Invullen groen'!H171<>0,'Invullen groen'!H171,""),"")
A17: =IFERROR(IF('Invullen groen'!H28>0,12,""),"") | B17: =IFERROR(IF('Invullen groen'!H28>0,'Invullen groen'!A28,""),"") | C17: =IFERROR(IF('Invullen groen'!H28>0,'Invullen groen'!G28,""),"") | D17: =IFERROR(IF('Invullen groen'!H28>0,'Invullen groen'!H28,""),"") | F17: =IFERROR(IF('Invullen groen'!H172<>0,'Invullen groen'!A172,""),"") | G17: =IFERROR(IF('Invullen groen'!H172<>0,'Invullen groen'!G172,""),"") | H17: =IFERROR(IF('Invullen groen'!H172<>0,'Invullen groen'!H172,""),"")
A18: =IFERROR(IF('Invullen groen'!H29>0,13,""),"") | B18: =IFERROR(IF('Invullen groen'!H29>0,'Invullen groen'!A29,""),"") | C18: =IFERROR(IF('Invullen groen'!H29>0,'Invullen groen'!G29,""),"") | D18: =IFERROR(IF('Invullen groen'!H29>0,'Invullen groen'!H29,""),"") | F18: =IFERROR(IF('Invullen groen'!H173<>0,'Invullen groen'!A173,""),"") | G18: =IFERROR(IF('Invullen groen'!H173<>0,'Invullen groen'!G173,""),"") | H18: =IFERROR(IF('Invullen groen'!H173<>0,'Invullen groen'!H173,""),"")
A19: =IFERROR(IF('Invullen groen'!H30>0,14,""),"") | B19: =IFERROR(IF('Invullen groen'!H30>0,'Invullen groen'!A30,""),"") | C19: =IFERROR(IF('Invullen groen'!H30>0,'Invullen groen'!G30,""),"") | D19: =IFERROR(IF('Invullen groen'!H30>0,'Invullen groen'!H30,""),"") | F19: =IFERROR(IF('Invullen groen'!H174<>0,'Invullen groen'!A174,""),"") | G19: =IFERROR(IF('Invullen groen'!H174<>0,'Invullen groen'!G174,""),"") | H19: =IFERROR(IF('Invullen groen'!H174<>0,'Invullen groen'!H174,""),"")
A20: =IFERROR(IF('Invullen groen'!H31>0,15,""),"") | B20: =IFERROR(IF('Invullen groen'!H31>0,'Invullen groen'!A31,""),"") | C20: =IFERROR(IF('Invullen groen'!H31>0,'Invullen groen'!G31,""),"") | D20: =IFERROR(IF('Invullen groen'!H31>0,'Invullen groen'!H31,""),"") | F20: =IFERROR(IF('Invullen groen'!H175<>0,'Invullen groen'!A175,""),"") | G20: =IFERROR(IF('Invullen groen'!H175<>0,'Invullen groen'!G175,""),"") | H20: =IFERROR(IF('Invullen groen'!H175<>0,'Invullen groen'!H175,""),"")
A21: =IFERROR(IF('Invullen groen'!H32>0,16,""),"") | B21: =IFERROR(IF('Invullen groen'!H32>0,'Invullen groen'!A32,""),"") | C21: =IFERROR(IF('Invullen groen'!H32>0,'Invullen groen'!G32,""),"") | D21: =IFERROR(IF('Invullen groen'!H32>0,'Invullen groen'!H32,""),"") | F21: =IFERROR(IF('Invullen groen'!H176<>0,'Invullen groen'!A176,""),"") | G21: =IFERROR(IF('Invullen groen'!H176<>0,'Invullen groen'!G176,""),"") | H21: =IFERROR(IF('Invullen groen'!H176<>0,'Invullen groen'!H176,""),"")
A22: =IFERROR(IF('Invullen groen'!H33>0,17,""),"") | B22: =IFERROR(IF('Invullen groen'!H33>0,'Invullen groen'!A33,""),"") | C22: =IFERROR(IF('Invullen groen'!H33>0,'Invullen groen'!G33,""),"") | D22: =IFERROR(IF('Invullen groen'!H33>0,'Invullen groen'!H33,""),"") | F22: =IFERROR(IF('Invullen groen'!H177<>0,'Invullen groen'!A177,""),"") | G22: =IFERROR(IF('Invullen groen'!H177<>0,'Invullen groen'!G177,""),"") | H22: =IFERROR(IF('Invullen groen'!H177<>0,'Invullen groen'!H177,""),"")
A23: =IFERROR(IF('Invullen groen'!H34>0,18,""),"") | B23: =IFERROR(IF('Invullen groen'!H34>0,'Invullen groen'!A34,""),"") | C23: =IFERROR(IF('Invullen groen'!H34>0,'Invullen groen'!G34,""),"") | D23: =IFERROR(IF('Invullen groen'!H34>0,'Invullen groen'!H34,""),"") | F23: =IFERROR(IF('Invullen groen'!H178<>0,'Invullen groen'!A178,""),"") | G23: =IFERROR(IF('Invullen groen'!H178<>0,'Invullen groen'!G178,""),"") | H23: =IFERROR(IF('Invullen groen'!H178<>0,'Invullen groen'!H178,""),"")
A24: =IFERROR(IF('Invullen groen'!H35>0,19,""),"") | B24: =IFERROR(IF('Invullen groen'!H35>0,'Invullen groen'!A35,""),"") | C24: =IFERROR(IF('Invullen groen'!H35>0,'Invullen groen'!G35,""),"") | D24: =IFERROR(IF('Invullen groen'!H35>0,'Invullen groen'!H35,""),"") | F24: =IFERROR(IF('Invullen groen'!H179<>0,'Invullen groen'!A179,""),"") | G24: =IFERROR(IF('Invullen groen'!H179<>0,'Invullen groen'!G179,""),"") | H24: =IFERROR(IF('Invullen groen'!H179<>0,'Invullen groen'!H179,""),"")
A25: =IFERROR(IF('Invullen groen'!H36>0,20,""),"") | B25: =IFERROR(IF('Invullen groen'!H36>0,'Invullen groen'!A36,""),"") | C25: =IFERROR(IF('Invullen groen'!H36>0,'Invullen groen'!G36,""),"") | D25: =IFERROR(IF('Invullen groen'!H36>0,'Invullen groen'!H36,""),"") | F25: =IFERROR(IF('Invullen groen'!H180<>0,'Invullen groen'!A180,""),"") | G25: =IFERROR(IF('Invullen groen'!H180<>0,'Invullen groen'!G180,""),"") | H25: =IFERROR(IF('Invullen groen'!H180<>0,'Invullen groen'!H180,""),"")
A26: =IFERROR(IF('Invullen groen'!H37>0,21,""),"") | B26: =IFERROR(IF('Invullen groen'!H37>0,'Invullen groen'!A37,""),"") | C26: =IFERROR(IF('Invullen groen'!H37>0,'Invullen groen'!G37,""),"") | D26: =IFERROR(IF('Invullen groen'!H37>0,'Invullen groen'!H37,""),"") | F26: =IFERROR(IF('Invullen groen'!H181<>0,'Invullen groen'!A181,""),"") | G26: =IFERROR(IF('Invullen groen'!H181<>0,'Invullen groen'!G181,""),"") | H26: =IFERROR(IF('Invullen groen'!H181<>0,'Invullen groen'!H181,""),"")
A27: =IFERROR(IF('Invullen groen'!H38>0,22,""),"") | B27: =IFERROR(IF('Invullen groen'!H38>0,'Invullen groen'!A38,""),"") | C27: =IFERROR(IF('Invullen groen'!H38>0,'Invullen groen'!G38,""),"") | D27: =IFERROR(IF('Invullen groen'!H38>0,'Invullen groen'!H38,""),"") | F27: =IFERROR(IF('Invullen groen'!H220<>0,'Invullen groen'!A220,""),"") | G27: =IFERROR(IF('Invullen groen'!H220<>0,'Invullen groen'!G220,""),"") | H27: =IFERROR(IF('Invullen groen'!H220<>0,'Invullen groen'!H220,""),"")
A28: =IFERROR(IF('Invullen groen'!H39>0,23,""),"") | B28: =IFERROR(IF('Invullen groen'!H39>0,'Invullen groen'!A39,""),"") | C28: =IFERROR(IF('Invullen groen'!H39>0,'Invullen groen'!G39,""),"") | D28: =IFERROR(IF('Invullen groen'!H39>0,'Invullen groen'!H39,""),"") | F28: =IFERROR(IF('Invullen groen'!H221<>0,'Invullen groen'!A221,""),"") | G28: =IFERROR(IF('Invullen groen'!H221<>0,'Invullen groen'!G221,""),"") | H28: =IFERROR(IF('Invullen groen'!H221<>0,'Invullen groen'!H221,""),"")
A29: =IFERROR(IF('Invullen groen'!H40>0,24,""),"") | B29: =IFERROR(IF('Invullen groen'!H40>0,'Invullen groen'!A40,""),"") | C29: =IFERROR(IF('Invullen groen'!H40>0,'Invullen groen'!G40,""),"") | D29: =IFERROR(IF('Invullen groen'!H40>0,'Invullen groen'!H40,""),"") | F29: =IFERROR(IF('Invullen groen'!H222<>0,'Invullen groen'!A222,""),"") | G29: =IFERROR(IF('Invullen groen'!H222<>0,'Invullen groen'!G222,""),"") | H29: =IFERROR(IF('Invullen groen'!H222<>0,'Invullen groen'!H222,""),"")
A30: =IFERROR(IF('Invullen groen'!H41>0,25,""),"") | B30: =IFERROR(IF('Invullen groen'!H41>0,'Invullen groen'!A41,""),"") | C30: =IFERROR(IF('Invullen groen'!H41>0,'Invullen groen'!G41,""),"") | D30: =IFERROR(IF('Invullen groen'!H41>0,'Invullen groen'!H41,""),"") | F30: =IFERROR(IF('Invullen groen'!H223<>0,'Invullen groen'!A223,""),"") | G30: =IFERROR(IF('Invullen groen'!H223<>0,'Invullen groen'!G223,""),"") | H30: =IFERROR(IF('Invullen groen'!H223<>0,'Invullen groen'!H223,""),"")
A31: =IFERROR(IF('Invullen groen'!H42>0,26,""),"") | B31: =IFERROR(IF('Invullen groen'!H42>0,'Invullen groen'!A42,""),"") | C31: =IFERROR(IF('Invullen groen'!H42>0,'Invullen groen'!G42,""),"") | D31: =IFERROR(IF('Invullen groen'!H42>0,'Invullen groen'!H42,""),"") | F31: =IFERROR(IF('Invullen groen'!H224<>0,'Invullen groen'!A224,""),"") | G31: =IFERROR(IF('Invullen groen'!H224<>0,'Invullen groen'!G224,""),"") | H31: =IFERROR(IF('Invullen groen'!H224<>0,'Invullen groen'!H224,""),"")
A32: =IFERROR(IF('Invullen groen'!H43>0,27,""),"") | B32: =IFERROR(IF('Invullen groen'!H43>0,'Invullen groen'!A43,""),"") | C32: =IFERROR(IF('Invullen groen'!H43>0,'Invullen groen'!G43,""),"") | D32: =IFERROR(IF('Invullen groen'!H43>0,'Invullen groen'!H43,""),"") | F32: =IFERROR(IF('Invullen groen'!H225<>0,'Invullen groen'!A225,""),"") | G32: =IFERROR(IF('Invullen groen'!H225<>0,'Invullen groen'!G225,""),"") | H32: =IFERROR(IF('Invullen groen'!H225<>0,'Invullen groen'!H225,""),"")
A33: =IFERROR(IF('Invullen groen'!H44>0,28,""),"") | B33: =IFERROR(IF('Invullen groen'!H44>0,'Invullen groen'!A44,""),"") | C33: =IFERROR(IF('Invullen groen'!H44>0,'Invullen groen'!G44,""),"") | D33: =IFERROR(IF('Invullen groen'!H44>0,'Invullen groen'!H44,""),"") | F33: =IFERROR(IF('Invullen groen'!H226<>0,'Invullen groen'!A226,""),"") | G33: =IFERROR(IF('Invullen groen'!H226<>0,'Invullen groen'!G226,""),"") | H33: =IFERROR(IF('Invullen groen'!H226<>0,'Invullen groen'!H226,""),"")
A34: =IFERROR(IF('Invullen groen'!H45>0,29,""),"") | B34: =IFERROR(IF('Invullen groen'!H45>0,'Invullen groen'!A45,""),"") | C34: =IFERROR(IF('Invullen groen'!H45>0,'Invullen groen'!G45,""),"") | D34: =IFERROR(IF('Invullen groen'!H45>0,'Invullen groen'!H45,""),"") | F34: =IFERROR(IF('Invullen groen'!H227<>0,'Invullen groen'!A227,""),"") | G34: =IFERROR(IF('Invullen groen'!H227<>0,'Invullen groen'!G227,""),"") | H34: =IFERROR(IF('Invullen groen'!H227<>0,'Invullen groen'!H227,""),"")
A35: =IFERROR(IF('Invullen groen'!H46>0,30,""),"") | B35: =IFERROR(IF('Invullen groen'!H46>0,'Invullen groen'!A46,""),"") | C35: =IFERROR(IF('Invullen groen'!H46>0,'Invullen groen'!G46,""),"") | D35: =IFERROR(IF('Invullen groen'!H46>0,'Invullen groen'!H46,""),"") | F35: =IFERROR(IF('Invullen groen'!H228<>0,'Invullen groen'!A228,""),"") | G35: =IFERROR(IF('Invullen groen'!H228<>0,'Invullen groen'!G228,""),"") | H35: =IFERROR(IF('Invullen groen'!H228<>0,'Invullen groen'!H228,""),"")
A36: =IFERROR(IF('Invullen groen'!H47>0,31,""),"") | B36: =IFERROR(IF('Invullen groen'!H47>0,'Invullen groen'!A47,""),"") | C36: =IFERROR(IF('Invullen groen'!H47>0,'Invullen groen'!G47,""),"") | D36: =IFERROR(IF('Invullen groen'!H47>0,'Invullen groen'!H47,""),"") | F36: =IFERROR(IF('Invullen groen'!H229<>0,'Invullen groen'!A229,""),"") | G36: =IFERROR(IF('Invullen groen'!H229<>0,'Invullen groen'!G229,""),"") | H36: =IFERROR(IF('Invullen groen'!H229<>0,'Invullen groen'!H229,""),"")
A37: =IFERROR(IF('Invullen groen'!H48>0,32,""),"") | B37: =IFERROR(IF('Invullen groen'!H48>0,'Invullen groen'!A48,""),"") | C37: =IFERROR(IF('Invullen groen'!H48>0,'Invullen groen'!G48,""),"") | D37: =IFERROR(IF('Invullen groen'!H48>0,'Invullen groen'!H48,""),"") | F37: =IFERROR(IF('Invullen groen'!H230<>0,'Invullen groen'!A230,""),"") | G37: =IFERROR(IF('Invullen groen'!H230<>0,'Invullen groen'!G230,""),"") | H37: =IFERROR(IF('Invullen groen'!H230<>0,'Invullen groen'!H230,""),"")
A38: =IFERROR(IF('Invullen groen'!H49>0,33,""),"") | B38: =IFERROR(IF('Invullen groen'!H49>0,'Invullen groen'!A49,""),"") | C38: =IFERROR(IF('Invullen groen'!H49>0,'Invullen groen'!G49,""),"") | D38: =IFERROR(IF('Invullen groen'!H49>0,'Invullen groen'!H49,""),"")
A39: =IFERROR(IF('Invullen groen'!H50>0,34,""),"") | B39: =IFERROR(IF('Invullen groen'!H50>0,'Invullen groen'!A50,""),"") | C39: =IFERROR(IF('Invullen groen'!H50>0,'Invullen groen'!G50,""),"") | D39: =IFERROR(IF('Invullen groen'!H50>0,'Invullen groen'!H50,""),"")
A40: =IFERROR(IF('Invullen groen'!H51>0,35,""),"") | B40: =IFERROR(IF('Invullen groen'!H51>0,'Invullen groen'!A51,""),"") | C40: =IFERROR(IF('Invullen groen'!H51>0,'Invullen groen'!G51,""),"") | D40: =IFERROR(IF('Invullen groen'!H51>0,'Invullen groen'!H51,""),"")
A41: =IFERROR(IF('Invullen groen'!H52>0,36,""),"") | B41: =IFERROR(IF('Invullen groen'!H52>0,'Invullen groen'!A52,""),"") | C41: =IFERROR(IF('Invullen groen'!H52>0,'Invullen groen'!G52,""),"") | D41: =IFERROR(IF('Invullen groen'!H52>0,'Invullen groen'!H52,""),"")
A42: =IFERROR(IF('Invullen groen'!H53>0,37,""),"") | B42: =IFERROR(IF('Invullen groen'!H53>0,'Invullen groen'!A53,""),"") | C42: =IFERROR(IF('Invullen groen'!H53>0,'Invullen groen'!G53,""),"") | D42: =IFERROR(IF('Invullen groen'!H53>0,'Invullen groen'!H53,""),"")
A43: =IFERROR(IF('Invullen groen'!H54>0,38,""),"") | B43: =IFERROR(IF('Invullen groen'!H54>0,'Invullen groen'!A54,""),"") | C43: =IFERROR(IF('Invullen groen'!H54>0,'Invullen groen'!G54,""),"") | D43: =IFERROR(IF('Invullen groen'!H54>0,'Invullen groen'!H54,""),"")
A44: =IFERROR(IF('Invullen groen'!H55>0,39,""),"") | B44: =IFERROR(IF('Invullen groen'!H55>0,'Invullen groen'!A55,""),"") | C44: =IFERROR(IF('Invullen groen'!H55>0,'Invullen groen'!G55,""),"") | D44: =IFERROR(IF('Invullen groen'!H55>0,'Invullen groen'!H55,""),"")
A45: =IFERROR(IF('Invullen groen'!H56>0,40,""),"") | B45: =IFERROR(IF('Invullen groen'!H56>0,'Invullen groen'!A56,""),"") | C45: =IFERROR(IF('Invullen groen'!H56>0,'Invullen groen'!G56,""),"") | D45: =IFERROR(IF('Invullen groen'!H56>0,'Invullen groen'!H56,""),"")
A46: =IFERROR(IF('Invullen groen'!H57>0,41,""),"") | B46: =IFERROR(IF('Invullen groen'!H57>0,'Invullen groen'!A57,""),"") | C46: =IFERROR(IF('Invullen groen'!H57>0,'Invullen groen'!G57,""),"") | D46: =IFERROR(IF('Invullen groen'!H57>0,'Invullen groen'!H57,""),"")
A47: =IFERROR(IF('Invullen groen'!H58>0,42,""),"") | B47: =IFERROR(IF('Invullen groen'!H58>0,'Invullen groen'!A58,""),"") | C47: =IFERROR(IF('Invullen groen'!H58>0,'Invullen groen'!G58,""),"") | D47: =IFERROR(IF('Invullen groen'!H58>0,'Invullen groen'!H58,""),"")
A48: =IFERROR(IF('Invullen groen'!H59>0,43,""),"") | B48: =IFERROR(IF('Invullen groen'!H59>0,'Invullen groen'!A59,""),"") | C48: =IFERROR(IF('Invullen groen'!H59>0,'Invullen groen'!G59,""),"") | D48: =IFERROR(IF('Invullen groen'!H59>0,'Invullen groen'!H59,""),"")
A49: =IFERROR(IF('Invullen groen'!H60>0,44,""),"") | B49: =IFERROR(IF('Invullen groen'!H60>0,'Invullen groen'!A60,""),"") | C49: =IFERROR(IF('Invullen groen'!H60>0,'Invullen groen'!G60,""),"") | D49: =IFERROR(IF('Invullen groen'!H60>0,'Invullen groen'!H60,""),"")
A50: =IFERROR(IF('Invullen groen'!H61>0,45,""),"") | B50: =IFERROR(IF('Invullen groen'!H61>0,'Invullen groen'!A61,""),"") | C50: =IFERROR(IF('Invullen groen'!H61>0,'Invullen groen'!G61,""),"") | D50: =IFERROR(IF('Invullen groen'!H61>0,'Invullen groen'!H61,""),"")
A51: =IFERROR(IF('Invullen groen'!H62>0,46,""),"") | B51: =IFERROR(IF('Invullen groen'!H62>0,'Invullen groen'!A62,""),"") | C51: =IFERROR(IF('Invullen groen'!H62>0,'Invullen groen'!G62,""),"") | D51: =IFERROR(IF('Invullen groen'!H62>0,'Invullen groen'!H62,""),"")
A52: =IFERROR(IF('Invullen groen'!H63>0,47,""),"") | B52: =IFERROR(IF('Invullen groen'!H63>0,'Invullen groen'!A63,""),"") | C52: =IFERROR(IF('Invullen groen'!H63>0,'Invullen groen'!G63,""),"") | D52: =IFERROR(IF('Invullen groen'!H63>0,'Invullen groen'!H63,""),"")
A53: =IFERROR(IF('Invullen groen'!H64>0,48,""),"") | B53: =IFERROR(IF('Invullen groen'!H64>0,'Invullen groen'!A64,""),"") | C53: =IFERROR(IF('Invullen groen'!H64>0,'Invullen groen'!G64,""),"") | D53: =IFERROR(IF('Invullen groen'!H64>0,'Invullen groen'!H64,""),"")
A54: =IFERROR(IF('Invullen groen'!H65>0,49,""),"") | B54: =IFERROR(IF('Invullen groen'!H65>0,'Invullen groen'!A65,""),"") | C54: =IFERROR(IF('Invullen groen'!H65>0,'Invullen groen'!G65,""),"") | D54: =IFERROR(IF('Invullen groen'!H65>0,'Invullen groen'!H65,""),"")
A55: =IFERROR(IF('Invullen groen'!H66>0,50,""),"") | B55: =IFERROR(IF('Invullen groen'!H66>0,'Invullen groen'!A66,""),"") | C55: =IFERROR(IF('Invullen groen'!H66>0,'Invullen groen'!G66,""),"") | D55: =IFERROR(IF('Invullen groen'!H66>0,'Invullen groen'!H66,""),"")
A56: =IFERROR(IF('Invullen groen'!H67>0,51,""),"") | B56: =IFERROR(IF('Invullen groen'!H67>0,'Invullen groen'!A67,""),"") | C56: =IFERROR(IF('Invullen groen'!H67>0,'Invullen groen'!G67,""),"") | D56: =IFERROR(IF('Invullen groen'!H67>0,'Invullen groen'!H67,""),"")
A57: =IFERROR(IF('Invullen groen'!H68>0,52,""),"") | B57: =IFERROR(IF('Invullen groen'!H68>0,'Invullen groen'!A68,""),"") | C57: =IFERROR(IF('Invullen groen'!H68>0,'Invullen groen'!G68,""),"") | D57: =IFERROR(IF('Invullen groen'!H68>0,'Invullen groen'!H68,""),"")
A58: =IFERROR(IF('Invullen groen'!H69>0,53,""),"") | B58: =IFERROR(IF('Invullen groen'!H69>0,'Invullen groen'!A69,""),"") | C58: =IFERROR(IF('Invullen groen'!H69>0,'Invullen groen'!G69,""),"") | D58: =IFERROR(IF('Invullen groen'!H69>0,'Invullen groen'!H69,""),"")
A59: =IFERROR(IF('Invullen groen'!H70>0,54,""),"") | B59: =IFERROR(IF('Invullen groen'!H70>0,'Invullen groen'!A70,""),"") | C59: =IFERROR(IF('Invullen groen'!H70>0,'Invullen groen'!G70,""),"") | D59: =IFERROR(IF('Invullen groen'!H70>0,'Invullen groen'!H70,""),"")
A60: =IFERROR(IF('Invullen groen'!H71>0,55,""),"") | B60: =IFERROR(IF('Invullen groen'!H71>0,'Invullen groen'!A71,""),"") | C60: =IFERROR(IF('Invullen groen'!H71>0,'Invullen groen'!G71,""),"") | D60: =IFERROR(IF('Invullen groen'!H71>0,'Invullen groen'!H71,""),"")
A61: =IFERROR(IF('Invullen groen'!H72>0,56,""),"") | B61: =IFERROR(IF('Invullen groen'!H72>0,'Invullen groen'!A72,""),"") | C61: =IFERROR(IF('Invullen groen'!H72>0,'Invullen groen'!G72,""),"") | D61: =IFERROR(IF('Invullen groen'!H72>0,'Invullen groen'!H72,""),"")
A62: =IFERROR(IF('Invullen groen'!H73>0,57,""),"") | B62: =IFERROR(IF('Invullen groen'!H73>0,'Invullen groen'!A73,""),"") | C62: =IFERROR(IF('Invullen groen'!H73>0,'Invullen groen'!G73,""),"") | D62: =IFERROR(IF('Invullen groen'!H73>0,'Invullen groen'!H73,""),"")
A63: =IFERROR(IF('Invullen groen'!H74>0,58,""),"") | B63: =IFERROR(IF('Invullen groen'!H74>0,'Invullen groen'!A74,""),"") | C63: =IFERROR(IF('Invullen groen'!H74>0,'Invullen groen'!G74,""),"") | D63: =IFERROR(IF('Invullen groen'!H74>0,'Invullen groen'!H74,""),"")
A64: Totaal lasten | D64: =SUM(D6:D63) | F64: Totaal dekking / baten | H64: =SUM(H6:H37)
A65: =IF(D64+H64=0,"✓ Budgettair neutraal — saldo = 0","⚠ Niet budgettair neutraal: "&TEXT(D64+H64,"#.##0"))
A67: Lasten = positieve bedragen sectie A (Uitgaven) | Baten/Dekking = investeringen (sectie B), reserves (sectie C) en voorzieningen (sectie D)

Sheet Tabellen
A1: Grootb | B1: Omschrijving grootboeknummer | C1: htv | D1: omschrijving programma | E1: taakveld | F1: omschrijving taakveld | H1: Cat | I1: Omschr categorie | J1: Hulptabel kolom D
A2: 601001 | B2: kosten raad | D2: bestuur en ondersteuning | E2: T01 | F2: bestuur | H2: 41100 | I2: salarissen | J2: 0 | K2: bestuur en ondersteuning
A3: 601002 | B3: werkbudget griffie | D3: bestuur en ondersteuning | E3: T01 | F3: bestuur | H3: 41101 | I3: uitkeringen voormalig personeel | J3: 1 | K3: veiligheid
A4: 601003 | B4: rekenkamerfunctie | D4: bestuur en ondersteuning | E4: T01 | F4: bestuur | H4: 41102 | I4: sociale verzekeringswetten | J4: 2 | K4: verkeer, vervoer en waterstaat
A5: 601004 | B5: gemeentefinanciën | D5: bestuur en ondersteuning | E5: T01 | F5: bestuur | H5: 41103 | I5: sociale lasten voorgaande jaren | J5: 3 | K5: economie
A6: 601005 | B6: jeugdraad | D6: bestuur en ondersteuning | E6: T01 | F6: bestuur | H6: 41104 | I6: vergoedingen stagiares | J6: 4 | K6: onderwijs
A7: 601006 | B7: burgemeester | D7: bestuur en ondersteuning | E7: T01 | F7: bestuur | H7: 41105 | I7: corona salarissen | J7: 5 | K7: sport, cultuur en recreatie
A8: 601007 | B8: kosten voormalig b&w | D8: bestuur en ondersteuning | E8: T01 | F8: bestuur | H8: 42100 | I8: belastingen en heffingen | J8: 6 | K8: sociaal domein
A9: 601008 | B9: college van b&w | D9: bestuur en ondersteuning | E9: T01 | F9: bestuur | H9: 43100 | I9: grondaankopen | J9: 7 | K9: volksgezondheid en milieu
A10: 601009 | B10: sociaal-cultureel fonds | D10: bestuur en ondersteuning | E10: T01 | F10: bestuur | H10: 43200 | I10: uitbestede investeringen | J10: 8 | K10: volkshuisv., ro en stedelijke vernieuwing
A11: 601010 | B11: kosten representatie | D11: bestuur en ondersteuning | E11: T01 | F11: bestuur | H11: 43201 | I11: duurzame roerende goederen
A12: 601011 | B12: broodjes, bloemen ed | D12: bestuur en ondersteuning | E12: T01 | F12: bestuur | H12: 43299 | I12: overboeking uitbestede investeringen
A13: 601012 | B13: metropoolregio eindhoven | D13: bestuur en ondersteuning | E13: T01 | F13: bestuur | H13: 43301 | I13: pachten erfpacht ed
A14: 601013 | B14: stimuleringsfonds | D14: bestuur en ondersteuning | E14: T01 | F14: bestuur | H14: 43410 | I14: sociale verstrekkingen in natura
A15: 601014 | B15: regionale projecten | D15: bestuur en ondersteuning | E15: T01 | F15: bestuur | H15: 43411 | I15: corona soc verstrekking
A16: 601015 | B16: campus samenwerking | D16: bestuur en ondersteuning | E16: T01 | F16: bestuur | H16: 43511 | I16: inhuur personeel
A17: 601016 | B17: bestuurlijk platf sted gebied eindh | D17: bestuur en ondersteuning | E17: T01 | F17: bestuur | H17: 43512 | I17: corona inhuur personeel
A18: 601017 | B18: project voorzieningen sge | D18: bestuur en ondersteuning | E18: T01 | F18: bestuur | H18: 43801 | I18: gasverbruik
A19: 601018 | B19: challenge ontsluiting | D19: bestuur en ondersteuning | E19: T01 | F19: bestuur | H19: 43802 | I19: electriciteitsverbruik
A20: 601019 | B20: contributies/lidmaatschappen | D20: bestuur en ondersteuning | E20: T01 | F20: bestuur | H20: 43803 | I20: brandstoffen
A21: 601020 | B21: samenwerking best oirschot | D21: bestuur en ondersteuning | E21: T01 | F21: bestuur | H21: 43804 | I21: kosten algemene plannen
A22: 601901 | B22: directe toerek bestuur | D22: bestuur en ondersteuning | E22: T01 | F22: bestuur | H22: 43805 | I22: huurlasten
... A174: 613022 | B174: mutatie reserve t31 | D174: bestuur en ondersteuning | E174: T010 | F174: mutaties reserves | H174: 87501 | I174: verrekeningen
A175: 613023 | B175: mutatie reserve t32 | D175: bestuur en ondersteuning | E175: T010 | F175: mutaties reserves
A176: 613024 | B176: mutatie reserve t33 | D176: bestuur en ondersteuning | E176: T010 | F176: mutaties reserves
A177: 613025 | B177: mutatie reserve t34 | D177: bestuur en ondersteuning | E177: T010 | F177: mutaties reserves
A178: 613026 | B178: mutatie reserve t41 | D178: bestuur en ondersteuning | E178: T010 | F178: mutaties reserves
A179: 613027 | B179: mutatie reserve t42 | D179: bestuur en ondersteuning | E179: T010 | F179: mutaties reserves
A180: 613028 | B180: mutatie reserve t43 | D180: bestuur en ondersteuning | E180: T010 | F180: mutaties reserves
A181: 613029 | B181: mutatie reserve t51 | D181: bestuur en ondersteuning | E181: T010 | F181: mutaties reserves
A182: 613030 | B182: mutatie reserve t52 | D182: bestuur en ondersteuning | E182: T010 | F182: mutaties reserves
A183: 613031 | B183: mutatie reserve t53 | D183: bestuur en ondersteuning | E183: T010 | F183: mutaties reserves
A184: 613032 | B184: mutatie reserve t54 | D184: bestuur en ondersteuning | E184: T010 | F184: mutaties reserves
A185: 613033 | B185: mutatie reserve t55 | D185: bestuur en ondersteuning | E185: T010 | F185: mutaties reserves
A186: 613034 | B186: mutatie reserve t56 | D186: bestuur en ondersteuning | E186: T010 | F186: mutaties reserves
... A695: 696901 | B695: directe toerek jeugdreclassering | D695: sociaal domein | E695: T6822 | F695: jeugdreclassering
